Workbook
Name _\a: #REF!
Name _\b: #REF!
Name _\c: #REF!
Name _\d: #REF!
Name _\g: #REF!
Name _\p: #REF!
Name _\r: #REF!
Name _\t: #REF!
Name _\x: #REF!
Name __\a: #REF!
Name __\b: #REF!
Name __\c: #REF!
Name __\d: #REF!
Name __\g: #REF!
Name __\p: #REF!
Name __\r: #REF!
Name __\t: #REF!
Name __\x: #REF!
Name ___\a: #REF!
Name ___\b: #REF!
Name ___\c: #REF!
Name ___\d: #REF!
Name ___\g: #REF!
Name ___\p: #REF!
Name ___\r: #REF!
Name ___\t: #REF!
Name ___\x: #REF!
Name AwalES: #REF!
Name AwalES: #REF!
Name AwalES: #REF!
Name CACCORD: #REF!
Name CACCORD: #REF!
Name CACCORD: #REF!
Name CBENZ: #REF!
Name CBENZ: #REF!
Name CBENZ: #REF!
Name CBMW_520: #REF!
Name CBMW_520: #REF!
Name CBMW_520: #REF!
Name CCAKRA: #REF!
Name CCAKRA: #REF!
Name CCAKRA: #REF!
Name CCEFIRO: #REF!
Name CCEFIRO: #REF!
Name CCEFIRO: #REF!
Name CCHARADE: #REF!
Name CCHARADE: #REF!
Name CCHARADE: #REF!
Name CCITY: #REF!
Name CCITY: #REF!
Name CCITY: #REF!
Name CCIVIC: #REF!
Name CCIVIC: #REF!
Name CCIVIC: #REF!
Name CCOROLLA: #REF!
Name CCOROLLA: #REF!
Name CCOROLLA: #REF!
Name CCORONA: #REF!
Name CCORONA: #REF!
Name CCORONA: #REF!

Sheet How To
B5: 1. | C5: Update data yang ada di sheet "OS" yang di kolom KUNING SECARA 5 HARIAN, yang tidak berwarna kuning jangan di otak-atik
C7: Dealer | D7: Outlet Code (Sales Code) | E7: Outlet Name | F7: Katashiki | G7: Suffix | H7: Tanggal SPK | I7: Status SPK | J7: Status Supply | K7: Tanggal Cut Of
I8: FIRMED | J8: MATCH MDP
I9: PENDING LOAN | J9: MATCH SUPPLY STOCK ON HAND
I10: ALREADY DO | J10: UNMATCH
I11: CANCEL
I12: CUSTOMER PENDING ISSUE
B14: 2.
F17: Update tanggal cut off tiap 5 HARIAN
B22: 3. | C22: Setelah semua data sudah diinput dengan benar, silahkan masuk ke sheet "Pvt OS" -> klik 1x di pivot table manapun -> pilih di menu bar "Analyze" -> pilih "Refresh All"
B23: 4. | C23: Masuk ke sheet "AO Report" -> input angka OP Target pada kolom yang tersedia
B33: 5. | C33: Masuk ke sheet "Action Plan" -> input angka Stock, MDP, dan Carry Over unit pada tabel yang tersedia
B50: 6. | C50: Input plan DO from OS Matching per 5 harian dengan mempertimbangkan jumlah Stock On Hand dan MDP heijunka
B66: 7. | C66: Masuk ke sheet "Reason Unmatch" -> update kolom yang ada dengan angka yang ada pada pivot di sebelah kanan -> jelaskan pula reason pada kolom "Remarks"
B83: 8. | C83: Masuk ke sheet "Action Plan" -> update kolom yang ada dengan angka yang ada pada pivot di sebelah kanan -> jelaskan pula reason pada kolom "Action Plan to Sell"

Sheet AO Report(0)
O1: ''
B2: AREA OPERATION REPORT - TUNAS NATIONAL - as of | R2: =OS!A6 -> 46244
C4: [A] Stock Matching with OS | AD4: Closing Estimation | AM4: RSSP OM | AP4: 0.85
G6: =SUM(G7:G21) -> 53 | AD6: OAP Target | AE6: 92 | AM6: OPT | AN6: 87 | AP6: =AE6-AE7 -> 39
C7: =AE10-X22 -> 123 | E7: =C7 -> 123 | G7: =GETPIVOTDATA("Area AGM",'Pvt OS'!$AG$8) -> 1 | N7: MATCHING RATIO | Q7: =O14/G6 -> 0.79245283 | AD7: [A] Matching with Outstanding | AE7: =SUM(X16:X22) -> 53 | AF7: =AE7/AE9 -> 0.57608696 | AM7: EC | AN7: 2185
C8: =C7-C19 -> 81 | E8: =C8 -> 81 | H8: =GETPIVOTDATA("Area AGM",'Pvt OS'!$AK$8) -> 0 | AD8: [B] New Order (SPK) | AE8: =X58 -> 39 | AF8: =AE8/$AE$9 -> 0.42391304 | AM8: Gap | AN8: =AN7-AE7 -> 2132
G9: =GETPIVOTDATA("Area AGM",'Pvt OS'!$Y$8) -> 4 | J9: =GETPIVOTDATA("Area AGM",'Pvt OS'!$BI$8) -> 5 | X9: =AE6 -> 92 | AD9: Total Estimasi Closing [A+B] | AE9: =AE7+AE8 -> 92 | AF9: =AE9/AE6 -> 1 | AN9: 2185
H10: =GETPIVOTDATA("Area AGM",'Pvt OS'!$AC$8) -> 0 | J10: =SUM(H9:H10) -> 0 | X10: =X9-SUM(X16:X22) -> 39 | AD10: Total Invoicable Stock | AE10: ='Action Plan'!F27 -> 133 | AN10: =AN9-AE9 -> 2093
G11: =GETPIVOTDATA("Area AGM",'Pvt OS'!$Q$8) -> 0 | J11: =SUM(K11:K14) -> 7 | K11: =GETPIVOTDATA("Area AGM",'Pvt OS'!$BE$8) -> 0 | AD11: Efficiency (STO) | AE11: =AE9/AE10 -> 0.69172932 | AM11: =2125-AE7 -> 2072 | AN11: =AM11/2125 -> 0.97505882
H12: =GETPIVOTDATA("Area AGM",'Pvt OS'!$U$8) -> 0
G13: =GETPIVOTDATA("Area AGM",'Pvt OS'!$I$8) -> 0 | K13: =GETPIVOTDATA("Area AGM",'Pvt OS'!$BA$8) -> 0
H14: =GETPIVOTDATA("Area AGM",'Pvt OS'!$M$8) -> 0 | K14: =GETPIVOTDATA("Area AGM",'Pvt OS'!$AW$8) -> 7 | O14: =SUM(O15:O20) -> 42 | U14: Total potential DO fr OS : | V14: =SUM(X16:X22) -> 53
G15: =SUM(H15:H20) -> 48 | H15: =GETPIVOTDATA("Area AGM",'Pvt OS'!$E$8) -> 18 | J15: =SUM(K15:K21) -> 42 | K15: =H12+H14 -> 0 | O15: =J15-O19 -> 26 | X15: =X16-O14 -> 1 | AM15: =88%*AE6 -> 80.96 | AN15: 1960
K16: =GETPIVOTDATA("Area AGM",'Pvt OS'!$AS$8) -> 18 | V16: =ROUND($O$14*V$78,0) -> 13 | X16: =SUM(Q21,R20,S19,T18,U17,V16) -> 43 | AN16: =AN15-AE6 -> 1868 | AP16: =X22+O14 -> 52
U17: =ROUND($O$14*U$78,0) -> 11 | AP17: 1800
T18: =ROUND($O$14*T$78,0) -> 10 | AP18: =AP17-AP16 -> 1748
C19: =J15 -> 42 | E19: =C19 -> 42 | H19: =GETPIVOTDATA("Area AGM",'Pvt OS'!$A$8) -> 30 | K19: =GETPIVOTDATA("Area AGM",'Pvt OS'!$AO$8) -> 24 | O19: =IFERROR(GETPIVOTDATA("Area AGM",'Pvt OS'!$BM$8,"Status Supply","Match Supply Stock On Hand"),0)+IFERROR(GETPIVOTDATA("Area AGM",'Pvt OS'!$BP$8,"Status Supply","Match Supply Stock On Hand"),0) -> 16 | S19: =ROUND($O$14*S$78,0) -> 9
R20: =ROUND($O$14*R$78,0) -> 0 | S20: s
Q21: =ROUND($O$14*Q$78,0) -> 0
G22: ,, | Q22: 3 | R22: 7 | X22: =SUM(Q22:V22) -> 10 | Y22: MTD
C23: Full Stock | E23: Invoicable Stk | G23: OS Order | J23: Stock Matching | Q23: 1-5 | R23: 6-10 | S23: 11-15 | T23: 16-20 | U23: 21-25 | V23: 25-31
O25: Revised Plan
O26: Original Plan
O27: Actual RS
S34: 0.4 | T34: 0.6 | V34: =3948-AE7-#REF! -> #REF!
C35: [B] Matching Stock from Order
AR36: SPK Nett actual
C37: SPK plan | AR37: GAP
F38: 1-5 | G38: 6-10 | H38: 11-15 | I38: 16-20 | J38: 21-25 | K38: 25-31 | X38: =X39+X44 -> 114
E39: TTL | F39: Effective to N RS | J39: For N+1 RS | V39: =K50 -> 19 | X39: =V39+U42 -> 38 | Z39: N+1 OP tgt | AA39: Day 21-30 CKD SPK | AB39: Comp.
C40: SPK Gross Plan | E40: 122 | F40: =SUM(F41:I41) -> 80 | J40: =SUM(J41:K41) -> 42
F41: =F82 -> 20 | G41: 20 | H41: 20 | I41: =I82 -> 20 | J41: 20 | K41: 22
C42: SPK Gross actual | E42: =SUM(F42:K42) -> 54 | F42: 30 | G42: 24 | U42: =J50 -> 19 | Z42: 1727 | AA42: =X39 -> 38 | AB42: =AA42/Z42 -> 0.022003474
C43: GAP | F43: =F42-F41 -> 10 | G43: =G42-G41 -> 4 | H43: =H42-H41 -> -20 | I43: =I42-I41 -> -20 | J43: =J42-J41 -> -20 | K43: =K42-K41 -> -22
T44: =I50 -> 19 | X44: =SUM(Q51,R48,S46,T44) -> 76
C45: Cancellation assum. | E45: =SUM(F45:K45) -> 6 | F45: =ROUND($M$47*F41,0) -> 1 | G45: =ROUND($M$47*G41,0) -> 1 | H45: =ROUND($M$47*H41,0) -> 1 | I45: =ROUND($M$47*I41,0) -> 1 | J45: =ROUND($M$47*J41,0) -> 1 | K45: =ROUND($M$47*K41,0) -> 1 | M45: Cancel ratio
C46: Cancellation actual | E46: =SUM(F46:K46) -> 0 | F46: 0 | G46: 0 | H46: 0 | I46: 0 | J46: 0 | M46: 3m avg. | N46: Loan rej. | S46: =H50 -> 19
C47: Cancellation ratio | F47: =IFERROR(F46/F42,0) -> 0 | G47: =IFERROR(G46/G42,0) -> 0 | H47: =IFERROR(H46/H42,0) -> 0 | I47: =IFERROR(I46/I42,0) -> 0 | J47: =IFERROR(J46/J42,0) -> 0 | K47: =IFERROR(K46/K42,0) -> 0 | M47: 0.04 | N47: 0.02
R48: =G50 -> 19
C49: SPK Nett Plan | E49: =SUM(F50:K50) -> 114 | F49: =SUM(F50:I50) -> 76 | J49: =SUM(J50:K50) -> 38
F50: =F41-F45 -> 19 | G50: =G41-G45 -> 19 | H50: =H41-H45 -> 19 | I50: =I41-I45 -> 19 | J50: =J41-J45 -> 19 | K50: =K41-K45-2 -> 19
C51: SPK Nett actual | E51: =SUM(F51:K51) -> 54 | F51: =F42-F46 -> 30 | G51: =G42-G46 -> 24 | H51: =H42-H46 -> 0 | I51: =I42-I46 -> 0 | J51: =J42-J46 -> 0 | K51: =K42-K46 -> 0 | Q51: =F50 -> 19
C52: GAP | F52: =F51-F50 -> 11 | G52: =G51-G50 -> 5 | H52: =H51-H50 -> -19 | I52: =I51-I50 -> -19 | J52: =J51-J50 -> -19 | K52: =K51-K50 -> -19
Q53: =Q51 -> 19 | R53: =R48+Q53 -> 38 | S53: =S46+R53 -> 57 | T53: =T44+S53 -> 76 | U53: =U42+T53 -> 95 | V53: =V39+U53 -> 114
Q54: 1-5 | R54: 6-10 | S54: 11-15 | T54: 16-20 | U54: 21-25 | V54: 25-31
C55: MDP plan | O55: RS plan
C56: =SUM(C57:C64) -> 81
C57: =H8 -> 0 | E57: =C57 -> 0
C58: =H10 -> 0 | E58: =C58 -> 0 | V58: =ROUND($Z$80*V$80,0) -> 12 | X58: =SUM(Q65,R64,S63,T62,U60,V58) -> 39
C59: =E8 -> 81 | K59: =V74 -> 17
J60: =U74 -> 12 | U60: =ROUND($Z$80*U$80,0) -> 10
I61: =T74 -> 15
H62: =S74 -> 14 | T62: =ROUND($Z$80*T$80,0) -> 9
G63: =R74 -> 9 | S63: =ROUND($Z$80*S$80,0) -> 8
F64: =Q74 -> 6 | R64: =ROUND($Z$80*R$80,0) -> 0
E65: ='Action Plan'!B27 -> 38 | Q65: =ROUND($Z$80*Q$80,0) -> 0
C66: FFS | E66: =E65+E57+E58 -> 38 | F66: =F64+E66 -> 44 | G66: =G63+F66 -> 53 | H66: =H62+G66 -> 67 | I66: =I61+H66 -> 82 | J66: =J60+I66 -> 94 | K66: =K59+J66 -> 111 | L66: Accum. | Q66: =Q65 -> 0 | R66: =R64+Q66 -> 0 | S66: =S63+R66 -> 8 | T66: =T62+S66 -> 17 | U66: =U60+T66 -> 27 | V66: =V58+U66 -> 39 | W66: Accum.
Q67: =Q66/F66 -> 0 | R67: =R66/G66 -> 0 | S67: =S66/H66 -> 0.11940299 | T67: =T66/I66 -> 0.20731707 | U67: =U66/J66 -> 0.28723404 | V67: =V66/K66 -> 0.35135135 | W67: [B]RS / FFS MTD
E68: 0 OH Stock | F68: 1-5 | G68: 6-10 | H68: 11-15 | I68: 16-20 | J68: 21-25 | K68: 25-31 | Q68: 1-5 | R68: 6-10 | S68: 11-15 | T68: 16-20 | U68: 21-25 | V68: 25-31 | AR68: SPK Nett Plan
K71: =Q21+R20+S19+Q65+R64+S63 -> 17 | Q71: 1-5 | R71: 6-10 | S71: 11-15 | T71: 16-20 | U71: 21-25 | V71: 25-31 | X71: Full Month | AD71: =1913-2050 -> -137
O72: TTL Supply | Q72: =SUM(Q73:Q75) -> 57 | R72: =SUM(R73:R75) -> 14 | S72: =SUM(S73:S75) -> 14 | T72: =SUM(T73:T75) -> 15 | U72: =SUM(U73:U75) -> 12 | V72: =SUM(V73:V75) -> 17 | X72: =SUM(Q72:V72) -> 129
O73: OH Stock | Q73: 38 | X73: =SUM(Q73:V73) -> 38 | AD73: =V16+AD71 -> -124
O74: MDP | Q74: 6 | R74: 9 | S74: 14 | T74: 15 | U74: 12 | V74: 17 | X74: =SUM(Q74:V74) -> 73
O75: C/O | Q75: 13 | R75: 5 | X75: =SUM(Q75:V75) -> 18
S78: 0.21 | T78: 0.23 | U78: 0.26 | V78: 0.3 | X78: =SUM(Q78:V78) -> 1
E79: ='Action Plan'!C27 -> 76 | F79: =ROUND($E$79*F81,0) -> 15 | G79: =ROUND($E$79*G81,0) -> 11 | H79: =ROUND($E$79*H81,0) -> 11 | I79: =ROUND($E$79*I81,0) -> 15 | J79: =ROUND($E$79*J81,0) -> 11 | K79: =ROUND($E$79*K81,0) -> 11
S80: 0.21 | T80: 0.23 | U80: 0.26 | V80: 0.3 | X80: =SUM(Q80:V80) -> 1 | Z80: =AB80-AE7 -> 39 | AB80: =AE6 -> 92
E81: =ROUND(AE6/91.3%,0) -> 101 | F81: 0.2 | G81: 0.15 | H81: 0.15 | I81: 0.2 | J81: 0.15 | K81: 0.15 | M81: =SUM(F81:K81) -> 1 | Q81: 0.2 | R81: 0.1 | S81: 0.1 | T81: 0.2 | U81: 0.2 | V81: 0.2 | W81: =SUM(W78,W80) -> 0 | X81: =SUM(Q81:V81) -> 1
F82: =ROUND($E$81*F81,0) -> 20 | G82: =ROUND($E$81*G81,0) -> 15 | H82: =ROUND($E$81*H81,0) -> 15 | I82: =ROUND($E$81*I81,0) -> 20 | J82: =ROUND($E$81*J81,0) -> 15 | K82: =ROUND($E$81*K81,0) -> 15 | L82: =ROUND($E$81*L81,0) -> 0 | Z82: 145
Q83: =Q22 -> 3 | R83: =R20 -> 0 | S83: =S19 -> 9 | T83: =T18 -> 10 | U83: =U17 -> 11 | V83: =V16 -> 13
Q84: =Q65 -> 0 | R84: =R64 -> 0 | S84: =S63 -> 8 | T84: =T62 -> 9 | U84: =U60 -> 10 | V84: =V58 -> 12
Q85: =SUM(Q83:Q84) -> 3 | R85: =SUM(R83:R84) -> 0 | S85: =SUM(S83:S84) -> 17 | T85: =SUM(T83:T84) -> 19 | U85: =SUM(U83:U84) -> 21 | V85: =SUM(V83:V84) -> 25 | X85: =SUM(Q85:V85) -> 85
Q86: =Q85/$X$85 -> 0.035294118 | R86: =R85/$X$85 -> 0 | S86: =S85/$X$85 -> 0.2 | T86: =T85/$X$85 -> 0.22352941 | U86: =U85/$X$85 -> 0.24705882 | V86: =V85/$X$85 -> 0.29411765
S87: =SUM(Q86:S86) -> 0.23529412 | U87: =SUM(Q86:U86) -> 0.70588235
K88: =100/6 -> 16.666667 | Q88: 0.125 | R88: 0.125 | S88: 0.13 | T88: 0.2 | U88: 0.21 | V88: 0.21
O93: =SUM(Q93:S93) -> 17 | Q93: =Q65+Q21 -> 0 | R93: =R64+R20 -> 0 | S93: =S63+S19 -> 17 | T93: =T62+T18 -> 19 | U93: =U60+U17 -> 21 | V93: =V58+V16 -> 25 | X93: =SUM(Q93:V93) -> 82
O94: =SUM(Q94:S94) -> 0.20731707 | Q94: =Q93/$X$93 -> 0 | R94: =R93/$X$93 -> 0 | S94: =S93/$X$93 -> 0.20731707 | T94: =T93/$X$93 -> 0.23170732 | U94: =U93/$X$93 -> 0.25609756 | V94: =V93/$X$93 -> 0.30487805
S97: =SUM(Q93:S93) -> 17 | T97: =S97+T93 -> 36 | X97: =ROUND(Z97*X93,0) -> 25 | Z97: 0.3
X98: =ROUND(Z98*X93,0) -> 49 | Z98: 0.6
S100: =S97/2150 -> 0.0079069767 | T100: =T97/X93 -> 0.43902439

Sheet Remaining Target
C5: DO AFI | D5: 1-5 | E5: 6-10 | F5: 11-15 | G5: 16-20 | H5: 21-25 | I5: 26-EOM
C6: Ori Plan
C7: Revised Plan
C8: Actual DO
C9: GAP | D9: =D8-D6 -> 0 | E9: =E8-E6 -> 0 | F9: =F8-F6 -> 0 | G9: =G8-G6 -> 0 | H9: =H8-H6 -> 0 | I9: =I7-I6 -> 0

Sheet by MDL
D2: 1 Minggu | E2: 2 Minggu | F2: 3 Minggu | G2: 4 Minggu | H2: > 4 Minggu | J2: All | K2: <30D
B3: Status OS yg sudah matching tapi diestimasikan tetap tidak bisa jadi RS di bulan ini
B4: Gap from OS | C4: Matched Unfirmed (PL + CPI) | I4: Unmatched to Stock
D6: 1 w | E6: 2 w | F6: 3 w | G6: 4 w | H6: >4 w | J6: Firmed | K6: P.Loan | L6: Remarks
B7: Avanza New | C7: =SUM(D7:G7) -> 0 | D7: =IFERROR(GETPIVOTDATA("Area AGM",#REF!,"Dealer",""&$S$18&"","Model",""&$B7&"","Umur Outstansing",""&D$2&""),0) -> 0 | E7: =IFERROR(GETPIVOTDATA("Area AGM",#REF!,"Dealer",""&$S$18&"","Model",""&$B7&"","Umur Outstansing",""&E$2&""),0) -> 0 | F7: =IFERROR(GETPIVOTDATA("Area AGM",#REF!,"Dealer",""&$S$18&"","Model",""&$B7&"","Umur Outstansing",""&F$2&""),0) -> 0 | G7: =IFERROR(GETPIVOTDATA("Area AGM",#REF!,"Dealer",""&$S$18&"","Model",""&$B7&"","Umur Outstansing",""&G$2&""),0) -> 0 | H7: =IFERROR(GETPIVOTDATA("Area AGM",#REF!,"Dealer",""&$S$18&"","Model",""&$B7&"","Umur Outstansing",""&H$2&""),0) -> 0 | I7: =SUM(J7:K7) -> 0 | J7: =IFERROR(GETPIVOTDATA("Area AGM",#REF!,"Dealer",""&$S$18&"","Model",""&$B7&""),0) -> 0 | K7: =IFERROR(GETPIVOTDATA("Area AGM",#REF!,"Dealer",""&$S$18&"","Model",""&$B7&""),0) -> 0 | L7: - Maximize swapping & change facility - Re-offer with the current type & color available | P7: Budi Jaya
B8: Veloz New | C8: =SUM(D8:G8) -> 0 | D8: =IFERROR(GETPIVOTDATA("Area AGM",#REF!,"Dealer",""&$S$18&"","Model",""&$B8&"","Umur Outstansing",""&D$2&""),0) -> 0 | E8: =IFERROR(GETPIVOTDATA("Area AGM",#REF!,"Dealer",""&$S$18&"","Model",""&$B8&"","Umur Outstansing",""&E$2&""),0) -> 0 | F8: =IFERROR(GETPIVOTDATA("Area AGM",#REF!,"Dealer",""&$S$18&"","Model",""&$B8&"","Umur Outstansing",""&F$2&""),0) -> 0 | G8: =IFERROR(GETPIVOTDATA("Area AGM",#REF!,"Dealer",""&$S$18&"","Model",""&$B8&"","Umur Outstansing",""&G$2&""),0) -> 0 | H8: =IFERROR(GETPIVOTDATA("Area AGM",#REF!,"Dealer",""&$S$18&"","Model",""&$B8&"","Umur Outstansing",""&H$2&""),0) -> 0 | I8: =SUM(J8:K8) -> 0 | J8: =IFERROR(GETPIVOTDATA("Area AGM",#REF!,"Dealer",""&$S$18&"","Model",""&$B8&""),0) -> 0 | K8: =IFERROR(GETPIVOTDATA("Area AGM",#REF!,"Dealer",""&$S$18&"","Model",""&$B8&""),0) -> 0 | P8: Duta Cendana
B9: Raize | C9: =SUM(D9:G9) -> 0 | D9: =IFERROR(GETPIVOTDATA("Area AGM",#REF!,"Dealer",""&$S$18&"","Model",""&$B9&"","Umur Outstansing",""&D$2&""),0) -> 0 | E9: =IFERROR(GETPIVOTDATA("Area AGM",#REF!,"Dealer",""&$S$18&"","Model",""&$B9&"","Umur Outstansing",""&E$2&""),0) -> 0 | F9: =IFERROR(GETPIVOTDATA("Area AGM",#REF!,"Dealer",""&$S$18&"","Model",""&$B9&"","Umur Outstansing",""&F$2&""),0) -> 0 | G9: =IFERROR(GETPIVOTDATA("Area AGM",#REF!,"Dealer",""&$S$18&"","Model",""&$B9&"","Umur Outstansing",""&G$2&""),0) -> 0 | H9: =IFERROR(GETPIVOTDATA("Area AGM",#REF!,"Dealer",""&$S$18&"","Model",""&$B9&"","Umur Outstansing",""&H$2&""),0) -> 0 | I9: =SUM(J9:K9) -> 0 | J9: =IFERROR(GETPIVOTDATA("Area AGM",#REF!,"Dealer",""&$S$18&"","Model",""&$B9&""),0) -> 0 | K9: =IFERROR(GETPIVOTDATA("Area AGM",#REF!,"Dealer",""&$S$18&"","Model",""&$B9&""),0) -> 0 | P9: Selamat Toyota
B10: Agya | C10: =SUM(D10:G10) -> 0 | D10: =IFERROR(GETPIVOTDATA("Area AGM",#REF!,"Dealer",""&$S$18&"","Model",""&$B10&"","Umur Outstansing",""&D$2&""),0) -> 0 | E10: =IFERROR(GETPIVOTDATA("Area AGM",#REF!,"Dealer",""&$S$18&"","Model",""&$B10&"","Umur Outstansing",""&E$2&""),0) -> 0 | F10: =IFERROR(GETPIVOTDATA("Area AGM",#REF!,"Dealer",""&$S$18&"","Model",""&$B10&"","Umur Outstansing",""&F$2&""),0) -> 0 | G10: =IFERROR(GETPIVOTDATA("Area AGM",#REF!,"Dealer",""&$S$18&"","Model",""&$B10&"","Umur Outstansing",""&G$2&""),0) -> 0 | H10: =IFERROR(GETPIVOTDATA("Area AGM",#REF!,"Dealer",""&$S$18&"","Model",""&$B10&"","Umur Outstansing",""&H$2&""),0) -> 0 | I10: =SUM(J10:K10) -> 0 | J10: =IFERROR(GETPIVOTDATA("Area AGM",#REF!,"Dealer",""&$S$18&"","Model",""&$B10&""),0) -> 0 | K10: =IFERROR(GETPIVOTDATA("Area AGM",#REF!,"Dealer",""&$S$18&"","Model",""&$B10&""),0) -> 0 | P10: Sinar Mas
B11: Calya | C11: =SUM(D11:G11) -> 0 | D11: =IFERROR(GETPIVOTDATA("Area AGM",#REF!,"Dealer",""&$S$18&"","Model",""&$B11&"","Umur Outstansing",""&D$2&""),0) -> 0 | E11: =IFERROR(GETPIVOTDATA("Area AGM",#REF!,"Dealer",""&$S$18&"","Model",""&$B11&"","Umur Outstansing",""&E$2&""),0) -> 0 | F11: =IFERROR(GETPIVOTDATA("Area AGM",#REF!,"Dealer",""&$S$18&"","Model",""&$B11&"","Umur Outstansing",""&F$2&""),0) -> 0 | G11: =IFERROR(GETPIVOTDATA("Area AGM",#REF!,"Dealer",""&$S$18&"","Model",""&$B11&"","Umur Outstansing",""&G$2&""),0) -> 0 | H11: =IFERROR(GETPIVOTDATA("Area AGM",#REF!,"Dealer",""&$S$18&"","Model",""&$B11&"","Umur Outstansing",""&H$2&""),0) -> 0 | I11: =SUM(J11:K11) -> 0 | J11: =IFERROR(GETPIVOTDATA("Area AGM",#REF!,"Dealer",""&$S$18&"","Model",""&$B11&""),0) -> 0 | K11: =IFERROR(GETPIVOTDATA("Area AGM",#REF!,"Dealer",""&$S$18&"","Model",""&$B11&""),0) -> 0 | P11: Rejeki Toyota
B12: Yaris | C12: =SUM(D12:G12) -> 0 | D12: =IFERROR(GETPIVOTDATA("Area AGM",#REF!,"Dealer",""&$S$18&"","Model",""&$B12&"","Umur Outstansing",""&D$2&""),0) -> 0 | E12: =IFERROR(GETPIVOTDATA("Area AGM",#REF!,"Dealer",""&$S$18&"","Model",""&$B12&"","Umur Outstansing",""&E$2&""),0) -> 0 | F12: =IFERROR(GETPIVOTDATA("Area AGM",#REF!,"Dealer",""&$S$18&"","Model",""&$B12&"","Umur Outstansing",""&F$2&""),0) -> 0 | G12: =IFERROR(GETPIVOTDATA("Area AGM",#REF!,"Dealer",""&$S$18&"","Model",""&$B12&"","Umur Outstansing",""&G$2&""),0) -> 0 | H12: =IFERROR(GETPIVOTDATA("Area AGM",#REF!,"Dealer",""&$S$18&"","Model",""&$B12&"","Umur Outstansing",""&H$2&""),0) -> 0 | I12: =SUM(J12:K12) -> 0 | J12: =IFERROR(GETPIVOTDATA("Area AGM",#REF!,"Dealer",""&$S$18&"","Model",""&$B12&""),0) -> 0 | K12: =IFERROR(GETPIVOTDATA("Area AGM",#REF!,"Dealer",""&$S$18&"","Model",""&$B12&""),0) -> 0 | P12: Astrido Toyota
B13: Innova | C13: =SUM(D13:G13) -> 0 | D13: =IFERROR(GETPIVOTDATA("Area AGM",#REF!,"Dealer",""&$S$18&"","Model",""&$B13&"","Umur Outstansing",""&D$2&""),0) -> 0 | E13: =IFERROR(GETPIVOTDATA("Area AGM",#REF!,"Dealer",""&$S$18&"","Model",""&$B13&"","Umur Outstansing",""&E$2&""),0) -> 0 | F13: =IFERROR(GETPIVOTDATA("Area AGM",#REF!,"Dealer",""&$S$18&"","Model",""&$B13&"","Umur Outstansing",""&F$2&""),0) -> 0 | G13: =IFERROR(GETPIVOTDATA("Area AGM",#REF!,"Dealer",""&$S$18&"","Model",""&$B13&"","Umur Outstansing",""&G$2&""),0) -> 0 | H13: =IFERROR(GETPIVOTDATA("Area AGM",#REF!,"Dealer",""&$S$18&"","Model",""&$B13&"","Umur Outstansing",""&H$2&""),0) -> 0 | I13: =SUM(J13:K13) -> 0 | J13: =IFERROR(GETPIVOTDATA("Area AGM",#REF!,"Dealer",""&$S$18&"","Model",""&$B13&""),0) -> 0 | K13: =IFERROR(GETPIVOTDATA("Area AGM",#REF!,"Dealer",""&$S$18&"","Model",""&$B13&""),0) -> 0 | P13: Auto2000
B14: Fortuner 4x2 | C14: =SUM(D14:G14) -> 0 | D14: =IFERROR(GETPIVOTDATA("Area AGM",#REF!,"Dealer",""&$S$18&"","Model",""&$B14&"","Umur Outstansing",""&D$2&""),0) -> 0 | E14: =IFERROR(GETPIVOTDATA("Area AGM",#REF!,"Dealer",""&$S$18&"","Model",""&$B14&"","Umur Outstansing",""&E$2&""),0) -> 0 | F14: =IFERROR(GETPIVOTDATA("Area AGM",#REF!,"Dealer",""&$S$18&"","Model",""&$B14&"","Umur Outstansing",""&F$2&""),0) -> 0 | G14: =IFERROR(GETPIVOTDATA("Area AGM",#REF!,"Dealer",""&$S$18&"","Model",""&$B14&"","Umur Outstansing",""&G$2&""),0) -> 0 | H14: =IFERROR(GETPIVOTDATA("Area AGM",#REF!,"Dealer",""&$S$18&"","Model",""&$B14&"","Umur Outstansing",""&H$2&""),0) -> 0 | I14: =SUM(J14:K14) -> 0 | J14: =IFERROR(GETPIVOTDATA("Area AGM",#REF!,"Dealer",""&$S$18&"","Model",""&$B14&""),0) -> 0 | K14: =IFERROR(GETPIVOTDATA("Area AGM",#REF!,"Dealer",""&$S$18&"","Model",""&$B14&""),0) -> 0 | P14: Merdeka Motor
B15: Rush | C15: =SUM(D15:G15) -> 0 | D15: =IFERROR(GETPIVOTDATA("Area AGM",#REF!,"Dealer",""&$S$18&"","Model",""&$B15&"","Umur Outstansing",""&D$2&""),0) -> 0 | E15: =IFERROR(GETPIVOTDATA("Area AGM",#REF!,"Dealer",""&$S$18&"","Model",""&$B15&"","Umur Outstansing",""&E$2&""),0) -> 0 | F15: =IFERROR(GETPIVOTDATA("Area AGM",#REF!,"Dealer",""&$S$18&"","Model",""&$B15&"","Umur Outstansing",""&F$2&""),0) -> 0 | G15: =IFERROR(GETPIVOTDATA("Area AGM",#REF!,"Dealer",""&$S$18&"","Model",""&$B15&"","Umur Outstansing",""&G$2&""),0) -> 0 | H15: =IFERROR(GETPIVOTDATA("Area AGM",#REF!,"Dealer",""&$S$18&"","Model",""&$B15&"","Umur Outstansing",""&H$2&""),0) -> 0 | I15: =SUM(J15:K15) -> 0 | J15: =IFERROR(GETPIVOTDATA("Area AGM",#REF!,"Dealer",""&$S$18&"","Model",""&$B15&""),0) -> 0 | K15: =IFERROR(GETPIVOTDATA("Area AGM",#REF!,"Dealer",""&$S$18&"","Model",""&$B15&""),0) -> 0 | P15: Plaza Toyota
B16: Others | C16: =SUM(D16:G16) -> 0 | D16: =SUM(D21:D53) -> 0 | E16: =SUM(E21:E53) -> 0 | F16: =SUM(F21:F53) -> 0 | G16: =SUM(G21:G53) -> 0 | H16: =SUM(H21:H52) -> 0 | I16: =SUM(J16:K16) -> 0 | J16: =SUM(J21:J53) -> 0 | K16: =SUM(K21:K53) -> 0 | P16: Wijaya Toyota
B17: Grand Total | C17: =SUM(D17:G17) -> 0 | D17: =SUM(D7:D16) -> 0 | E17: =SUM(E7:E16) -> 0 | F17: =SUM(F7:F16) -> 0 | G17: =SUM(G7:G16) -> 0 | H17: =SUM(H7:H16) -> 0 | I17: =SUM(I7:I16) -> 0 | J17: =SUM(J7:J16) -> 0 | K17: =SUM(K7:K16) -> 0 | P17: Tunas Toyota
S18: Duta Cendana
S19: Model | T19: Stock Matching | U19: Unfirmed & Match | V19: BU | W19: Total OS | X19: OS Match | Y19: Firmed & Match >60D | Z19: Firmed & Match 30-60D | AA19: Firmed & Match <30D | AB19: PL Match <30D | AC19: Stock EOM | AD19: Distplan | AE19: MDP TLS | AF19: C/O | AG19: 2nd Allo | AH19: Delay | AI19: Total Supply | AJ19: RS Latest | AK19: Remaining FFS | AL19: Gap fr Matching | AM19: FFS | AN19: C/O AFI | AO19: C/O AFI not yet DO | AP19: SPK Latest | AQ19: RS from new SPK | AR19: Remaining SPK | AU19: Action Plan to Sell | BA19: Funnel Plan
Q20: STO | R20: OP | AL20: Gap fr Matching | AS20: Match fr New SPK | AT20: Un Match | BA20: Leads/Prospect | BB20: Hot Prospect | BC20: SPK | BD20: DO
B21: ALPHARD | C21: =SUM(D21:G21) -> 0 | D21: =IFERROR(GETPIVOTDATA("Area AGM",#REF!,"Dealer",""&$S$18&"","Model",""&$B21&"","Umur Outstansing",""&D$2&""),0) -> 0 | E21: =IFERROR(GETPIVOTDATA("Area AGM",#REF!,"Dealer",""&$S$18&"","Model",""&$B21&"","Umur Outstansing",""&E$2&""),0) -> 0 | F21: =IFERROR(GETPIVOTDATA("Area AGM",#REF!,"Dealer",""&$S$18&"","Model",""&$B21&"","Umur Outstansing",""&F$2&""),0) -> 0 | G21: =IFERROR(GETPIVOTDATA("Area AGM",#REF!,"Dealer",""&$S$18&"","Model",""&$B21&"","Umur Outstansing",""&G$2&""),0) -> 0 | H21: =IFERROR(GETPIVOTDATA("Area AGM",#REF!,"Dealer",""&$S$18&"","Model",""&$B21&"","Umur Outstansing",""&H$2&""),0) -> 0 | J21: =IFERROR(GETPIVOTDATA("Area AGM",#REF!,"Dealer",""&$S$18&"","Model",""&$B21&""),0) -> 0 | K21: =IFERROR(GETPIVOTDATA("Area AGM",#REF!,"Dealer",""&$S$18&"","Model",""&$B21&""),0) -> 0 | P21: Avanza New | Q21: =IFERROR(R21/AI21,0) -> 0 | R21: =IFERROR(GETPIVOTDATA("RS Target",#REF!,"Dealer",""&$S$18&"","Model",""&$P21&""),0) -> 0 | S21: Avanza New | T21: =SUM(Y21:AB21,AO21) -> 0 | U21: =IFERROR(GETPIVOTDATA("Area AGM",'Pvt OS'!#REF!,"Dealer",""&$S$18&"","Model",""&$S21&""),0) -> 0 | V21: =W21-X21 -> 0 | W21: =IFERROR(GETPIVOTDATA("Area AGM",'Pvt OS'!#REF!,"Dealer",""&$S$18&"","Model",""&$S21&""),0)+IFERROR(GETPIVOTDATA("Area AGM",'Pvt OS'!$A$8,"Dealer",""&$S$18&"","Model",""&$S21&""),0) -> 0 | X21: =SUM(Y21:AB21) -> 0 | Y21: =IFERROR(GETPIVOTDATA("Area AGM",'Pvt OS'!$U$8,"Dealer",""&$S$18&"","Model",""&$S21&""),0) -> 0 | Z21: =IFERROR(GETPIVOTDATA("Area AGM",'Pvt OS'!$M$8,"Dealer",""&$S$18&"","Model",""&$S21&""),0) -> 0 | AA21: =IFERROR(GETPIVOTDATA("Area AGM",'Pvt OS'!#REF!,"Dealer",""&$S$18&"","Model",""&$S21&""),0) -> 0 | AB21: =IFERROR(GETPIVOTDATA("Area AGM",'Pvt OS'!$AO$8,"Dealer",""&$S$18&"","Model",""&$S21&""),0) -> 0 | AC21: =IFERROR(GETPIVOTDATA("Stock",#REF!,"Dealer",""&$S$18&"","Model",""&$S21&""),0) -> 0 | AD21: =IFERROR(GETPIVOTDATA("MDP",#REF!,"Dealer",""&$S$18&"","Model",""&$S21&""),0) -> 0 | AE21: =IFERROR(GETPIVOTDATA("RRN",#REF!,"Model2",""&$S21&"","Dealer",""&$S$18&""),0) -> 0 | AF21: =IFERROR(GETPIVOTDATA("CO",#REF!,"Dealer Name",""&$S$18&"","Model",""&$S21&""),0) -> 0 | AG21: =IFERROR(GETPIVOTDATA("Sum of Distplan Final",#REF!,"Dealer",""&$S$18&"","Model",""&$S21&""),0) -> 0 | AH21: =IFERROR(GETPIVOTDATA("RRN",#REF!,"Model",""&$S21&"","Dealer",""&$S$18&""),0) -> 0 | AI21: =AC21+AD21+AF21+AG21-AH21 -> 0 | AJ21: =IFERROR(GETPIVOTDATA("volume_rs",#REF!,"Model",""&$S21&"","Dealer",""&$S$18&""),0) -> 0 | AK21: =AI21-AJ21-X21+AN21 -> 0 | AL21: =IFERROR(GETPIVOTDATA("Area AGM",'Pvt OS'!#REF!,"Dealer",""&$S$18&"","Model",""&$S21&""),0) -> 0 | AM21: =AK21+AL21 -> 0 | AN21: =IFERROR(GETPIVOTDATA("Row Labels",#REF!,"Dealer",""&$S$18&"","Model",""&$S21&""),0) -> 0 | AO21: =IFERROR(GETPIVOTDATA("RS Afi",#REF!,"Dealer",""&$S$18&"","Model",""&$S21&""),0) -> 0 | AP21: =IFERROR(GETPIVOTDATA("qty",#REF!,"Model",""&$S21&"","Dealer",""&$S$18&""),0) -> 0 | AQ21: =IFERROR(GETPIVOTDATA("volume_rs",#REF!,"Model",""&$S21&"","Dealer",""&$S$18&""),0) -> 0 | AR21: =AP21-AQ21 -> 0 | AS21: =IFERROR(GETPIVOTDATA("Area AGM",'Pvt OS'!#REF!,"Dealer",""&$S$18&"","Model",""&$S21&""),0) -> 0 | AT21: =AR21-AS21 -> 0 | AU21: Attached | BA21: =#REF! -> #REF! | BB21: =#REF! -> #REF! | BC21: =#REF! -> #REF! | BD21: =#REF! -> #REF!
B22: AVANZA | C22: =SUM(D22:G22) -> 0 | D22: =IFERROR(GETPIVOTDATA("Area AGM",#REF!,"Dealer",""&$S$18&"","Model",""&$B22&"","Umur Outstansing",""&D$2&""),0) -> 0 | E22: =IFERROR(GETPIVOTDATA("Area AGM",#REF!,"Dealer",""&$S$18&"","Model",""&$B22&"","Umur Outstansing",""&E$2&""),0) -> 0 | F22: =IFERROR(GETPIVOTDATA("Area AGM",#REF!,"Dealer",""&$S$18&"","Model",""&$B22&"","Umur Outstansing",""&F$2&""),0) -> 0 | G22: =IFERROR(GETPIVOTDATA("Area AGM",#REF!,"Dealer",""&$S$18&"","Model",""&$B22&"","Umur Outstansing",""&G$2&""),0) -> 0 | H22: =IFERROR(GETPIVOTDATA("Area AGM",#REF!,"Dealer",""&$S$18&"","Model",""&$B22&"","Umur Outstansing",""&H$2&""),0) -> 0 | J22: =IFERROR(GETPIVOTDATA("Area AGM",#REF!,"Dealer",""&$S$18&"","Model",""&$B22&""),0) -> 0 | K22: =IFERROR(GETPIVOTDATA("Area AGM",#REF!,"Dealer",""&$S$18&"","Model",""&$B22&""),0) -> 0 | P22: Veloz New | Q22: =IFERROR(R22/AI22,0) -> 0 | R22: =IFERROR(GETPIVOTDATA("RS Target",#REF!,"Dealer",""&$S$18&"","Model",""&$P22&""),0) -> 0 | S22: Veloz New | T22: =SUM(Y22:AB22,AO22) -> 0 | U22: =IFERROR(GETPIVOTDATA("Area AGM",'Pvt OS'!#REF!,"Dealer",""&$S$18&"","Model",""&$S22&""),0) -> 0 | V22: =W22-X22 -> 0 | W22: =IFERROR(GETPIVOTDATA("Area AGM",'Pvt OS'!#REF!,"Dealer",""&$S$18&"","Model",""&$S22&""),0)+IFERROR(GETPIVOTDATA("Area AGM",'Pvt OS'!$A$8,"Dealer",""&$S$18&"","Model",""&$S22&""),0) -> 0 | X22: =SUM(Y22:AB22) -> 0 | Y22: =IFERROR(GETPIVOTDATA("Area AGM",'Pvt OS'!$U$8,"Dealer",""&$S$18&"","Model",""&$S22&""),0) -> 0 | Z22: =IFERROR(GETPIVOTDATA("Area AGM",'Pvt OS'!$M$8,"Dealer",""&$S$18&"","Model",""&$S22&""),0) -> 0 | AA22: =IFERROR(GETPIVOTDATA("Area AGM",'Pvt OS'!#REF!,"Dealer",""&$S$18&"","Model",""&$S22&""),0) -> 0 | AB22: =IFERROR(GETPIVOTDATA("Area AGM",'Pvt OS'!$AO$8,"Dealer",""&$S$18&"","Model",""&$S22&""),0) -> 0 | AC22: =IFERROR(GETPIVOTDATA("Stock",#REF!,"Dealer",""&$S$18&"","Model",""&$S22&""),0) -> 0 | AD22: =IFERROR(GETPIVOTDATA("MDP",#REF!,"Dealer",""&$S$18&"","Model",""&$S22&""),0) -> 0 | AE22: =IFERROR(GETPIVOTDATA("RRN",#REF!,"Model2",""&$S22&"","Dealer",""&$S$18&""),0) -> 0 | AF22: =IFERROR(GETPIVOTDATA("CO",#REF!,"Dealer Name",""&$S$18&"","Model",""&$S22&""),0) -> 0 | AG22: =IFERROR(GETPIVOTDATA("Sum of Distplan Final",#REF!,"Dealer",""&$S$18&"","Model",""&$S22&""),0) -> 0 | AH22: =IFERROR(GETPIVOTDATA("RRN",#REF!,"Model",""&$S22&"","Dealer",""&$S$18&""),0) -> 0 | AI22: =AC22+AD22+AF22+AG22-AH22 -> 0 | AJ22: =IFERROR(GETPIVOTDATA("volume_rs",#REF!,"Model",""&$S22&"","Dealer",""&$S$18&""),0) -> 0 | AK22: =AI22-AJ22-X22+AN22 -> 0 | AL22: =IFERROR(GETPIVOTDATA("Area AGM",'Pvt OS'!#REF!,"Dealer",""&$S$18&"","Model",""&$S22&""),0) -> 0 | AM22: =AK22+AL22 -> 0 | AN22: =IFERROR(GETPIVOTDATA("Row Labels",#REF!,"Dealer",""&$S$18&"","Model",""&$S22&""),0) -> 0 | AO22: =IFERROR(GETPIVOTDATA("RS Afi",#REF!,"Dealer",""&$S$18&"","Model",""&$S22&""),0) -> 0 | AP22: =IFERROR(GETPIVOTDATA("qty",#REF!,"Model",""&$S22&"","Dealer",""&$S$18&""),0) -> 0 | AQ22: =IFERROR(GETPIVOTDATA("volume_rs",#REF!,"Model",""&$S22&"","Dealer",""&$S$18&""),0) -> 0 | AR22: =AP22-AQ22 -> 0 | AS22: =IFERROR(GETPIVOTDATA("Area AGM",'Pvt OS'!#REF!,"Dealer",""&$S$18&"","Model",""&$S22&""),0) -> 0 | AT22: =AR22-AS22 -> 0 | BA22: =#REF! -> #REF! | BB22: =#REF! -> #REF! | BC22: =#REF! -> #REF! | BD22: =#REF! -> #REF!
B23: SIENTA | C23: =SUM(D23:G23) -> 0 | D23: =IFERROR(GETPIVOTDATA("Area AGM",#REF!,"Dealer",""&$S$18&"","Model",""&$B23&"","Umur Outstansing",""&D$2&""),0) -> 0 | E23: =IFERROR(GETPIVOTDATA("Area AGM",#REF!,"Dealer",""&$S$18&"","Model",""&$B23&"","Umur Outstansing",""&E$2&""),0) -> 0 | F23: =IFERROR(GETPIVOTDATA("Area AGM",#REF!,"Dealer",""&$S$18&"","Model",""&$B23&"","Umur Outstansing",""&F$2&""),0) -> 0 | G23: =IFERROR(GETPIVOTDATA("Area AGM",#REF!,"Dealer",""&$S$18&"","Model",""&$B23&"","Umur Outstansing",""&G$2&""),0) -> 0 | H23: =IFERROR(GETPIVOTDATA("Area AGM",#REF!,"Dealer",""&$S$18&"","Model",""&$B23&"","Umur Outstansing",""&H$2&""),0) -> 0 | J23: =IFERROR(GETPIVOTDATA("Area AGM",#REF!,"Dealer",""&$S$18&"","Model",""&$B23&""),0) -> 0 | K23: =IFERROR(GETPIVOTDATA("Area AGM",#REF!,"Dealer",""&$S$18&"","Model",""&$B23&""),0) -> 0 | P23: Raize | Q23: =IFERROR(R23/AI23,0) -> 0 | R23: =IFERROR(GETPIVOTDATA("RS Target",#REF!,"Dealer",""&$S$18&"","Model",""&$P23&""),0) -> 0 | S23: Raize | T23: =SUM(Y23:AB23,AO23) -> 0 | U23: =IFERROR(GETPIVOTDATA("Area AGM",'Pvt OS'!#REF!,"Dealer",""&$S$18&"","Model",""&$S23&""),0) -> 0 | V23: =W23-X23 -> 0 | W23: =IFERROR(GETPIVOTDATA("Area AGM",'Pvt OS'!#REF!,"Dealer",""&$S$18&"","Model",""&$S23&""),0)+IFERROR(GETPIVOTDATA("Area AGM",'Pvt OS'!$A$8,"Dealer",""&$S$18&"","Model",""&$S23&""),0) -> 0 | X23: =SUM(Y23:AB23) -> 0 | Y23: =IFERROR(GETPIVOTDATA("Area AGM",'Pvt OS'!$U$8,"Dealer",""&$S$18&"","Model",""&$S23&""),0) -> 0 | Z23: =IFERROR(GETPIVOTDATA("Area AGM",'Pvt OS'!$M$8,"Dealer",""&$S$18&"","Model",""&$S23&""),0) -> 0 | AA23: =IFERROR(GETPIVOTDATA("Area AGM",'Pvt OS'!#REF!,"Dealer",""&$S$18&"","Model",""&$S23&""),0) -> 0 | AB23: =IFERROR(GETPIVOTDATA("Area AGM",'Pvt OS'!$AO$8,"Dealer",""&$S$18&"","Model",""&$S23&""),0) -> 0 | AC23: =IFERROR(GETPIVOTDATA("Stock",#REF!,"Dealer",""&$S$18&"","Model",""&$S23&""),0) -> 0 | AD23: =IFERROR(GETPIVOTDATA("MDP",#REF!,"Dealer",""&$S$18&"","Model",""&$S23&""),0) -> 0 | AE23: =IFERROR(GETPIVOTDATA("RRN",#REF!,"Model2",""&$S23&"","Dealer",""&$S$18&""),0) -> 0 | AF23: =IFERROR(GETPIVOTDATA("CO",#REF!,"Dealer Name",""&$S$18&"","Model",""&$S23&""),0) -> 0 | AG23: =IFERROR(GETPIVOTDATA("Sum of Distplan Final",#REF!,"Dealer",""&$S$18&"","Model",""&$S23&""),0) -> 0 | AH23: =IFERROR(GETPIVOTDATA("RRN",#REF!,"Model",""&$S23&"","Dealer",""&$S$18&""),0) -> 0 | AI23: =AC23+AD23+AF23+AG23-AH23 -> 0 | AJ23: =IFERROR(GETPIVOTDATA("volume_rs",#REF!,"Model",""&$S23&"","Dealer",""&$S$18&""),0) -> 0 | AK23: =AI23-AJ23-X23+AN23 -> 0 | AL23: =IFERROR(GETPIVOTDATA("Area AGM",'Pvt OS'!#REF!,"Dealer",""&$S$18&"","Model",""&$S23&""),0) -> 0 | AM23: =AK23+AL23 -> 0 | AN23: =IFERROR(GETPIVOTDATA("Row Labels",#REF!,"Dealer",""&$S$18&"","Model",""&$S23&""),0) -> 0 | AO23: =IFERROR(GETPIVOTDATA("RS Afi",#REF!,"Dealer",""&$S$18&"","Model",""&$S23&""),0) -> 0 | AP23: =IFERROR(GETPIVOTDATA("qty",#REF!,"Model",""&$S23&"","Dealer",""&$S$18&""),0) -> 0 | AQ23: =IFERROR(GETPIVOTDATA("volume_rs",#REF!,"Model",""&$S23&"","Dealer",""&$S$18&""),0) -> 0 | AR23: =AP23-AQ23 -> 0 | AS23: =IFERROR(GETPIVOTDATA("Area AGM",'Pvt OS'!#REF!,"Dealer",""&$S$18&"","Model",""&$S23&""),0) -> 0 | AT23: =AR23-AS23 -> 0 | BA23: =#REF! -> #REF! | BB23: =#REF! -> #REF! | BC23: =#REF! -> #REF! | BD23: =#REF! -> #REF!
B24: C-HR | C24: =SUM(D24:G24) -> 0 | D24: =IFERROR(GETPIVOTDATA("Area AGM",#REF!,"Dealer",""&$S$18&"","Model",""&$B24&"","Umur Outstansing",""&D$2&""),0) -> 0 | E24: =IFERROR(GETPIVOTDATA("Area AGM",#REF!,"Dealer",""&$S$18&"","Model",""&$B24&"","Umur Outstansing",""&E$2&""),0) -> 0 | F24: =IFERROR(GETPIVOTDATA("Area AGM",#REF!,"Dealer",""&$S$18&"","Model",""&$B24&"","Umur Outstansing",""&F$2&""),0) -> 0 | G24: =IFERROR(GETPIVOTDATA("Area AGM",#REF!,"Dealer",""&$S$18&"","Model",""&$B24&"","Umur Outstansing",""&G$2&""),0) -> 0 | H24: =IFERROR(GETPIVOTDATA("Area AGM",#REF!,"Dealer",""&$S$18&"","Model",""&$B24&"","Umur Outstansing",""&H$2&""),0) -> 0 | J24: =IFERROR(GETPIVOTDATA("Area AGM",#REF!,"Dealer",""&$S$18&"","Model",""&$B24&""),0) -> 0 | K24: =IFERROR(GETPIVOTDATA("Area AGM",#REF!,"Dealer",""&$S$18&"","Model",""&$B24&""),0) -> 0 | P24: Agya | Q24: =IFERROR(R24/AI24,0) -> 0 | R24: =IFERROR(GETPIVOTDATA("RS Target",#REF!,"Dealer",""&$S$18&"","Model",""&$P24&""),0) -> 0 | S24: Agya | T24: =SUM(Y24:AB24,AO24) -> 0 | U24: =IFERROR(GETPIVOTDATA("Area AGM",'Pvt OS'!#REF!,"Dealer",""&$S$18&"","Model",""&$S24&""),0) -> 0 | V24: =W24-X24 -> 0 | W24: =IFERROR(GETPIVOTDATA("Area AGM",'Pvt OS'!#REF!,"Dealer",""&$S$18&"","Model",""&$S24&""),0)+IFERROR(GETPIVOTDATA("Area AGM",'Pvt OS'!$A$8,"Dealer",""&$S$18&"","Model",""&$S24&""),0) -> 0 | X24: =SUM(Y24:AB24) -> 0 | Y24: =IFERROR(GETPIVOTDATA("Area AGM",'Pvt OS'!$U$8,"Dealer",""&$S$18&"","Model",""&$S24&""),0) -> 0 | Z24: =IFERROR(GETPIVOTDATA("Area AGM",'Pvt OS'!$M$8,"Dealer",""&$S$18&"","Model",""&$S24&""),0) -> 0 | AA24: =IFERROR(GETPIVOTDATA("Area AGM",'Pvt OS'!#REF!,"Dealer",""&$S$18&"","Model",""&$S24&""),0) -> 0 | AB24: =IFERROR(GETPIVOTDATA("Area AGM",'Pvt OS'!$AO$8,"Dealer",""&$S$18&"","Model",""&$S24&""),0) -> 0 | AC24: =IFERROR(GETPIVOTDATA("Stock",#REF!,"Dealer",""&$S$18&"","Model",""&$S24&""),0) -> 0 | AD24: =IFERROR(GETPIVOTDATA("MDP",#REF!,"Dealer",""&$S$18&"","Model",""&$S24&""),0) -> 0 | AE24: =IFERROR(GETPIVOTDATA("RRN",#REF!,"Model2",""&$S24&"","Dealer",""&$S$18&""),0) -> 0 | AF24: =IFERROR(GETPIVOTDATA("CO",#REF!,"Dealer Name",""&$S$18&"","Model",""&$S24&""),0) -> 0 | AG24: =IFERROR(GETPIVOTDATA("Sum of Distplan Final",#REF!,"Dealer",""&$S$18&"","Model",""&$S24&""),0) -> 0 | AH24: =IFERROR(GETPIVOTDATA("RRN",#REF!,"Model",""&$S24&"","Dealer",""&$S$18&""),0) -> 0 | AI24: =AC24+AD24+AF24+AG24-AH24 -> 0 | AJ24: =IFERROR(GETPIVOTDATA("volume_rs",#REF!,"Model",""&$S24&"","Dealer",""&$S$18&""),0) -> 0 | AK24: =AI24-AJ24-X24+AN24 -> 0 | AL24: =IFERROR(GETPIVOTDATA("Area AGM",'Pvt OS'!#REF!,"Dealer",""&$S$18&"","Model",""&$S24&""),0) -> 0 | AM24: =AK24+AL24 -> 0 | AN24: =IFERROR(GETPIVOTDATA("Row Labels",#REF!,"Dealer",""&$S$18&"","Model",""&$S24&""),0) -> 0 | AO24: =IFERROR(GETPIVOTDATA("RS Afi",#REF!,"Dealer",""&$S$18&"","Model",""&$S24&""),0) -> 0 | AP24: =IFERROR(GETPIVOTDATA("qty",#REF!,"Model",""&$S24&"","Dealer",""&$S$18&""),0) -> 0 | AQ24: =IFERROR(GETPIVOTDATA("volume_rs",#REF!,"Model",""&$S24&"","Dealer",""&$S$18&""),0) -> 0 | AR24: =AP24-AQ24 -> 0 | AS24: =IFERROR(GETPIVOTDATA("Area AGM",'Pvt OS'!#REF!,"Dealer",""&$S$18&"","Model",""&$S24&""),0) -> 0 | AT24: =AR24-AS24 -> 0 | BA24: =#REF! -> #REF! | BB24: =#REF! -> #REF! | BC24: =#REF! -> #REF! | BD24: =#REF! -> #REF!
B25: C-HR HYBRID | C25: =SUM(D25:G25) -> 0 | D25: =IFERROR(GETPIVOTDATA("Area AGM",#REF!,"Dealer",""&$S$18&"","Model",""&$B25&"","Umur Outstansing",""&D$2&""),0) -> 0 | E25: =IFERROR(GETPIVOTDATA("Area AGM",#REF!,"Dealer",""&$S$18&"","Model",""&$B25&"","Umur Outstansing",""&E$2&""),0) -> 0 | F25: =IFERROR(GETPIVOTDATA("Area AGM",#REF!,"Dealer",""&$S$18&"","Model",""&$B25&"","Umur Outstansing",""&F$2&""),0) -> 0 | G25: =IFERROR(GETPIVOTDATA("Area AGM",#REF!,"Dealer",""&$S$18&"","Model",""&$B25&"","Umur Outstansing",""&G$2&""),0) -> 0 | H25: =IFERROR(GETPIVOTDATA("Area AGM",#REF!,"Dealer",""&$S$18&"","Model",""&$B25&"","Umur Outstansing",""&H$2&""),0) -> 0 | J25: =IFERROR(GETPIVOTDATA("Area AGM",#REF!,"Dealer",""&$S$18&"","Model",""&$B25&""),0) -> 0 | K25: =IFERROR(GETPIVOTDATA("Area AGM",#REF!,"Dealer",""&$S$18&"","Model",""&$B25&""),0) -> 0 | P25: Calya | Q25: =IFERROR(R25/AI25,0) -> 0 | R25: =IFERROR(GETPIVOTDATA("RS Target",#REF!,"Dealer",""&$S$18&"","Model",""&$P25&""),0) -> 0 | S25: Calya | T25: =SUM(Y25:AB25,AO25) -> 0 | U25: =IFERROR(GETPIVOTDATA("Area AGM",'Pvt OS'!#REF!,"Dealer",""&$S$18&"","Model",""&$S25&""),0) -> 0 | V25: =W25-X25 -> 0 | W25: =IFERROR(GETPIVOTDATA("Area AGM",'Pvt OS'!#REF!,"Dealer",""&$S$18&"","Model",""&$S25&""),0)+IFERROR(GETPIVOTDATA("Area AGM",'Pvt OS'!$A$8,"Dealer",""&$S$18&"","Model",""&$S25&""),0) -> 0 | X25: =SUM(Y25:AB25) -> 0 | Y25: =IFERROR(GETPIVOTDATA("Area AGM",'Pvt OS'!$U$8,"Dealer",""&$S$18&"","Model",""&$S25&""),0) -> 0 | Z25: =IFERROR(GETPIVOTDATA("Area AGM",'Pvt OS'!$M$8,"Dealer",""&$S$18&"","Model",""&$S25&""),0) -> 0 | AA25: =IFERROR(GETPIVOTDATA("Area AGM",'Pvt OS'!#REF!,"Dealer",""&$S$18&"","Model",""&$S25&""),0) -> 0 | AB25: =IFERROR(GETPIVOTDATA("Area AGM",'Pvt OS'!$AO$8,"Dealer",""&$S$18&"","Model",""&$S25&""),0) -> 0 | AC25: =IFERROR(GETPIVOTDATA("Stock",#REF!,"Dealer",""&$S$18&"","Model",""&$S25&""),0) -> 0 | AD25: =IFERROR(GETPIVOTDATA("MDP",#REF!,"Dealer",""&$S$18&"","Model",""&$S25&""),0) -> 0 | AE25: =IFERROR(GETPIVOTDATA("RRN",#REF!,"Model2",""&$S25&"","Dealer",""&$S$18&""),0) -> 0 | AF25: =IFERROR(GETPIVOTDATA("CO",#REF!,"Dealer Name",""&$S$18&"","Model",""&$S25&""),0) -> 0 | AG25: =IFERROR(GETPIVOTDATA("Sum of Distplan Final",#REF!,"Dealer",""&$S$18&"","Model",""&$S25&""),0) -> 0 | AH25: =IFERROR(GETPIVOTDATA("RRN",#REF!,"Model",""&$S25&"","Dealer",""&$S$18&""),0) -> 0 | AI25: =AC25+AD25+AF25+AG25-AH25 -> 0 | AJ25: =IFERROR(GETPIVOTDATA("volume_rs",#REF!,"Model",""&$S25&"","Dealer",""&$S$18&""),0) -> 0 | AK25: =AI25-AJ25-X25+AN25 -> 0 | AL25: =IFERROR(GETPIVOTDATA("Area AGM",'Pvt OS'!#REF!,"Dealer",""&$S$18&"","Model",""&$S25&""),0) -> 0 | AM25: =AK25+AL25 -> 0 | AN25: =IFERROR(GETPIVOTDATA("Row Labels",#REF!,"Dealer",""&$S$18&"","Model",""&$S25&""),0) -> 0 | AO25: =IFERROR(GETPIVOTDATA("RS Afi",#REF!,"Dealer",""&$S$18&"","Model",""&$S25&""),0) -> 0 | AP25: =IFERROR(GETPIVOTDATA("qty",#REF!,"Model",""&$S25&"","Dealer",""&$S$18&""),0) -> 0 | AQ25: =IFERROR(GETPIVOTDATA("volume_rs",#REF!,"Model",""&$S25&"","Dealer",""&$S$18&""),0) -> 0 | AR25: =AP25-AQ25 -> 0 | AS25: =IFERROR(GETPIVOTDATA("Area AGM",'Pvt OS'!#REF!,"Dealer",""&$S$18&"","Model",""&$S25&""),0) -> 0 | AT25: =AR25-AS25 -> 0 | BA25: =#REF! -> #REF! | BB25: =#REF! -> #REF! | BC25: =#REF! -> #REF! | BD25: =#REF! -> #REF!
B26: CAMRY | C26: =SUM(D26:G26) -> 0 | D26: =IFERROR(GETPIVOTDATA("Area AGM",#REF!,"Dealer",""&$S$18&"","Model",""&$B26&"","Umur Outstansing",""&D$2&""),0) -> 0 | E26: =IFERROR(GETPIVOTDATA("Area AGM",#REF!,"Dealer",""&$S$18&"","Model",""&$B26&"","Umur Outstansing",""&E$2&""),0) -> 0 | F26: =IFERROR(GETPIVOTDATA("Area AGM",#REF!,"Dealer",""&$S$18&"","Model",""&$B26&"","Umur Outstansing",""&F$2&""),0) -> 0 | G26: =IFERROR(GETPIVOTDATA("Area AGM",#REF!,"Dealer",""&$S$18&"","Model",""&$B26&"","Umur Outstansing",""&G$2&""),0) -> 0 | H26: =IFERROR(GETPIVOTDATA("Area AGM",#REF!,"Dealer",""&$S$18&"","Model",""&$B26&"","Umur Outstansing",""&H$2&""),0) -> 0 | J26: =IFERROR(GETPIVOTDATA("Area AGM",#REF!,"Dealer",""&$S$18&"","Model",""&$B26&""),0) -> 0 | K26: =IFERROR(GETPIVOTDATA("Area AGM",#REF!,"Dealer",""&$S$18&"","Model",""&$B26&""),0) -> 0 | P26: Yaris | Q26: =IFERROR(R26/AI26,0) -> 0 | R26: =IFERROR(GETPIVOTDATA("RS Target",#REF!,"Dealer",""&$S$18&"","Model",""&$P26&""),0) -> 0 | S26: Yaris | T26: =SUM(Y26:AB26,AO26) -> 0 | U26: =IFERROR(GETPIVOTDATA("Area AGM",'Pvt OS'!#REF!,"Dealer",""&$S$18&"","Model",""&$S26&""),0) -> 0 | V26: =W26-X26 -> 0 | W26: =IFERROR(GETPIVOTDATA("Area AGM",'Pvt OS'!#REF!,"Dealer",""&$S$18&"","Model",""&$S26&""),0)+IFERROR(GETPIVOTDATA("Area AGM",'Pvt OS'!$A$8,"Dealer",""&$S$18&"","Model",""&$S26&""),0) -> 0 | X26: =SUM(Y26:AB26) -> 0 | Y26: =IFERROR(GETPIVOTDATA("Area AGM",'Pvt OS'!$U$8,"Dealer",""&$S$18&"","Model",""&$S26&""),0) -> 0 | Z26: =IFERROR(GETPIVOTDATA("Area AGM",'Pvt OS'!$M$8,"Dealer",""&$S$18&"","Model",""&$S26&""),0) -> 0 | AA26: =IFERROR(GETPIVOTDATA("Area AGM",'Pvt OS'!#REF!,"Dealer",""&$S$18&"","Model",""&$S26&""),0) -> 0 | AB26: =IFERROR(GETPIVOTDATA("Area AGM",'Pvt OS'!$AO$8,"Dealer",""&$S$18&"","Model",""&$S26&""),0) -> 0 | AC26: =IFERROR(GETPIVOTDATA("Stock",#REF!,"Dealer",""&$S$18&"","Model",""&$S26&""),0) -> 0 | AD26: =IFERROR(GETPIVOTDATA("MDP",#REF!,"Dealer",""&$S$18&"","Model",""&$S26&""),0) -> 0 | AE26: =IFERROR(GETPIVOTDATA("RRN",#REF!,"Model2",""&$S26&"","Dealer",""&$S$18&""),0) -> 0 | AF26: =IFERROR(GETPIVOTDATA("CO",#REF!,"Dealer Name",""&$S$18&"","Model",""&$S26&""),0) -> 0 | AG26: =IFERROR(GETPIVOTDATA("Sum of Distplan Final",#REF!,"Dealer",""&$S$18&"","Model",""&$S26&""),0) -> 0 | AH26: =IFERROR(GETPIVOTDATA("RRN",#REF!,"Model",""&$S26&"","Dealer",""&$S$18&""),0) -> 0 | AI26: =AC26+AD26+AF26+AG26-AH26 -> 0 | AJ26: =IFERROR(GETPIVOTDATA("volume_rs",#REF!,"Model",""&$S26&"","Dealer",""&$S$18&""),0) -> 0 | AK26: =AI26-AJ26-X26+AN26 -> 0 | AL26: =IFERROR(GETPIVOTDATA("Area AGM",'Pvt OS'!#REF!,"Dealer",""&$S$18&"","Model",""&$S26&""),0) -> 0 | AM26: =AK26+AL26 -> 0 | AN26: =IFERROR(GETPIVOTDATA("Row Labels",#REF!,"Dealer",""&$S$18&"","Model",""&$S26&""),0) -> 0 | AO26: =IFERROR(GETPIVOTDATA("RS Afi",#REF!,"Dealer",""&$S$18&"","Model",""&$S26&""),0) -> 0 | AP26: =IFERROR(GETPIVOTDATA("qty",#REF!,"Model",""&$S26&"","Dealer",""&$S$18&""),0) -> 0 | AQ26: =IFERROR(GETPIVOTDATA("volume_rs",#REF!,"Model",""&$S26&"","Dealer",""&$S$18&""),0) -> 0 | AR26: =AP26-AQ26 -> 0 | AS26: =IFERROR(GETPIVOTDATA("Area AGM",'Pvt OS'!#REF!,"Dealer",""&$S$18&"","Model",""&$S26&""),0) -> 0 | AT26: =AR26-AS26 -> 0 | BA26: =#REF! -> #REF! | BB26: =#REF! -> #REF! | BC26: =#REF! -> #REF! | BD26: =#REF! -> #REF!
B27: DYNA | C27: =SUM(D27:G27) -> 0 | D27: =IFERROR(GETPIVOTDATA("Area AGM",#REF!,"Dealer",""&$S$18&"","Model",""&$B27&"","Umur Outstansing",""&D$2&""),0) -> 0 | E27: =IFERROR(GETPIVOTDATA("Area AGM",#REF!,"Dealer",""&$S$18&"","Model",""&$B27&"","Umur Outstansing",""&E$2&""),0) -> 0 | F27: =IFERROR(GETPIVOTDATA("Area AGM",#REF!,"Dealer",""&$S$18&"","Model",""&$B27&"","Umur Outstansing",""&F$2&""),0) -> 0 | G27: =IFERROR(GETPIVOTDATA("Area AGM",#REF!,"Dealer",""&$S$18&"","Model",""&$B27&"","Umur Outstansing",""&G$2&""),0) -> 0 | H27: =IFERROR(GETPIVOTDATA("Area AGM",#REF!,"Dealer",""&$S$18&"","Model",""&$B27&"","Umur Outstansing",""&H$2&""),0) -> 0 | J27: =IFERROR(GETPIVOTDATA("Area AGM",#REF!,"Dealer",""&$S$18&"","Model",""&$B27&""),0) -> 0 | K27: =IFERROR(GETPIVOTDATA("Area AGM",#REF!,"Dealer",""&$S$18&"","Model",""&$B27&""),0) -> 0 | P27: Innova | Q27: =IFERROR(R27/AI27,0) -> 0 | R27: =IFERROR(GETPIVOTDATA("RS Target",#REF!,"Dealer",""&$S$18&"","Model",""&$P27&""),0) -> 0 | S27: Innova | T27: =SUM(Y27:AB27,AO27) -> 0 | U27: =IFERROR(GETPIVOTDATA("Area AGM",'Pvt OS'!#REF!,"Dealer",""&$S$18&"","Model",""&$S27&""),0) -> 0 | V27: =W27-X27 -> 0 | W27: =IFERROR(GETPIVOTDATA("Area AGM",'Pvt OS'!#REF!,"Dealer",""&$S$18&"","Model",""&$S27&""),0)+IFERROR(GETPIVOTDATA("Area AGM",'Pvt OS'!$A$8,"Dealer",""&$S$18&"","Model",""&$S27&""),0) -> 0 | X27: =SUM(Y27:AB27) -> 0 | Y27: =IFERROR(GETPIVOTDATA("Area AGM",'Pvt OS'!$U$8,"Dealer",""&$S$18&"","Model",""&$S27&""),0) -> 0 | Z27: =IFERROR(GETPIVOTDATA("Area AGM",'Pvt OS'!$M$8,"Dealer",""&$S$18&"","Model",""&$S27&""),0) -> 0 | AA27: =IFERROR(GETPIVOTDATA("Area AGM",'Pvt OS'!#REF!,"Dealer",""&$S$18&"","Model",""&$S27&""),0) -> 0 | AB27: =IFERROR(GETPIVOTDATA("Area AGM",'Pvt OS'!$AO$8,"Dealer",""&$S$18&"","Model",""&$S27&""),0) -> 0 | AC27: =IFERROR(GETPIVOTDATA("Stock",#REF!,"Dealer",""&$S$18&"","Model",""&$S27&""),0) -> 0 | AD27: =IFERROR(GETPIVOTDATA("MDP",#REF!,"Dealer",""&$S$18&"","Model",""&$S27&""),0) -> 0 | AE27: =IFERROR(GETPIVOTDATA("RRN",#REF!,"Model2",""&$S27&"","Dealer",""&$S$18&""),0) -> 0 | AF27: =IFERROR(GETPIVOTDATA("CO",#REF!,"Dealer Name",""&$S$18&"","Model",""&$S27&""),0) -> 0 | AG27: =IFERROR(GETPIVOTDATA("Sum of Distplan Final",#REF!,"Dealer",""&$S$18&"","Model",""&$S27&""),0) -> 0 | AH27: =IFERROR(GETPIVOTDATA("RRN",#REF!,"Model",""&$S27&"","Dealer",""&$S$18&""),0) -> 0 | AI27: =AC27+AD27+AF27+AG27-AH27 -> 0 | AJ27: =IFERROR(GETPIVOTDATA("volume_rs",#REF!,"Model",""&$S27&"","Dealer",""&$S$18&""),0) -> 0 | AK27: =AI27-AJ27-X27+AN27 -> 0 | AL27: =IFERROR(GETPIVOTDATA("Area AGM",'Pvt OS'!#REF!,"Dealer",""&$S$18&"","Model",""&$S27&""),0) -> 0 | AM27: =AK27+AL27 -> 0 | AN27: =IFERROR(GETPIVOTDATA("Row Labels",#REF!,"Dealer",""&$S$18&"","Model",""&$S27&""),0) -> 0 | AO27: =IFERROR(GETPIVOTDATA("RS Afi",#REF!,"Dealer",""&$S$18&"","Model",""&$S27&""),0) -> 0 | AP27: =IFERROR(GETPIVOTDATA("qty",#REF!,"Model",""&$S27&"","Dealer",""&$S$18&""),0) -> 0 | AQ27: =IFERROR(GETPIVOTDATA("volume_rs",#REF!,"Model",""&$S27&"","Dealer",""&$S$18&""),0) -> 0 | AR27: =AP27-AQ27 -> 0 | AS27: =IFERROR(GETPIVOTDATA("Area AGM",'Pvt OS'!#REF!,"Dealer",""&$S$18&"","Model",""&$S27&""),0) -> 0 | AT27: =AR27-AS27 -> 0 | BA27: =#REF! -> #REF! | BB27: =#REF! -> #REF! | BC27: =#REF! -> #REF! | BD27: =#REF! -> #REF!
B28: FORTUNER 4X4 | C28: =SUM(D28:G28) -> 0 | D28: =IFERROR(GETPIVOTDATA("Area AGM",#REF!,"Dealer",""&$S$18&"","Model",""&$B28&"","Umur Outstansing",""&D$2&""),0) -> 0 | E28: =IFERROR(GETPIVOTDATA("Area AGM",#REF!,"Dealer",""&$S$18&"","Model",""&$B28&"","Umur Outstansing",""&E$2&""),0) -> 0 | F28: =IFERROR(GETPIVOTDATA("Area AGM",#REF!,"Dealer",""&$S$18&"","Model",""&$B28&"","Umur Outstansing",""&F$2&""),0) -> 0 | G28: =IFERROR(GETPIVOTDATA("Area AGM",#REF!,"Dealer",""&$S$18&"","Model",""&$B28&"","Umur Outstansing",""&G$2&""),0) -> 0 | H28: =IFERROR(GETPIVOTDATA("Area AGM",#REF!,"Dealer",""&$S$18&"","Model",""&$B28&"","Umur Outstansing",""&H$2&""),0) -> 0 | J28: =IFERROR(GETPIVOTDATA("Area AGM",#REF!,"Dealer",""&$S$18&"","Model",""&$B28&""),0) -> 0 | K28: =IFERROR(GETPIVOTDATA("Area AGM",#REF!,"Dealer",""&$S$18&"","Model",""&$B28&""),0) -> 0 | P28: Fortuner 4x2 | Q28: =IFERROR(R28/AI28,0) -> 0 | R28: =IFERROR(GETPIVOTDATA("RS Target",#REF!,"Dealer",""&$S$18&"","Model",""&$P28&""),0) -> 0 | S28: Fortuner 4x2 | T28: =SUM(Y28:AB28,AO28) -> 0 | U28: =IFERROR(GETPIVOTDATA("Area AGM",'Pvt OS'!#REF!,"Dealer",""&$S$18&"","Model",""&$S28&""),0) -> 0 | V28: =W28-X28 -> 0 | W28: =IFERROR(GETPIVOTDATA("Area AGM",'Pvt OS'!#REF!,"Dealer",""&$S$18&"","Model",""&$S28&""),0)+IFERROR(GETPIVOTDATA("Area AGM",'Pvt OS'!$A$8,"Dealer",""&$S$18&"","Model",""&$S28&""),0) -> 0 | X28: =SUM(Y28:AB28) -> 0 | Y28: =IFERROR(GETPIVOTDATA("Area AGM",'Pvt OS'!$U$8,"Dealer",""&$S$18&"","Model",""&$S28&""),0) -> 0 | Z28: =IFERROR(GETPIVOTDATA("Area AGM",'Pvt OS'!$M$8,"Dealer",""&$S$18&"","Model",""&$S28&""),0) -> 0 | AA28: =IFERROR(GETPIVOTDATA("Area AGM",'Pvt OS'!#REF!,"Dealer",""&$S$18&"","Model",""&$S28&""),0) -> 0 | AB28: =IFERROR(GETPIVOTDATA("Area AGM",'Pvt OS'!$AO$8,"Dealer",""&$S$18&"","Model",""&$S28&""),0) -> 0 | AC28: =IFERROR(GETPIVOTDATA("Stock",#REF!,"Dealer",""&$S$18&"","Model",""&$S28&""),0) -> 0 | AD28: =IFERROR(GETPIVOTDATA("MDP",#REF!,"Dealer",""&$S$18&"","Model",""&$S28&""),0) -> 0 | AE28: =IFERROR(GETPIVOTDATA("RRN",#REF!,"Model2",""&$S28&"","Dealer",""&$S$18&""),0) -> 0 | AF28: =IFERROR(GETPIVOTDATA("CO",#REF!,"Dealer Name",""&$S$18&"","Model",""&$S28&""),0) -> 0 | AG28: =IFERROR(GETPIVOTDATA("Sum of Distplan Final",#REF!,"Dealer",""&$S$18&"","Model",""&$S28&""),0) -> 0 | AH28: =IFERROR(GETPIVOTDATA("RRN",#REF!,"Model",""&$S28&"","Dealer",""&$S$18&""),0) -> 0 | AI28: =AC28+AD28+AF28+AG28-AH28 -> 0 | AJ28: =IFERROR(GETPIVOTDATA("volume_rs",#REF!,"Model",""&$S28&"","Dealer",""&$S$18&""),0) -> 0 | AK28: =AI28-AJ28-X28+AN28 -> 0 | AL28: =IFERROR(GETPIVOTDATA("Area AGM",'Pvt OS'!#REF!,"Dealer",""&$S$18&"","Model",""&$S28&""),0) -> 0 | AM28: =AK28+AL28 -> 0 | AN28: =IFERROR(GETPIVOTDATA("Row Labels",#REF!,"Dealer",""&$S$18&"","Model",""&$S28&""),0) -> 0 | AO28: =IFERROR(GETPIVOTDATA("RS Afi",#REF!,"Dealer",""&$S$18&"","Model",""&$S28&""),0) -> 0 | AP28: =IFERROR(GETPIVOTDATA("qty",#REF!,"Model",""&$S28&"","Dealer",""&$S$18&""),0) -> 0 | AQ28: =IFERROR(GETPIVOTDATA("volume_rs",#REF!,"Model",""&$S28&"","Dealer",""&$S$18&""),0) -> 0 | AR28: =AP28-AQ28 -> 0 | AS28: =IFERROR(GETPIVOTDATA("Area AGM",'Pvt OS'!#REF!,"Dealer",""&$S$18&"","Model",""&$S28&""),0) -> 0 | AT28: =AR28-AS28 -> 0 | BA28: =#REF! -> #REF! | BB28: =#REF! -> #REF! | BC28: =#REF! -> #REF! | BD28: =#REF! -> #REF!
B29: HIACE | C29: =SUM(D29:G29) -> 0 | D29: =IFERROR(GETPIVOTDATA("Area AGM",#REF!,"Dealer",""&$S$18&"","Model",""&$B29&"","Umur Outstansing",""&D$2&""),0) -> 0 | E29: =IFERROR(GETPIVOTDATA("Area AGM",#REF!,"Dealer",""&$S$18&"","Model",""&$B29&"","Umur Outstansing",""&E$2&""),0) -> 0 | F29: =IFERROR(GETPIVOTDATA("Area AGM",#REF!,"Dealer",""&$S$18&"","Model",""&$B29&"","Umur Outstansing",""&F$2&""),0) -> 0 | G29: =IFERROR(GETPIVOTDATA("Area AGM",#REF!,"Dealer",""&$S$18&"","Model",""&$B29&"","Umur Outstansing",""&G$2&""),0) -> 0 | H29: =IFERROR(GETPIVOTDATA("Area AGM",#REF!,"Dealer",""&$S$18&"","Model",""&$B29&"","Umur Outstansing",""&H$2&""),0) -> 0 | J29: =IFERROR(GETPIVOTDATA("Area AGM",#REF!,"Dealer",""&$S$18&"","Model",""&$B29&""),0) -> 0 | K29: =IFERROR(GETPIVOTDATA("Area AGM",#REF!,"Dealer",""&$S$18&"","Model",""&$B29&""),0) -> 0 | P29: Rush | Q29: =IFERROR(R29/AI29,0) -> 0 | R29: =IFERROR(GETPIVOTDATA("RS Target",#REF!,"Dealer",""&$S$18&"","Model",""&$P29&""),0) -> 0 | S29: Rush | T29: =SUM(Y29:AB29,AO29) -> 0 | U29: =IFERROR(GETPIVOTDATA("Area AGM",'Pvt OS'!#REF!,"Dealer",""&$S$18&"","Model",""&$S29&""),0) -> 0 | V29: =W29-X29 -> 0 | W29: =IFERROR(GETPIVOTDATA("Area AGM",'Pvt OS'!#REF!,"Dealer",""&$S$18&"","Model",""&$S29&""),0)+IFERROR(GETPIVOTDATA("Area AGM",'Pvt OS'!$A$8,"Dealer",""&$S$18&"","Model",""&$S29&""),0) -> 0 | X29: =SUM(Y29:AB29) -> 0 | Y29: =IFERROR(GETPIVOTDATA("Area AGM",'Pvt OS'!$U$8,"Dealer",""&$S$18&"","Model",""&$S29&""),0) -> 0 | Z29: =IFERROR(GETPIVOTDATA("Area AGM",'Pvt OS'!$M$8,"Dealer",""&$S$18&"","Model",""&$S29&""),0) -> 0 | AA29: =IFERROR(GETPIVOTDATA("Area AGM",'Pvt OS'!#REF!,"Dealer",""&$S$18&"","Model",""&$S29&""),0) -> 0 | AB29: =IFERROR(GETPIVOTDATA("Area AGM",'Pvt OS'!$AO$8,"Dealer",""&$S$18&"","Model",""&$S29&""),0) -> 0 | AC29: =IFERROR(GETPIVOTDATA("Stock",#REF!,"Dealer",""&$S$18&"","Model",""&$S29&""),0) -> 0 | AD29: =IFERROR(GETPIVOTDATA("MDP",#REF!,"Dealer",""&$S$18&"","Model",""&$S29&""),0) -> 0 | AE29: =IFERROR(GETPIVOTDATA("RRN",#REF!,"Model2",""&$S29&"","Dealer",""&$S$18&""),0) -> 0 | AF29: =IFERROR(GETPIVOTDATA("CO",#REF!,"Dealer Name",""&$S$18&"","Model",""&$S29&""),0) -> 0 | AG29: =IFERROR(GETPIVOTDATA("Sum of Distplan Final",#REF!,"Dealer",""&$S$18&"","Model",""&$S29&""),0) -> 0 | AH29: =IFERROR(GETPIVOTDATA("RRN",#REF!,"Model",""&$S29&"","Dealer",""&$S$18&""),0) -> 0 | AI29: =AC29+AD29+AF29+AG29-AH29 -> 0 | AJ29: =IFERROR(GETPIVOTDATA("volume_rs",#REF!,"Model",""&$S29&"","Dealer",""&$S$18&""),0) -> 0 | AK29: =AI29-AJ29-X29+AN29 -> 0 | AL29: =IFERROR(GETPIVOTDATA("Area AGM",'Pvt OS'!#REF!,"Dealer",""&$S$18&"","Model",""&$S29&""),0) -> 0 | AM29: =AK29+AL29 -> 0 | AN29: =IFERROR(GETPIVOTDATA("Row Labels",#REF!,"Dealer",""&$S$18&"","Model",""&$S29&""),0) -> 0 | AO29: =IFERROR(GETPIVOTDATA("RS Afi",#REF!,"Dealer",""&$S$18&"","Model",""&$S29&""),0) -> 0 | AP29: =IFERROR(GETPIVOTDATA("qty",#REF!,"Model",""&$S29&"","Dealer",""&$S$18&""),0) -> 0 | AQ29: =IFERROR(GETPIVOTDATA("volume_rs",#REF!,"Model",""&$S29&"","Dealer",""&$S$18&""),0) -> 0 | AR29: =AP29-AQ29 -> 0 | AS29: =IFERROR(GETPIVOTDATA("Area AGM",'Pvt OS'!#REF!,"Dealer",""&$S$18&"","Model",""&$S29&""),0) -> 0 | AT29: =AR29-AS29 -> 0 | BA29: =#REF! -> #REF! | BB29: =#REF! -> #REF! | BC29: =#REF! -> #REF! | BD29: =#REF! -> #REF!
B30: HILUX D-CAB | C30: =SUM(D30:G30) -> 0 | D30: =IFERROR(GETPIVOTDATA("Area AGM",#REF!,"Dealer",""&$S$18&"","Model",""&$B30&"","Umur Outstansing",""&D$2&""),0) -> 0 | E30: =IFERROR(GETPIVOTDATA("Area AGM",#REF!,"Dealer",""&$S$18&"","Model",""&$B30&"","Umur Outstansing",""&E$2&""),0) -> 0 | F30: =IFERROR(GETPIVOTDATA("Area AGM",#REF!,"Dealer",""&$S$18&"","Model",""&$B30&"","Umur Outstansing",""&F$2&""),0) -> 0 | G30: =IFERROR(GETPIVOTDATA("Area AGM",#REF!,"Dealer",""&$S$18&"","Model",""&$B30&"","Umur Outstansing",""&G$2&""),0) -> 0 | H30: =IFERROR(GETPIVOTDATA("Area AGM",#REF!,"Dealer",""&$S$18&"","Model",""&$B30&"","Umur Outstansing",""&H$2&""),0) -> 0 | J30: =IFERROR(GETPIVOTDATA("Area AGM",#REF!,"Dealer",""&$S$18&"","Model",""&$B30&""),0) -> 0 | K30: =IFERROR(GETPIVOTDATA("Area AGM",#REF!,"Dealer",""&$S$18&"","Model",""&$B30&""),0) -> 0 | P30: Others | Q30: =IFERROR(R30/AI30,0) -> 0 | R30: =R31-SUM(R21:R29) -> 0 | S30: Others | T30: =SUM(Y30:AB30,AO30) -> 0 | U30: =U31-SUM(U21:U29) -> 0 | V30: =W30-X30 -> 0 | W30: =W31-SUM(W21:W29) -> 0 | X30: =SUM(Y30:AB30) -> 0 | Y30: =Y31-SUM(Y21:Y29) -> 0 | Z30: =Z31-SUM(Z21:Z29) -> 0 | AA30: =AA31-SUM(AA21:AA29) -> 0 | AB30: =AB31-SUM(AB21:AB29) -> 0 | AC30: =AC31-SUM(AC21:AC29) -> 0 | AD30: =AD31-SUM(AD21:AD29) -> 0 | AE30: =AE31-SUM(AE21:AE29) -> 0 | AF30: =AF31-SUM(AF21:AF29) -> 0 | ... AH30: =AH31-SUM(AH21:AH29) -> 0 | AI30: =AC30+AD30+AF30+AG30-AH30 -> 0 | AJ30: =AJ31-SUM(AJ21:AJ29) -> 0 | AK30: =AI30-AJ30-X30+AN30 -> 0 | AL30: =AL31-SUM(AL21:AL29) -> 0 | AM30: =AK30+AL30 -> 0 | AN30: =AN31-SUM(AN21:AN29) -> 0 | AO30: =AO31-SUM(AO21:AO29) -> 0 | AP30: =AP31-SUM(AP21:AP29) -> 0 | AQ30: =AQ31-SUM(AQ21:AQ29) -> 0 | AR30: =AP30-AQ30 -> 0 | AS30: =AS31-SUM(AS21:AS29) -> 0 | AT30: =AR30-AS30 -> 0 | BA30: =#REF! -> #REF! | BB30: =#REF! -> #REF! | BC30: =#REF! -> #REF! | BD30: =#REF! -> #REF!
B31: HILUX S-CAB | C31: =SUM(D31:G31) -> 0 | D31: =IFERROR(GETPIVOTDATA("Area AGM",#REF!,"Dealer",""&$S$18&"","Model",""&$B31&"","Umur Outstansing",""&D$2&""),0) -> 0 | E31: =IFERROR(GETPIVOTDATA("Area AGM",#REF!,"Dealer",""&$S$18&"","Model",""&$B31&"","Umur Outstansing",""&E$2&""),0) -> 0 | F31: =IFERROR(GETPIVOTDATA("Area AGM",#REF!,"Dealer",""&$S$18&"","Model",""&$B31&"","Umur Outstansing",""&F$2&""),0) -> 0 | G31: =IFERROR(GETPIVOTDATA("Area AGM",#REF!,"Dealer",""&$S$18&"","Model",""&$B31&"","Umur Outstansing",""&G$2&""),0) -> 0 | H31: =IFERROR(GETPIVOTDATA("Area AGM",#REF!,"Dealer",""&$S$18&"","Model",""&$B31&"","Umur Outstansing",""&H$2&""),0) -> 0 | J31: =IFERROR(GETPIVOTDATA("Area AGM",#REF!,"Dealer",""&$S$18&"","Model",""&$B31&""),0) -> 0 | K31: =IFERROR(GETPIVOTDATA("Area AGM",#REF!,"Dealer",""&$S$18&"","Model",""&$B31&""),0) -> 0 | P31: Grand Total | Q31: =IFERROR(R31/AI31,0) -> 0 | R31: =IFERROR(GETPIVOTDATA("RS Target",#REF!,"Dealer",""&$S$18&""),0) -> 0 | S31: Grand Total | T31: =SUM(Y31:AB31,AO31) -> 0 | U31: =IFERROR(GETPIVOTDATA("Area AGM",'Pvt OS'!#REF!,"Dealer",""&$S$18&""),0) -> 0 | V31: =W31-X31 -> 0 | W31: =IFERROR(GETPIVOTDATA("Area AGM",'Pvt OS'!#REF!,"Dealer",""&$S$18&""),0)+IFERROR(GETPIVOTDATA("Area AGM",'Pvt OS'!$A$8,"Dealer",""&$S$18&""),0) -> 0 | X31: =SUM(Y31:AB31) -> 0 | Y31: =IFERROR(GETPIVOTDATA("Area AGM",'Pvt OS'!$U$8,"Dealer",""&$S$18&""),0) -> 0 | Z31: =IFERROR(GETPIVOTDATA("Area AGM",'Pvt OS'!$M$8,"Dealer",""&$S$18&""),0) -> 0 | AA31: =IFERROR(GETPIVOTDATA("Area AGM",'Pvt OS'!#REF!,"Dealer",""&$S$18&""),0) -> 0 | AB31: =IFERROR(GETPIVOTDATA("Area AGM",'Pvt OS'!$AO$8,"Dealer",""&$S$18&""),0) -> 0 | AC31: =IFERROR(GETPIVOTDATA("Stock",#REF!,"Dealer",""&$S$18&""),0) -> 0 | AD31: =IFERROR(GETPIVOTDATA("MDP",#REF!,"Dealer",""&$S$18&""),0) -> 0 | AE31: =IFERROR(GETPIVOTDATA("RRN",#REF!,"Dealer",""&$S$18&""),0) -> 0 | AF31: =IFERROR(GETPIVOTDATA("CO",#REF!,"Dealer Name",""&$S$18&""),0) -> 0 | AG31: =IFERROR(GETPIVOTDATA("Sum of Distplan Final",#REF!,"Dealer",""&$S$18&""),0) -> 0 | AH31: =IFERROR(GETPIVOTDATA("RRN",#REF!,"Dealer",""&$S$18&""),0) -> 0 | AI31: =AC31+AD31+AF31+AG31-AH31 -> 0 | AJ31: =IFERROR(GETPIVOTDATA("volume_rs",#REF!,"Dealer",""&$S$18&""),0) -> 0 | AK31: =AI31-AJ31-X31+AN31 -> 0 | AL31: =IFERROR(GETPIVOTDATA("Area AGM",'Pvt OS'!#REF!,"Dealer",""&$S$18&""),0) -> 0 | AM31: ='AO Report(0)'!#REF! -> #REF! | AN31: =IFERROR(GETPIVOTDATA("Row Labels",#REF!,"Dealer",""&$S$18&""),0) -> 0 | AO31: =IFERROR(GETPIVOTDATA("RS Afi",#REF!,"Dealer",""&$S$18&""),0) -> 0 | AP31: =IFERROR(GETPIVOTDATA("qty",#REF!,"Dealer",""&$S$18&""),0) -> 0 | AQ31: =IFERROR(GETPIVOTDATA("volume_rs",#REF!,"Dealer",""&$S$18&""),0) -> 0 | AR31: =AP31-AQ31 -> 0 | AS31: =IFERROR(GETPIVOTDATA("Area AGM",'Pvt OS'!#REF!,"Dealer",""&$S$18&""),0) -> 0 | AT31: =AR31-AS31 -> 0 | BA31: =#REF! -> #REF! | BB31: =#REF! -> #REF! | BC31: =#REF! -> #REF! | BD31: =#REF! -> #REF!
B32: TRANSMOVER | C32: =SUM(D32:G32) -> 0 | D32: =IFERROR(GETPIVOTDATA("Area AGM",#REF!,"Dealer",""&$S$18&"","Model",""&$B32&"","Umur Outstansing",""&D$2&""),0) -> 0 | E32: =IFERROR(GETPIVOTDATA("Area AGM",#REF!,"Dealer",""&$S$18&"","Model",""&$B32&"","Umur Outstansing",""&E$2&""),0) -> 0 | F32: =IFERROR(GETPIVOTDATA("Area AGM",#REF!,"Dealer",""&$S$18&"","Model",""&$B32&"","Umur Outstansing",""&F$2&""),0) -> 0 | G32: =IFERROR(GETPIVOTDATA("Area AGM",#REF!,"Dealer",""&$S$18&"","Model",""&$B32&"","Umur Outstansing",""&G$2&""),0) -> 0 | H32: =IFERROR(GETPIVOTDATA("Area AGM",#REF!,"Dealer",""&$S$18&"","Model",""&$B32&"","Umur Outstansing",""&H$2&""),0) -> 0 | J32: =IFERROR(GETPIVOTDATA("Area AGM",#REF!,"Dealer",""&$S$18&"","Model",""&$B32&""),0) -> 0 | K32: =IFERROR(GETPIVOTDATA("Area AGM",#REF!,"Dealer",""&$S$18&"","Model",""&$B32&""),0) -> 0
B33: VELLFIRE | C33: =SUM(D33:G33) -> 0 | D33: =IFERROR(GETPIVOTDATA("Area AGM",#REF!,"Dealer",""&$S$18&"","Model",""&$B33&"","Umur Outstansing",""&D$2&""),0) -> 0 | E33: =IFERROR(GETPIVOTDATA("Area AGM",#REF!,"Dealer",""&$S$18&"","Model",""&$B33&"","Umur Outstansing",""&E$2&""),0) -> 0 | F33: =IFERROR(GETPIVOTDATA("Area AGM",#REF!,"Dealer",""&$S$18&"","Model",""&$B33&"","Umur Outstansing",""&F$2&""),0) -> 0 | G33: =IFERROR(GETPIVOTDATA("Area AGM",#REF!,"Dealer",""&$S$18&"","Model",""&$B33&"","Umur Outstansing",""&G$2&""),0) -> 0 | H33: =IFERROR(GETPIVOTDATA("Area AGM",#REF!,"Dealer",""&$S$18&"","Model",""&$B33&"","Umur Outstansing",""&H$2&""),0) -> 0 | J33: =IFERROR(GETPIVOTDATA("Area AGM",#REF!,"Dealer",""&$S$18&"","Model",""&$B33&""),0) -> 0 | K33: =IFERROR(GETPIVOTDATA("Area AGM",#REF!,"Dealer",""&$S$18&"","Model",""&$B33&""),0) -> 0 | R33: =R34=R30 -> TRUE | T33: =T34=T30 -> TRUE | U33: =U34=U30 -> TRUE | V33: =V34=V30 -> TRUE | W33: =W34=W30 -> TRUE | X33: =X34=X30 -> TRUE | Y33: =Y34=Y30 -> TRUE | Z33: =Z34=Z30 -> TRUE | AA33: =AA34=AA30 -> TRUE | ... AT33: =AT34=AT30 -> TRUE
B34: VIOS | C34: =SUM(D34:G34) -> 0 | D34: =IFERROR(GETPIVOTDATA("Area AGM",#REF!,"Dealer",""&$S$18&"","Model",""&$B34&"","Umur Outstansing",""&D$2&""),0) -> 0 | E34: =IFERROR(GETPIVOTDATA("Area AGM",#REF!,"Dealer",""&$S$18&"","Model",""&$B34&"","Umur Outstansing",""&E$2&""),0) -> 0 | F34: =IFERROR(GETPIVOTDATA("Area AGM",#REF!,"Dealer",""&$S$18&"","Model",""&$B34&"","Umur Outstansing",""&F$2&""),0) -> 0 | G34: =IFERROR(GETPIVOTDATA("Area AGM",#REF!,"Dealer",""&$S$18&"","Model",""&$B34&"","Umur Outstansing",""&G$2&""),0) -> 0 | H34: =IFERROR(GETPIVOTDATA("Area AGM",#REF!,"Dealer",""&$S$18&"","Model",""&$B34&"","Umur Outstansing",""&H$2&""),0) -> 0 | J34: =IFERROR(GETPIVOTDATA("Area AGM",#REF!,"Dealer",""&$S$18&"","Model",""&$B34&""),0) -> 0 | K34: =IFERROR(GETPIVOTDATA("Area AGM",#REF!,"Dealer",""&$S$18&"","Model",""&$B34&""),0) -> 0 | Q34: =IFERROR(R34/AI34,0) -> 0 | R34: =SUM(R35:R67) -> 0 | T34: =SUM(T35:T67) -> 0 | U34: =SUM(U35:U67) -> 0 | V34: =SUM(V35:V67) -> 0 | W34: =SUM(W35:W67) -> 0 | X34: =SUM(X35:X67) -> 0 | Y34: =SUM(Y35:Y67) -> 0 | Z34: =SUM(Z35:Z67) -> 0 | AA34: =SUM(AA35:AA67) -> 0 | ... AT34: =SUM(AT35:AT67) -> 0
B35: VOXY | C35: =SUM(D35:G35) -> 0 | D35: =IFERROR(GETPIVOTDATA("Area AGM",#REF!,"Dealer",""&$S$18&"","Model",""&$B35&"","Umur Outstansing",""&D$2&""),0) -> 0 | E35: =IFERROR(GETPIVOTDATA("Area AGM",#REF!,"Dealer",""&$S$18&"","Model",""&$B35&"","Umur Outstansing",""&E$2&""),0) -> 0 | F35: =IFERROR(GETPIVOTDATA("Area AGM",#REF!,"Dealer",""&$S$18&"","Model",""&$B35&"","Umur Outstansing",""&F$2&""),0) -> 0 | G35: =IFERROR(GETPIVOTDATA("Area AGM",#REF!,"Dealer",""&$S$18&"","Model",""&$B35&"","Umur Outstansing",""&G$2&""),0) -> 0 | H35: =IFERROR(GETPIVOTDATA("Area AGM",#REF!,"Dealer",""&$S$18&"","Model",""&$B35&"","Umur Outstansing",""&H$2&""),0) -> 0 | J35: =IFERROR(GETPIVOTDATA("Area AGM",#REF!,"Dealer",""&$S$18&"","Model",""&$B35&""),0) -> 0 | K35: =IFERROR(GETPIVOTDATA("Area AGM",#REF!,"Dealer",""&$S$18&"","Model",""&$B35&""),0) -> 0 | P35: ALPHARD | Q35: =IFERROR(R35/AI35,0) -> 0 | R35: =IFERROR(GETPIVOTDATA("RS Target",#REF!,"Dealer",""&$S$18&"","Model",""&$P35&""),0) -> 0 | S35: ALPHARD | T35: =SUM(Y35:AB35,AO35) -> 0 | U35: =IFERROR(GETPIVOTDATA("Area AGM",'Pvt OS'!#REF!,"Dealer",""&$S$18&"","Model",""&$S35&""),0) -> 0 | V35: =W35-X35 -> 0 | W35: =IFERROR(GETPIVOTDATA("Area AGM",'Pvt OS'!#REF!,"Dealer",""&$S$18&"","Model",""&$S35&""),0)+IFERROR(GETPIVOTDATA("Area AGM",'Pvt OS'!$A$8,"Dealer",""&$S$18&"","Model",""&$S35&""),0) -> 0 | X35: =SUM(Y35:AB35) -> 0 | Y35: =IFERROR(GETPIVOTDATA("Area AGM",'Pvt OS'!$U$8,"Dealer",""&$S$18&"","Model",""&$S35&""),0) -> 0 | Z35: =IFERROR(GETPIVOTDATA("Area AGM",'Pvt OS'!$M$8,"Dealer",""&$S$18&"","Model",""&$S35&""),0) -> 0 | AA35: =IFERROR(GETPIVOTDATA("Area AGM",'Pvt OS'!#REF!,"Dealer",""&$S$18&"","Model",""&$S35&""),0) -> 0 | AB35: =IFERROR(GETPIVOTDATA("Area AGM",'Pvt OS'!$AO$8,"Dealer",""&$S$18&"","Model",""&$S35&""),0) -> 0 | AC35: =IFERROR(GETPIVOTDATA("Stock",#REF!,"Dealer",""&$S$18&"","Model",""&$S35&""),0) -> 0 | AD35: =IFERROR(GETPIVOTDATA("MDP",#REF!,"Dealer",""&$S$18&"","Model",""&$S35&""),0) -> 0 | AE35: =IFERROR(GETPIVOTDATA("RRN",#REF!,"Model2",""&$S35&"","Dealer",""&$S$18&""),0) -> 0 | AF35: =IFERROR(GETPIVOTDATA("CO",#REF!,"Dealer Name",""&$S$18&"","Model",""&$S35&""),0) -> 0 | AG35: =IFERROR(GETPIVOTDATA("Sum of Distplan Final",#REF!,"Dealer",""&$S$18&"","Model",""&$S35&""),0) -> 0 | AH35: =IFERROR(GETPIVOTDATA("RRN",#REF!,"Model",""&$S35&"","Dealer",""&$S$18&""),0) -> 0 | AI35: =AC35+AD35+AF35+AG35-AH35 -> 0 | AJ35: =IFERROR(GETPIVOTDATA("volume_rs",#REF!,"Model",""&$S35&"","Dealer",""&$S$18&""),0) -> 0 | AK35: =AI35-AJ35-X35+AN35 -> 0 | AL35: =IFERROR(GETPIVOTDATA("Area AGM",'Pvt OS'!#REF!,"Dealer",""&$S$18&"","Model",""&$S35&""),0) -> 0 | AM35: =AK35+AL35 -> 0 | AN35: =IFERROR(GETPIVOTDATA("Row Labels",#REF!,"Dealer",""&$S$18&"","Model",""&$S35&""),0) -> 0 | AO35: =IFERROR(GETPIVOTDATA("RS Afi",#REF!,"Dealer",""&$S$18&"","Model",""&$S35&""),0) -> 0 | AP35: =IFERROR(GETPIVOTDATA("qty",#REF!,"Model",""&$S35&"","Dealer",""&$S$18&""),0) -> 0 | AQ35: =IFERROR(GETPIVOTDATA("volume_rs",#REF!,"Model",""&$S35&"","Dealer",""&$S$18&""),0) -> 0 | AR35: =AP35-AQ35 -> 0 | AS35: =IFERROR(GETPIVOTDATA("Area AGM",'Pvt OS'!#REF!,"Dealer",""&$S$18&"","Model",""&$S35&""),0) -> 0 | AT35: =AR35-AS35 -> 0
B36: HIACE PREMIO | C36: =SUM(D36:G36) -> 0 | D36: =IFERROR(GETPIVOTDATA("Area AGM",#REF!,"Dealer",""&$S$18&"","Model",""&$B36&"","Umur Outstansing",""&D$2&""),0) -> 0 | E36: =IFERROR(GETPIVOTDATA("Area AGM",#REF!,"Dealer",""&$S$18&"","Model",""&$B36&"","Umur Outstansing",""&E$2&""),0) -> 0 | F36: =IFERROR(GETPIVOTDATA("Area AGM",#REF!,"Dealer",""&$S$18&"","Model",""&$B36&"","Umur Outstansing",""&F$2&""),0) -> 0 | G36: =IFERROR(GETPIVOTDATA("Area AGM",#REF!,"Dealer",""&$S$18&"","Model",""&$B36&"","Umur Outstansing",""&G$2&""),0) -> 0 | H36: =IFERROR(GETPIVOTDATA("Area AGM",#REF!,"Dealer",""&$S$18&"","Model",""&$B36&"","Umur Outstansing",""&H$2&""),0) -> 0 | J36: =IFERROR(GETPIVOTDATA("Area AGM",#REF!,"Dealer",""&$S$18&"","Model",""&$B36&""),0) -> 0 | K36: =IFERROR(GETPIVOTDATA("Area AGM",#REF!,"Dealer",""&$S$18&"","Model",""&$B36&""),0) -> 0 | P36: AVANZA | Q36: =IFERROR(R36/AI36,0) -> 0 | R36: =IFERROR(GETPIVOTDATA("RS Target",#REF!,"Dealer",""&$S$18&"","Model",""&$P36&""),0) -> 0 | S36: AVANZA | T36: =SUM(Y36:AB36,AO36) -> 0 | U36: =IFERROR(GETPIVOTDATA("Area AGM",'Pvt OS'!#REF!,"Dealer",""&$S$18&"","Model",""&$S36&""),0) -> 0 | V36: =W36-X36 -> 0 | W36: =IFERROR(GETPIVOTDATA("Area AGM",'Pvt OS'!#REF!,"Dealer",""&$S$18&"","Model",""&$S36&""),0)+IFERROR(GETPIVOTDATA("Area AGM",'Pvt OS'!$A$8,"Dealer",""&$S$18&"","Model",""&$S36&""),0) -> 0 | X36: =SUM(Y36:AB36) -> 0 | Y36: =IFERROR(GETPIVOTDATA("Area AGM",'Pvt OS'!$U$8,"Dealer",""&$S$18&"","Model",""&$S36&""),0) -> 0 | Z36: =IFERROR(GETPIVOTDATA("Area AGM",'Pvt OS'!$M$8,"Dealer",""&$S$18&"","Model",""&$S36&""),0) -> 0 | AA36: =IFERROR(GETPIVOTDATA("Area AGM",'Pvt OS'!#REF!,"Dealer",""&$S$18&"","Model",""&$S36&""),0) -> 0 | AB36: =IFERROR(GETPIVOTDATA("Area AGM",'Pvt OS'!$AO$8,"Dealer",""&$S$18&"","Model",""&$S36&""),0) -> 0 | AC36: =IFERROR(GETPIVOTDATA("Stock",#REF!,"Dealer",""&$S$18&"","Model",""&$S36&""),0) -> 0 | AD36: =IFERROR(GETPIVOTDATA("MDP",#REF!,"Dealer",""&$S$18&"","Model",""&$S36&""),0) -> 0 | AE36: =IFERROR(GETPIVOTDATA("RRN",#REF!,"Model2",""&$S36&"","Dealer",""&$S$18&""),0) -> 0 | AF36: =IFERROR(GETPIVOTDATA("CO",#REF!,"Dealer Name",""&$S$18&"","Model",""&$S36&""),0) -> 0 | AG36: =IFERROR(GETPIVOTDATA("Sum of Distplan Final",#REF!,"Dealer",""&$S$18&"","Model",""&$S36&""),0) -> 0 | AH36: =IFERROR(GETPIVOTDATA("RRN",#REF!,"Model",""&$S36&"","Dealer",""&$S$18&""),0) -> 0 | AI36: =AC36+AD36+AF36+AG36-AH36 -> 0 | AJ36: =IFERROR(GETPIVOTDATA("volume_rs",#REF!,"Model",""&$S36&"","Dealer",""&$S$18&""),0) -> 0 | AK36: =AI36-AJ36-X36+AN36 -> 0 | AL36: =IFERROR(GETPIVOTDATA("Area AGM",'Pvt OS'!#REF!,"Dealer",""&$S$18&"","Model",""&$S36&""),0) -> 0 | AM36: =AK36+AL36 -> 0 | AN36: =IFERROR(GETPIVOTDATA("Row Labels",#REF!,"Dealer",""&$S$18&"","Model",""&$S36&""),0) -> 0 | AO36: =IFERROR(GETPIVOTDATA("RS Afi",#REF!,"Dealer",""&$S$18&"","Model",""&$S36&""),0) -> 0 | AP36: =IFERROR(GETPIVOTDATA("qty",#REF!,"Model",""&$S36&"","Dealer",""&$S$18&""),0) -> 0 | AQ36: =IFERROR(GETPIVOTDATA("volume_rs",#REF!,"Model",""&$S36&"","Dealer",""&$S$18&""),0) -> 0 | AR36: =AP36-AQ36 -> 0 | AS36: =IFERROR(GETPIVOTDATA("Area AGM",'Pvt OS'!#REF!,"Dealer",""&$S$18&"","Model",""&$S36&""),0) -> 0 | AT36: =AR36-AS36 -> 0
B37: HILUX S-CAB 4X4 | C37: =SUM(D37:G37) -> 0 | D37: =IFERROR(GETPIVOTDATA("Area AGM",#REF!,"Dealer",""&$S$18&"","Model",""&$B37&"","Umur Outstansing",""&D$2&""),0) -> 0 | E37: =IFERROR(GETPIVOTDATA("Area AGM",#REF!,"Dealer",""&$S$18&"","Model",""&$B37&"","Umur Outstansing",""&E$2&""),0) -> 0 | F37: =IFERROR(GETPIVOTDATA("Area AGM",#REF!,"Dealer",""&$S$18&"","Model",""&$B37&"","Umur Outstansing",""&F$2&""),0) -> 0 | G37: =IFERROR(GETPIVOTDATA("Area AGM",#REF!,"Dealer",""&$S$18&"","Model",""&$B37&"","Umur Outstansing",""&G$2&""),0) -> 0 | H37: =IFERROR(GETPIVOTDATA("Area AGM",#REF!,"Dealer",""&$S$18&"","Model",""&$B37&"","Umur Outstansing",""&H$2&""),0) -> 0 | J37: =IFERROR(GETPIVOTDATA("Area AGM",#REF!,"Dealer",""&$S$18&"","Model",""&$B37&""),0) -> 0 | K37: =IFERROR(GETPIVOTDATA("Area AGM",#REF!,"Dealer",""&$S$18&"","Model",""&$B37&""),0) -> 0 | P37: SIENTA | Q37: =IFERROR(R37/AI37,0) -> 0 | R37: =IFERROR(GETPIVOTDATA("RS Target",#REF!,"Dealer",""&$S$18&"","Model",""&$P37&""),0) -> 0 | S37: SIENTA | T37: =SUM(Y37:AB37,AO37) -> 0 | U37: =IFERROR(GETPIVOTDATA("Area AGM",'Pvt OS'!#REF!,"Dealer",""&$S$18&"","Model",""&$S37&""),0) -> 0 | V37: =W37-X37 -> 0 | W37: =IFERROR(GETPIVOTDATA("Area AGM",'Pvt OS'!#REF!,"Dealer",""&$S$18&"","Model",""&$S37&""),0)+IFERROR(GETPIVOTDATA("Area AGM",'Pvt OS'!$A$8,"Dealer",""&$S$18&"","Model",""&$S37&""),0) -> 0 | X37: =SUM(Y37:AB37) -> 0 | Y37: =IFERROR(GETPIVOTDATA("Area AGM",'Pvt OS'!$U$8,"Dealer",""&$S$18&"","Model",""&$S37&""),0) -> 0 | Z37: =IFERROR(GETPIVOTDATA("Area AGM",'Pvt OS'!$M$8,"Dealer",""&$S$18&"","Model",""&$S37&""),0) -> 0 | AA37: =IFERROR(GETPIVOTDATA("Area AGM",'Pvt OS'!#REF!,"Dealer",""&$S$18&"","Model",""&$S37&""),0) -> 0 | AB37: =IFERROR(GETPIVOTDATA("Area AGM",'Pvt OS'!$AO$8,"Dealer",""&$S$18&"","Model",""&$S37&""),0) -> 0 | AC37: =IFERROR(GETPIVOTDATA("Stock",#REF!,"Dealer",""&$S$18&"","Model",""&$S37&""),0) -> 0 | AD37: =IFERROR(GETPIVOTDATA("MDP",#REF!,"Dealer",""&$S$18&"","Model",""&$S37&""),0) -> 0 | AE37: =IFERROR(GETPIVOTDATA("RRN",#REF!,"Model2",""&$S37&"","Dealer",""&$S$18&""),0) -> 0 | AF37: =IFERROR(GETPIVOTDATA("CO",#REF!,"Dealer Name",""&$S$18&"","Model",""&$S37&""),0) -> 0 | AG37: =IFERROR(GETPIVOTDATA("Sum of Distplan Final",#REF!,"Dealer",""&$S$18&"","Model",""&$S37&""),0) -> 0 | AH37: =IFERROR(GETPIVOTDATA("RRN",#REF!,"Model",""&$S37&"","Dealer",""&$S$18&""),0) -> 0 | AI37: =AC37+AD37+AF37+AG37-AH37 -> 0 | AJ37: =IFERROR(GETPIVOTDATA("volume_rs",#REF!,"Model",""&$S37&"","Dealer",""&$S$18&""),0) -> 0 | AK37: =AI37-AJ37-X37+AN37 -> 0 | AL37: =IFERROR(GETPIVOTDATA("Area AGM",'Pvt OS'!#REF!,"Dealer",""&$S$18&"","Model",""&$S37&""),0) -> 0 | AM37: =AK37+AL37 -> 0 | AN37: =IFERROR(GETPIVOTDATA("Row Labels",#REF!,"Dealer",""&$S$18&"","Model",""&$S37&""),0) -> 0 | AO37: =IFERROR(GETPIVOTDATA("RS Afi",#REF!,"Dealer",""&$S$18&"","Model",""&$S37&""),0) -> 0 | AP37: =IFERROR(GETPIVOTDATA("qty",#REF!,"Model",""&$S37&"","Dealer",""&$S$18&""),0) -> 0 | AQ37: =IFERROR(GETPIVOTDATA("volume_rs",#REF!,"Model",""&$S37&"","Dealer",""&$S$18&""),0) -> 0 | AR37: =AP37-AQ37 -> 0 | AS37: =IFERROR(GETPIVOTDATA("Area AGM",'Pvt OS'!#REF!,"Dealer",""&$S$18&"","Model",""&$S37&""),0) -> 0 | AT37: =AR37-AS37 -> 0
B38: LANDCRUISER 200 | C38: =SUM(D38:G38) -> 0 | D38: =IFERROR(GETPIVOTDATA("Area AGM",#REF!,"Dealer",""&$S$18&"","Model",""&$B38&"","Umur Outstansing",""&D$2&""),0) -> 0 | E38: =IFERROR(GETPIVOTDATA("Area AGM",#REF!,"Dealer",""&$S$18&"","Model",""&$B38&"","Umur Outstansing",""&E$2&""),0) -> 0 | F38: =IFERROR(GETPIVOTDATA("Area AGM",#REF!,"Dealer",""&$S$18&"","Model",""&$B38&"","Umur Outstansing",""&F$2&""),0) -> 0 | G38: =IFERROR(GETPIVOTDATA("Area AGM",#REF!,"Dealer",""&$S$18&"","Model",""&$B38&"","Umur Outstansing",""&G$2&""),0) -> 0 | H38: =IFERROR(GETPIVOTDATA("Area AGM",#REF!,"Dealer",""&$S$18&"","Model",""&$B38&"","Umur Outstansing",""&H$2&""),0) -> 0 | J38: =IFERROR(GETPIVOTDATA("Area AGM",#REF!,"Dealer",""&$S$18&"","Model",""&$B38&""),0) -> 0 | K38: =IFERROR(GETPIVOTDATA("Area AGM",#REF!,"Dealer",""&$S$18&"","Model",""&$B38&""),0) -> 0 | P38: C-HR | Q38: =IFERROR(R38/AI38,0) -> 0 | R38: =IFERROR(GETPIVOTDATA("RS Target",#REF!,"Dealer",""&$S$18&"","Model",""&$P38&""),0) -> 0 | S38: C-HR | T38: =SUM(Y38:AB38,AO38) -> 0 | U38: =IFERROR(GETPIVOTDATA("Area AGM",'Pvt OS'!#REF!,"Dealer",""&$S$18&"","Model",""&$S38&""),0) -> 0 | V38: =W38-X38 -> 0 | W38: =IFERROR(GETPIVOTDATA("Area AGM",'Pvt OS'!#REF!,"Dealer",""&$S$18&"","Model",""&$S38&""),0)+IFERROR(GETPIVOTDATA("Area AGM",'Pvt OS'!$A$8,"Dealer",""&$S$18&"","Model",""&$S38&""),0) -> 0 | X38: =SUM(Y38:AB38) -> 0 | Y38: =IFERROR(GETPIVOTDATA("Area AGM",'Pvt OS'!$U$8,"Dealer",""&$S$18&"","Model",""&$S38&""),0) -> 0 | Z38: =IFERROR(GETPIVOTDATA("Area AGM",'Pvt OS'!$M$8,"Dealer",""&$S$18&"","Model",""&$S38&""),0) -> 0 | AA38: =IFERROR(GETPIVOTDATA("Area AGM",'Pvt OS'!#REF!,"Dealer",""&$S$18&"","Model",""&$S38&""),0) -> 0 | AB38: =IFERROR(GETPIVOTDATA("Area AGM",'Pvt OS'!$AO$8,"Dealer",""&$S$18&"","Model",""&$S38&""),0) -> 0 | AC38: =IFERROR(GETPIVOTDATA("Stock",#REF!,"Dealer",""&$S$18&"","Model",""&$S38&""),0) -> 0 | AD38: =IFERROR(GETPIVOTDATA("MDP",#REF!,"Dealer",""&$S$18&"","Model",""&$S38&""),0) -> 0 | AE38: =IFERROR(GETPIVOTDATA("RRN",#REF!,"Model2",""&$S38&"","Dealer",""&$S$18&""),0) -> 0 | AF38: =IFERROR(GETPIVOTDATA("CO",#REF!,"Dealer Name",""&$S$18&"","Model",""&$S38&""),0) -> 0 | AG38: =IFERROR(GETPIVOTDATA("Sum of Distplan Final",#REF!,"Dealer",""&$S$18&"","Model",""&$S38&""),0) -> 0 | AH38: =IFERROR(GETPIVOTDATA("RRN",#REF!,"Model",""&$S38&"","Dealer",""&$S$18&""),0) -> 0 | AI38: =AC38+AD38+AF38+AG38-AH38 -> 0 | AJ38: =IFERROR(GETPIVOTDATA("volume_rs",#REF!,"Model",""&$S38&"","Dealer",""&$S$18&""),0) -> 0 | AK38: =AI38-AJ38-X38+AN38 -> 0 | AL38: =IFERROR(GETPIVOTDATA("Area AGM",'Pvt OS'!#REF!,"Dealer",""&$S$18&"","Model",""&$S38&""),0) -> 0 | AM38: =AK38+AL38 -> 0 | AN38: =IFERROR(GETPIVOTDATA("Row Labels",#REF!,"Dealer",""&$S$18&"","Model",""&$S38&""),0) -> 0 | AO38: =IFERROR(GETPIVOTDATA("RS Afi",#REF!,"Dealer",""&$S$18&"","Model",""&$S38&""),0) -> 0 | AP38: =IFERROR(GETPIVOTDATA("qty",#REF!,"Model",""&$S38&"","Dealer",""&$S$18&""),0) -> 0 | AQ38: =IFERROR(GETPIVOTDATA("volume_rs",#REF!,"Model",""&$S38&"","Dealer",""&$S$18&""),0) -> 0 | AR38: =AP38-AQ38 -> 0 | AS38: =IFERROR(GETPIVOTDATA("Area AGM",'Pvt OS'!#REF!,"Dealer",""&$S$18&"","Model",""&$S38&""),0) -> 0 | AT38: =AR38-AS38 -> 0
B39: COROLLA CROSS HYBRID | C39: =SUM(D39:G39) -> 0 | D39: =IFERROR(GETPIVOTDATA("Area AGM",#REF!,"Dealer",""&$S$18&"","Model",""&$B39&"","Umur Outstansing",""&D$2&""),0) -> 0 | E39: =IFERROR(GETPIVOTDATA("Area AGM",#REF!,"Dealer",""&$S$18&"","Model",""&$B39&"","Umur Outstansing",""&E$2&""),0) -> 0 | F39: =IFERROR(GETPIVOTDATA("Area AGM",#REF!,"Dealer",""&$S$18&"","Model",""&$B39&"","Umur Outstansing",""&F$2&""),0) -> 0 | G39: =IFERROR(GETPIVOTDATA("Area AGM",#REF!,"Dealer",""&$S$18&"","Model",""&$B39&"","Umur Outstansing",""&G$2&""),0) -> 0 | H39: =IFERROR(GETPIVOTDATA("Area AGM",#REF!,"Dealer",""&$S$18&"","Model",""&$B39&"","Umur Outstansing",""&H$2&""),0) -> 0 | J39: =IFERROR(GETPIVOTDATA("Area AGM",#REF!,"Dealer",""&$S$18&"","Model",""&$B39&""),0) -> 0 | K39: =IFERROR(GETPIVOTDATA("Area AGM",#REF!,"Dealer",""&$S$18&"","Model",""&$B39&""),0) -> 0 | P39: C-HR HYBRID | Q39: =IFERROR(R39/AI39,0) -> 0 | R39: =IFERROR(GETPIVOTDATA("RS Target",#REF!,"Dealer",""&$S$18&"","Model",""&$P39&""),0) -> 0 | S39: C-HR HYBRID | T39: =SUM(Y39:AB39,AO39) -> 0 | U39: =IFERROR(GETPIVOTDATA("Area AGM",'Pvt OS'!#REF!,"Dealer",""&$S$18&"","Model",""&$S39&""),0) -> 0 | V39: =W39-X39 -> 0 | W39: =IFERROR(GETPIVOTDATA("Area AGM",'Pvt OS'!#REF!,"Dealer",""&$S$18&"","Model",""&$S39&""),0)+IFERROR(GETPIVOTDATA("Area AGM",'Pvt OS'!$A$8,"Dealer",""&$S$18&"","Model",""&$S39&""),0) -> 0 | X39: =SUM(Y39:AB39) -> 0 | Y39: =IFERROR(GETPIVOTDATA("Area AGM",'Pvt OS'!$U$8,"Dealer",""&$S$18&"","Model",""&$S39&""),0) -> 0 | Z39: =IFERROR(GETPIVOTDATA("Area AGM",'Pvt OS'!$M$8,"Dealer",""&$S$18&"","Model",""&$S39&""),0) -> 0 | AA39: =IFERROR(GETPIVOTDATA("Area AGM",'Pvt OS'!#REF!,"Dealer",""&$S$18&"","Model",""&$S39&""),0) -> 0 | AB39: =IFERROR(GETPIVOTDATA("Area AGM",'Pvt OS'!$AO$8,"Dealer",""&$S$18&"","Model",""&$S39&""),0) -> 0 | AC39: =IFERROR(GETPIVOTDATA("Stock",#REF!,"Dealer",""&$S$18&"","Model",""&$S39&""),0) -> 0 | AD39: =IFERROR(GETPIVOTDATA("MDP",#REF!,"Dealer",""&$S$18&"","Model",""&$S39&""),0) -> 0 | AE39: =IFERROR(GETPIVOTDATA("RRN",#REF!,"Model2",""&$S39&"","Dealer",""&$S$18&""),0) -> 0 | AF39: =IFERROR(GETPIVOTDATA("CO",#REF!,"Dealer Name",""&$S$18&"","Model",""&$S39&""),0) -> 0 | AG39: =IFERROR(GETPIVOTDATA("Sum of Distplan Final",#REF!,"Dealer",""&$S$18&"","Model",""&$S39&""),0) -> 0 | AH39: =IFERROR(GETPIVOTDATA("RRN",#REF!,"Model",""&$S39&"","Dealer",""&$S$18&""),0) -> 0 | AI39: =AC39+AD39+AF39+AG39-AH39 -> 0 | AJ39: =IFERROR(GETPIVOTDATA("volume_rs",#REF!,"Model",""&$S39&"","Dealer",""&$S$18&""),0) -> 0 | AK39: =AI39-AJ39-X39+AN39 -> 0 | AL39: =IFERROR(GETPIVOTDATA("Area AGM",'Pvt OS'!#REF!,"Dealer",""&$S$18&"","Model",""&$S39&""),0) -> 0 | AM39: =AK39+AL39 -> 0 | AN39: =IFERROR(GETPIVOTDATA("Row Labels",#REF!,"Dealer",""&$S$18&"","Model",""&$S39&""),0) -> 0 | AO39: =IFERROR(GETPIVOTDATA("RS Afi",#REF!,"Dealer",""&$S$18&"","Model",""&$S39&""),0) -> 0 | AP39: =IFERROR(GETPIVOTDATA("qty",#REF!,"Model",""&$S39&"","Dealer",""&$S$18&""),0) -> 0 | AQ39: =IFERROR(GETPIVOTDATA("volume_rs",#REF!,"Model",""&$S39&"","Dealer",""&$S$18&""),0) -> 0 | AR39: =AP39-AQ39 -> 0 | AS39: =IFERROR(GETPIVOTDATA("Area AGM",'Pvt OS'!#REF!,"Dealer",""&$S$18&"","Model",""&$S39&""),0) -> 0 | AT39: =AR39-AS39 -> 0
B40: COROLLA CROSS | C40: =SUM(D40:G40) -> 0 | D40: =IFERROR(GETPIVOTDATA("Area AGM",#REF!,"Dealer",""&$S$18&"","Model",""&$B40&"","Umur Outstansing",""&D$2&""),0) -> 0 | E40: =IFERROR(GETPIVOTDATA("Area AGM",#REF!,"Dealer",""&$S$18&"","Model",""&$B40&"","Umur Outstansing",""&E$2&""),0) -> 0 | F40: =IFERROR(GETPIVOTDATA("Area AGM",#REF!,"Dealer",""&$S$18&"","Model",""&$B40&"","Umur Outstansing",""&F$2&""),0) -> 0 | G40: =IFERROR(GETPIVOTDATA("Area AGM",#REF!,"Dealer",""&$S$18&"","Model",""&$B40&"","Umur Outstansing",""&G$2&""),0) -> 0 | H40: =IFERROR(GETPIVOTDATA("Area AGM",#REF!,"Dealer",""&$S$18&"","Model",""&$B40&"","Umur Outstansing",""&H$2&""),0) -> 0 | J40: =IFERROR(GETPIVOTDATA("Area AGM",#REF!,"Dealer",""&$S$18&"","Model",""&$B40&""),0) -> 0 | K40: =IFERROR(GETPIVOTDATA("Area AGM",#REF!,"Dealer",""&$S$18&"","Model",""&$B40&""),0) -> 0 | P40: CAMRY | Q40: =IFERROR(R40/AI40,0) -> 0 | R40: =IFERROR(GETPIVOTDATA("RS Target",#REF!,"Dealer",""&$S$18&"","Model",""&$P40&""),0) -> 0 | S40: CAMRY | T40: =SUM(Y40:AB40,AO40) -> 0 | U40: =IFERROR(GETPIVOTDATA("Area AGM",'Pvt OS'!#REF!,"Dealer",""&$S$18&"","Model",""&$S40&""),0) -> 0 | V40: =W40-X40 -> 0 | W40: =IFERROR(GETPIVOTDATA("Area AGM",'Pvt OS'!#REF!,"Dealer",""&$S$18&"","Model",""&$S40&""),0)+IFERROR(GETPIVOTDATA("Area AGM",'Pvt OS'!$A$8,"Dealer",""&$S$18&"","Model",""&$S40&""),0) -> 0 | X40: =SUM(Y40:AB40) -> 0 | Y40: =IFERROR(GETPIVOTDATA("Area AGM",'Pvt OS'!$U$8,"Dealer",""&$S$18&"","Model",""&$S40&""),0) -> 0 | Z40: =IFERROR(GETPIVOTDATA("Area AGM",'Pvt OS'!$M$8,"Dealer",""&$S$18&"","Model",""&$S40&""),0) -> 0 | AA40: =IFERROR(GETPIVOTDATA("Area AGM",'Pvt OS'!#REF!,"Dealer",""&$S$18&"","Model",""&$S40&""),0) -> 0 | AB40: =IFERROR(GETPIVOTDATA("Area AGM",'Pvt OS'!$AO$8,"Dealer",""&$S$18&"","Model",""&$S40&""),0) -> 0 | AC40: =IFERROR(GETPIVOTDATA("Stock",#REF!,"Dealer",""&$S$18&"","Model",""&$S40&""),0) -> 0 | AD40: =IFERROR(GETPIVOTDATA("MDP",#REF!,"Dealer",""&$S$18&"","Model",""&$S40&""),0) -> 0 | AE40: =IFERROR(GETPIVOTDATA("RRN",#REF!,"Model2",""&$S40&"","Dealer",""&$S$18&""),0) -> 0 | AF40: =IFERROR(GETPIVOTDATA("CO",#REF!,"Dealer Name",""&$S$18&"","Model",""&$S40&""),0) -> 0 | AG40: =IFERROR(GETPIVOTDATA("Sum of Distplan Final",#REF!,"Dealer",""&$S$18&"","Model",""&$S40&""),0) -> 0 | AH40: =IFERROR(GETPIVOTDATA("RRN",#REF!,"Model",""&$S40&"","Dealer",""&$S$18&""),0) -> 0 | AI40: =AC40+AD40+AF40+AG40-AH40 -> 0 | AJ40: =IFERROR(GETPIVOTDATA("volume_rs",#REF!,"Model",""&$S40&"","Dealer",""&$S$18&""),0) -> 0 | AK40: =AI40-AJ40-X40+AN40 -> 0 | AL40: =IFERROR(GETPIVOTDATA("Area AGM",'Pvt OS'!#REF!,"Dealer",""&$S$18&"","Model",""&$S40&""),0) -> 0 | AM40: =AK40+AL40 -> 0 | AN40: =IFERROR(GETPIVOTDATA("Row Labels",#REF!,"Dealer",""&$S$18&"","Model",""&$S40&""),0) -> 0 | AO40: =IFERROR(GETPIVOTDATA("RS Afi",#REF!,"Dealer",""&$S$18&"","Model",""&$S40&""),0) -> 0 | AP40: =IFERROR(GETPIVOTDATA("qty",#REF!,"Model",""&$S40&"","Dealer",""&$S$18&""),0) -> 0 | AQ40: =IFERROR(GETPIVOTDATA("volume_rs",#REF!,"Model",""&$S40&"","Dealer",""&$S$18&""),0) -> 0 | AR40: =AP40-AQ40 -> 0 | AS40: =IFERROR(GETPIVOTDATA("Area AGM",'Pvt OS'!#REF!,"Dealer",""&$S$18&"","Model",""&$S40&""),0) -> 0 | AT40: =AR40-AS40 -> 0
B41: COROLLA | C41: =SUM(D41:G41) -> 0 | D41: =IFERROR(GETPIVOTDATA("Area AGM",#REF!,"Dealer",""&$S$18&"","Model",""&$B41&"","Umur Outstansing",""&D$2&""),0) -> 0 | E41: =IFERROR(GETPIVOTDATA("Area AGM",#REF!,"Dealer",""&$S$18&"","Model",""&$B41&"","Umur Outstansing",""&E$2&""),0) -> 0 | F41: =IFERROR(GETPIVOTDATA("Area AGM",#REF!,"Dealer",""&$S$18&"","Model",""&$B41&"","Umur Outstansing",""&F$2&""),0) -> 0 | G41: =IFERROR(GETPIVOTDATA("Area AGM",#REF!,"Dealer",""&$S$18&"","Model",""&$B41&"","Umur Outstansing",""&G$2&""),0) -> 0 | H41: =IFERROR(GETPIVOTDATA("Area AGM",#REF!,"Dealer",""&$S$18&"","Model",""&$B41&"","Umur Outstansing",""&H$2&""),0) -> 0 | J41: =IFERROR(GETPIVOTDATA("Area AGM",#REF!,"Dealer",""&$S$18&"","Model",""&$B41&""),0) -> 0 | K41: =IFERROR(GETPIVOTDATA("Area AGM",#REF!,"Dealer",""&$S$18&"","Model",""&$B41&""),0) -> 0 | P41: DYNA | Q41: =IFERROR(R41/AI41,0) -> 0 | R41: =IFERROR(GETPIVOTDATA("RS Target",#REF!,"Dealer",""&$S$18&"","Model",""&$P41&""),0) -> 0 | S41: DYNA | T41: =SUM(Y41:AB41,AO41) -> 0 | U41: =IFERROR(GETPIVOTDATA("Area AGM",'Pvt OS'!#REF!,"Dealer",""&$S$18&"","Model",""&$S41&""),0) -> 0 | V41: =W41-X41 -> 0 | W41: =IFERROR(GETPIVOTDATA("Area AGM",'Pvt OS'!#REF!,"Dealer",""&$S$18&"","Model",""&$S41&""),0)+IFERROR(GETPIVOTDATA("Area AGM",'Pvt OS'!$A$8,"Dealer",""&$S$18&"","Model",""&$S41&""),0) -> 0 | X41: =SUM(Y41:AB41) -> 0 | Y41: =IFERROR(GETPIVOTDATA("Area AGM",'Pvt OS'!$U$8,"Dealer",""&$S$18&"","Model",""&$S41&""),0) -> 0 | Z41: =IFERROR(GETPIVOTDATA("Area AGM",'Pvt OS'!$M$8,"Dealer",""&$S$18&"","Model",""&$S41&""),0) -> 0 | AA41: =IFERROR(GETPIVOTDATA("Area AGM",'Pvt OS'!#REF!,"Dealer",""&$S$18&"","Model",""&$S41&""),0) -> 0 | AB41: =IFERROR(GETPIVOTDATA("Area AGM",'Pvt OS'!$AO$8,"Dealer",""&$S$18&"","Model",""&$S41&""),0) -> 0 | AC41: =IFERROR(GETPIVOTDATA("Stock",#REF!,"Dealer",""&$S$18&"","Model",""&$S41&""),0) -> 0 | AD41: =IFERROR(GETPIVOTDATA("MDP",#REF!,"Dealer",""&$S$18&"","Model",""&$S41&""),0) -> 0 | AE41: =IFERROR(GETPIVOTDATA("RRN",#REF!,"Model2",""&$S41&"","Dealer",""&$S$18&""),0) -> 0 | AF41: =IFERROR(GETPIVOTDATA("CO",#REF!,"Dealer Name",""&$S$18&"","Model",""&$S41&""),0) -> 0 | AG41: =IFERROR(GETPIVOTDATA("Sum of Distplan Final",#REF!,"Dealer",""&$S$18&"","Model",""&$S41&""),0) -> 0 | AH41: =IFERROR(GETPIVOTDATA("RRN",#REF!,"Model",""&$S41&"","Dealer",""&$S$18&""),0) -> 0 | AI41: =AC41+AD41+AF41+AG41-AH41 -> 0 | AJ41: =IFERROR(GETPIVOTDATA("volume_rs",#REF!,"Model",""&$S41&"","Dealer",""&$S$18&""),0) -> 0 | AK41: =AI41-AJ41-X41+AN41 -> 0 | AL41: =IFERROR(GETPIVOTDATA("Area AGM",'Pvt OS'!#REF!,"Dealer",""&$S$18&"","Model",""&$S41&""),0) -> 0 | AM41: =AK41+AL41 -> 0 | AN41: =IFERROR(GETPIVOTDATA("Row Labels",#REF!,"Dealer",""&$S$18&"","Model",""&$S41&""),0) -> 0 | AO41: =IFERROR(GETPIVOTDATA("RS Afi",#REF!,"Dealer",""&$S$18&"","Model",""&$S41&""),0) -> 0 | AP41: =IFERROR(GETPIVOTDATA("qty",#REF!,"Model",""&$S41&"","Dealer",""&$S$18&""),0) -> 0 | AQ41: =IFERROR(GETPIVOTDATA("volume_rs",#REF!,"Model",""&$S41&"","Dealer",""&$S$18&""),0) -> 0 | AR41: =AP41-AQ41 -> 0 | AS41: =IFERROR(GETPIVOTDATA("Area AGM",'Pvt OS'!#REF!,"Dealer",""&$S$18&"","Model",""&$S41&""),0) -> 0 | AT41: =AR41-AS41 -> 0
B42: CAMRY HYBRID | C42: =SUM(D42:G42) -> 0 | D42: =IFERROR(GETPIVOTDATA("Area AGM",#REF!,"Dealer",""&$S$18&"","Model",""&$B42&"","Umur Outstansing",""&D$2&""),0) -> 0 | E42: =IFERROR(GETPIVOTDATA("Area AGM",#REF!,"Dealer",""&$S$18&"","Model",""&$B42&"","Umur Outstansing",""&E$2&""),0) -> 0 | F42: =IFERROR(GETPIVOTDATA("Area AGM",#REF!,"Dealer",""&$S$18&"","Model",""&$B42&"","Umur Outstansing",""&F$2&""),0) -> 0 | G42: =IFERROR(GETPIVOTDATA("Area AGM",#REF!,"Dealer",""&$S$18&"","Model",""&$B42&"","Umur Outstansing",""&G$2&""),0) -> 0 | H42: =IFERROR(GETPIVOTDATA("Area AGM",#REF!,"Dealer",""&$S$18&"","Model",""&$B42&"","Umur Outstansing",""&H$2&""),0) -> 0 | J42: =IFERROR(GETPIVOTDATA("Area AGM",#REF!,"Dealer",""&$S$18&"","Model",""&$B42&""),0) -> 0 | K42: =IFERROR(GETPIVOTDATA("Area AGM",#REF!,"Dealer",""&$S$18&"","Model",""&$B42&""),0) -> 0 | P42: FORTUNER 4X4 | Q42: =IFERROR(R42/AI42,0) -> 0 | R42: =IFERROR(GETPIVOTDATA("RS Target",#REF!,"Dealer",""&$S$18&"","Model",""&$P42&""),0) -> 0 | S42: FORTUNER 4X4 | T42: =SUM(Y42:AB42,AO42) -> 0 | U42: =IFERROR(GETPIVOTDATA("Area AGM",'Pvt OS'!#REF!,"Dealer",""&$S$18&"","Model",""&$S42&""),0) -> 0 | V42: =W42-X42 -> 0 | W42: =IFERROR(GETPIVOTDATA("Area AGM",'Pvt OS'!#REF!,"Dealer",""&$S$18&"","Model",""&$S42&""),0)+IFERROR(GETPIVOTDATA("Area AGM",'Pvt OS'!$A$8,"Dealer",""&$S$18&"","Model",""&$S42&""),0) -> 0 | X42: =SUM(Y42:AB42) -> 0 | Y42: =IFERROR(GETPIVOTDATA("Area AGM",'Pvt OS'!$U$8,"Dealer",""&$S$18&"","Model",""&$S42&""),0) -> 0 | Z42: =IFERROR(GETPIVOTDATA("Area AGM",'Pvt OS'!$M$8,"Dealer",""&$S$18&"","Model",""&$S42&""),0) -> 0 | AA42: =IFERROR(GETPIVOTDATA("Area AGM",'Pvt OS'!#REF!,"Dealer",""&$S$18&"","Model",""&$S42&""),0) -> 0 | AB42: =IFERROR(GETPIVOTDATA("Area AGM",'Pvt OS'!$AO$8,"Dealer",""&$S$18&"","Model",""&$S42&""),0) -> 0 | AC42: =IFERROR(GETPIVOTDATA("Stock",#REF!,"Dealer",""&$S$18&"","Model",""&$S42&""),0) -> 0 | AD42: =IFERROR(GETPIVOTDATA("MDP",#REF!,"Dealer",""&$S$18&"","Model",""&$S42&""),0) -> 0 | AE42: =IFERROR(GETPIVOTDATA("RRN",#REF!,"Model2",""&$S42&"","Dealer",""&$S$18&""),0) -> 0 | AF42: =IFERROR(GETPIVOTDATA("CO",#REF!,"Dealer Name",""&$S$18&"","Model",""&$S42&""),0) -> 0 | AG42: =IFERROR(GETPIVOTDATA("Sum of Distplan Final",#REF!,"Dealer",""&$S$18&"","Model",""&$S42&""),0) -> 0 | AH42: =IFERROR(GETPIVOTDATA("RRN",#REF!,"Model",""&$S42&"","Dealer",""&$S$18&""),0) -> 0 | AI42: =AC42+AD42+AF42+AG42-AH42 -> 0 | AJ42: =IFERROR(GETPIVOTDATA("volume_rs",#REF!,"Model",""&$S42&"","Dealer",""&$S$18&""),0) -> 0 | AK42: =AI42-AJ42-X42+AN42 -> 0 | AL42: =IFERROR(GETPIVOTDATA("Area AGM",'Pvt OS'!#REF!,"Dealer",""&$S$18&"","Model",""&$S42&""),0) -> 0 | AM42: =AK42+AL42 -> 0 | AN42: =IFERROR(GETPIVOTDATA("Row Labels",#REF!,"Dealer",""&$S$18&"","Model",""&$S42&""),0) -> 0 | AO42: =IFERROR(GETPIVOTDATA("RS Afi",#REF!,"Dealer",""&$S$18&"","Model",""&$S42&""),0) -> 0 | AP42: =IFERROR(GETPIVOTDATA("qty",#REF!,"Model",""&$S42&"","Dealer",""&$S$18&""),0) -> 0 | AQ42: =IFERROR(GETPIVOTDATA("volume_rs",#REF!,"Model",""&$S42&"","Dealer",""&$S$18&""),0) -> 0 | AR42: =AP42-AQ42 -> 0 | AS42: =IFERROR(GETPIVOTDATA("Area AGM",'Pvt OS'!#REF!,"Dealer",""&$S$18&"","Model",""&$S42&""),0) -> 0 | AT42: =AR42-AS42 -> 0
B43: COROLLA HYBRID | C43: =SUM(D43:G43) -> 0 | D43: =IFERROR(GETPIVOTDATA("Area AGM",#REF!,"Dealer",""&$S$18&"","Model",""&$B43&"","Umur Outstansing",""&D$2&""),0) -> 0 | E43: =IFERROR(GETPIVOTDATA("Area AGM",#REF!,"Dealer",""&$S$18&"","Model",""&$B43&"","Umur Outstansing",""&E$2&""),0) -> 0 | F43: =IFERROR(GETPIVOTDATA("Area AGM",#REF!,"Dealer",""&$S$18&"","Model",""&$B43&"","Umur Outstansing",""&F$2&""),0) -> 0 | G43: =IFERROR(GETPIVOTDATA("Area AGM",#REF!,"Dealer",""&$S$18&"","Model",""&$B43&"","Umur Outstansing",""&G$2&""),0) -> 0 | H43: =IFERROR(GETPIVOTDATA("Area AGM",#REF!,"Dealer",""&$S$18&"","Model",""&$B43&"","Umur Outstansing",""&H$2&""),0) -> 0 | J43: =IFERROR(GETPIVOTDATA("Area AGM",#REF!,"Dealer",""&$S$18&"","Model",""&$B43&""),0) -> 0 | K43: =IFERROR(GETPIVOTDATA("Area AGM",#REF!,"Dealer",""&$S$18&"","Model",""&$B43&""),0) -> 0 | P43: HIACE | Q43: =IFERROR(R43/AI43,0) -> 0 | R43: =IFERROR(GETPIVOTDATA("RS Target",#REF!,"Dealer",""&$S$18&"","Model",""&$P43&""),0) -> 0 | S43: HIACE | T43: =SUM(Y43:AB43,AO43) -> 0 | U43: =IFERROR(GETPIVOTDATA("Area AGM",'Pvt OS'!#REF!,"Dealer",""&$S$18&"","Model",""&$S43&""),0) -> 0 | V43: =W43-X43 -> 0 | W43: =IFERROR(GETPIVOTDATA("Area AGM",'Pvt OS'!#REF!,"Dealer",""&$S$18&"","Model",""&$S43&""),0)+IFERROR(GETPIVOTDATA("Area AGM",'Pvt OS'!$A$8,"Dealer",""&$S$18&"","Model",""&$S43&""),0) -> 0 | X43: =SUM(Y43:AB43) -> 0 | Y43: =IFERROR(GETPIVOTDATA("Area AGM",'Pvt OS'!$U$8,"Dealer",""&$S$18&"","Model",""&$S43&""),0) -> 0 | Z43: =IFERROR(GETPIVOTDATA("Area AGM",'Pvt OS'!$M$8,"Dealer",""&$S$18&"","Model",""&$S43&""),0) -> 0 | AA43: =IFERROR(GETPIVOTDATA("Area AGM",'Pvt OS'!#REF!,"Dealer",""&$S$18&"","Model",""&$S43&""),0) -> 0 | AB43: =IFERROR(GETPIVOTDATA("Area AGM",'Pvt OS'!$AO$8,"Dealer",""&$S$18&"","Model",""&$S43&""),0) -> 0 | AC43: =IFERROR(GETPIVOTDATA("Stock",#REF!,"Dealer",""&$S$18&"","Model",""&$S43&""),0) -> 0 | AD43: =IFERROR(GETPIVOTDATA("MDP",#REF!,"Dealer",""&$S$18&"","Model",""&$S43&""),0) -> 0 | AE43: =IFERROR(GETPIVOTDATA("RRN",#REF!,"Model2",""&$S43&"","Dealer",""&$S$18&""),0) -> 0 | AF43: =IFERROR(GETPIVOTDATA("CO",#REF!,"Dealer Name",""&$S$18&"","Model",""&$S43&""),0) -> 0 | AG43: =IFERROR(GETPIVOTDATA("Sum of Distplan Final",#REF!,"Dealer",""&$S$18&"","Model",""&$S43&""),0) -> 0 | AH43: =IFERROR(GETPIVOTDATA("RRN",#REF!,"Model",""&$S43&"","Dealer",""&$S$18&""),0) -> 0 | AI43: =AC43+AD43+AF43+AG43-AH43 -> 0 | AJ43: =IFERROR(GETPIVOTDATA("volume_rs",#REF!,"Model",""&$S43&"","Dealer",""&$S$18&""),0) -> 0 | AK43: =AI43-AJ43-X43+AN43 -> 0 | AL43: =IFERROR(GETPIVOTDATA("Area AGM",'Pvt OS'!#REF!,"Dealer",""&$S$18&"","Model",""&$S43&""),0) -> 0 | AM43: =AK43+AL43 -> 0 | AN43: =IFERROR(GETPIVOTDATA("Row Labels",#REF!,"Dealer",""&$S$18&"","Model",""&$S43&""),0) -> 0 | AO43: =IFERROR(GETPIVOTDATA("RS Afi",#REF!,"Dealer",""&$S$18&"","Model",""&$S43&""),0) -> 0 | AP43: =IFERROR(GETPIVOTDATA("qty",#REF!,"Model",""&$S43&"","Dealer",""&$S$18&""),0) -> 0 | AQ43: =IFERROR(GETPIVOTDATA("volume_rs",#REF!,"Model",""&$S43&"","Dealer",""&$S$18&""),0) -> 0 | AR43: =AP43-AQ43 -> 0 | AS43: =IFERROR(GETPIVOTDATA("Area AGM",'Pvt OS'!#REF!,"Dealer",""&$S$18&"","Model",""&$S43&""),0) -> 0 | AT43: =AR43-AS43 -> 0
B44: SUPRA | C44: =SUM(D44:G44) -> 0 | D44: =IFERROR(GETPIVOTDATA("Area AGM",#REF!,"Dealer",""&$S$18&"","Model",""&$B44&"","Umur Outstansing",""&D$2&""),0) -> 0 | E44: =IFERROR(GETPIVOTDATA("Area AGM",#REF!,"Dealer",""&$S$18&"","Model",""&$B44&"","Umur Outstansing",""&E$2&""),0) -> 0 | F44: =IFERROR(GETPIVOTDATA("Area AGM",#REF!,"Dealer",""&$S$18&"","Model",""&$B44&"","Umur Outstansing",""&F$2&""),0) -> 0 | G44: =IFERROR(GETPIVOTDATA("Area AGM",#REF!,"Dealer",""&$S$18&"","Model",""&$B44&"","Umur Outstansing",""&G$2&""),0) -> 0 | H44: =IFERROR(GETPIVOTDATA("Area AGM",#REF!,"Dealer",""&$S$18&"","Model",""&$B44&"","Umur Outstansing",""&H$2&""),0) -> 0 | J44: =IFERROR(GETPIVOTDATA("Area AGM",#REF!,"Dealer",""&$S$18&"","Model",""&$B44&""),0) -> 0 | K44: =IFERROR(GETPIVOTDATA("Area AGM",#REF!,"Dealer",""&$S$18&"","Model",""&$B44&""),0) -> 0 | P44: HILUX D-CAB | Q44: =IFERROR(R44/AI44,0) -> 0 | R44: =IFERROR(GETPIVOTDATA("RS Target",#REF!,"Dealer",""&$S$18&"","Model",""&$P44&""),0) -> 0 | S44: HILUX D-CAB | T44: =SUM(Y44:AB44,AO44) -> 0 | U44: =IFERROR(GETPIVOTDATA("Area AGM",'Pvt OS'!#REF!,"Dealer",""&$S$18&"","Model",""&$S44&""),0) -> 0 | V44: =W44-X44 -> 0 | W44: =IFERROR(GETPIVOTDATA("Area AGM",'Pvt OS'!#REF!,"Dealer",""&$S$18&"","Model",""&$S44&""),0)+IFERROR(GETPIVOTDATA("Area AGM",'Pvt OS'!$A$8,"Dealer",""&$S$18&"","Model",""&$S44&""),0) -> 0 | X44: =SUM(Y44:AB44) -> 0 | Y44: =IFERROR(GETPIVOTDATA("Area AGM",'Pvt OS'!$U$8,"Dealer",""&$S$18&"","Model",""&$S44&""),0) -> 0 | Z44: =IFERROR(GETPIVOTDATA("Area AGM",'Pvt OS'!$M$8,"Dealer",""&$S$18&"","Model",""&$S44&""),0) -> 0 | AA44: =IFERROR(GETPIVOTDATA("Area AGM",'Pvt OS'!#REF!,"Dealer",""&$S$18&"","Model",""&$S44&""),0) -> 0 | AB44: =IFERROR(GETPIVOTDATA("Area AGM",'Pvt OS'!$AO$8,"Dealer",""&$S$18&"","Model",""&$S44&""),0) -> 0 | AC44: =IFERROR(GETPIVOTDATA("Stock",#REF!,"Dealer",""&$S$18&"","Model",""&$S44&""),0) -> 0 | AD44: =IFERROR(GETPIVOTDATA("MDP",#REF!,"Dealer",""&$S$18&"","Model",""&$S44&""),0) -> 0 | AE44: =IFERROR(GETPIVOTDATA("RRN",#REF!,"Model2",""&$S44&"","Dealer",""&$S$18&""),0) -> 0 | AF44: =IFERROR(GETPIVOTDATA("CO",#REF!,"Dealer Name",""&$S$18&"","Model",""&$S44&""),0) -> 0 | AG44: =IFERROR(GETPIVOTDATA("Sum of Distplan Final",#REF!,"Dealer",""&$S$18&"","Model",""&$S44&""),0) -> 0 | AH44: =IFERROR(GETPIVOTDATA("RRN",#REF!,"Model",""&$S44&"","Dealer",""&$S$18&""),0) -> 0 | AI44: =AC44+AD44+AF44+AG44-AH44 -> 0 | AJ44: =IFERROR(GETPIVOTDATA("volume_rs",#REF!,"Model",""&$S44&"","Dealer",""&$S$18&""),0) -> 0 | AK44: =AI44-AJ44-X44+AN44 -> 0 | AL44: =IFERROR(GETPIVOTDATA("Area AGM",'Pvt OS'!#REF!,"Dealer",""&$S$18&"","Model",""&$S44&""),0) -> 0 | AM44: =AK44+AL44 -> 0 | AN44: =IFERROR(GETPIVOTDATA("Row Labels",#REF!,"Dealer",""&$S$18&"","Model",""&$S44&""),0) -> 0 | AO44: =IFERROR(GETPIVOTDATA("RS Afi",#REF!,"Dealer",""&$S$18&"","Model",""&$S44&""),0) -> 0 | AP44: =IFERROR(GETPIVOTDATA("qty",#REF!,"Model",""&$S44&"","Dealer",""&$S$18&""),0) -> 0 | AQ44: =IFERROR(GETPIVOTDATA("volume_rs",#REF!,"Model",""&$S44&"","Dealer",""&$S$18&""),0) -> 0 | AR44: =AP44-AQ44 -> 0 | AS44: =IFERROR(GETPIVOTDATA("Area AGM",'Pvt OS'!#REF!,"Dealer",""&$S$18&"","Model",""&$S44&""),0) -> 0 | AT44: =AR44-AS44 -> 0
B45: GR YARIS | C45: =SUM(D45:G45) -> 0 | D45: =IFERROR(GETPIVOTDATA("Area AGM",#REF!,"Dealer",""&$S$18&"","Model",""&$B45&"","Umur Outstansing",""&D$2&""),0) -> 0 | E45: =IFERROR(GETPIVOTDATA("Area AGM",#REF!,"Dealer",""&$S$18&"","Model",""&$B45&"","Umur Outstansing",""&E$2&""),0) -> 0 | F45: =IFERROR(GETPIVOTDATA("Area AGM",#REF!,"Dealer",""&$S$18&"","Model",""&$B45&"","Umur Outstansing",""&F$2&""),0) -> 0 | G45: =IFERROR(GETPIVOTDATA("Area AGM",#REF!,"Dealer",""&$S$18&"","Model",""&$B45&"","Umur Outstansing",""&G$2&""),0) -> 0 | H45: =IFERROR(GETPIVOTDATA("Area AGM",#REF!,"Dealer",""&$S$18&"","Model",""&$B45&"","Umur Outstansing",""&H$2&""),0) -> 0 | J45: =IFERROR(GETPIVOTDATA("Area AGM",#REF!,"Dealer",""&$S$18&"","Model",""&$B45&""),0) -> 0 | K45: =IFERROR(GETPIVOTDATA("Area AGM",#REF!,"Dealer",""&$S$18&"","Model",""&$B45&""),0) -> 0 | P45: HILUX S-CAB | Q45: =IFERROR(R45/AI45,0) -> 0 | R45: =IFERROR(GETPIVOTDATA("RS Target",#REF!,"Dealer",""&$S$18&"","Model",""&$P45&""),0) -> 0 | S45: HILUX S-CAB | T45: =SUM(Y45:AB45,AO45) -> 0 | U45: =IFERROR(GETPIVOTDATA("Area AGM",'Pvt OS'!#REF!,"Dealer",""&$S$18&"","Model",""&$S45&""),0) -> 0 | V45: =W45-X45 -> 0 | W45: =IFERROR(GETPIVOTDATA("Area AGM",'Pvt OS'!#REF!,"Dealer",""&$S$18&"","Model",""&$S45&""),0)+IFERROR(GETPIVOTDATA("Area AGM",'Pvt OS'!$A$8,"Dealer",""&$S$18&"","Model",""&$S45&""),0) -> 0 | X45: =SUM(Y45:AB45) -> 0 | Y45: =IFERROR(GETPIVOTDATA("Area AGM",'Pvt OS'!$U$8,"Dealer",""&$S$18&"","Model",""&$S45&""),0) -> 0 | Z45: =IFERROR(GETPIVOTDATA("Area AGM",'Pvt OS'!$M$8,"Dealer",""&$S$18&"","Model",""&$S45&""),0) -> 0 | AA45: =IFERROR(GETPIVOTDATA("Area AGM",'Pvt OS'!#REF!,"Dealer",""&$S$18&"","Model",""&$S45&""),0) -> 0 | AB45: =IFERROR(GETPIVOTDATA("Area AGM",'Pvt OS'!$AO$8,"Dealer",""&$S$18&"","Model",""&$S45&""),0) -> 0 | AC45: =IFERROR(GETPIVOTDATA("Stock",#REF!,"Dealer",""&$S$18&"","Model",""&$S45&""),0) -> 0 | AD45: =IFERROR(GETPIVOTDATA("MDP",#REF!,"Dealer",""&$S$18&"","Model",""&$S45&""),0) -> 0 | AE45: =IFERROR(GETPIVOTDATA("RRN",#REF!,"Model2",""&$S45&"","Dealer",""&$S$18&""),0) -> 0 | AF45: =IFERROR(GETPIVOTDATA("CO",#REF!,"Dealer Name",""&$S$18&"","Model",""&$S45&""),0) -> 0 | AG45: =IFERROR(GETPIVOTDATA("Sum of Distplan Final",#REF!,"Dealer",""&$S$18&"","Model",""&$S45&""),0) -> 0 | AH45: =IFERROR(GETPIVOTDATA("RRN",#REF!,"Model",""&$S45&"","Dealer",""&$S$18&""),0) -> 0 | AI45: =AC45+AD45+AF45+AG45-AH45 -> 0 | AJ45: =IFERROR(GETPIVOTDATA("volume_rs",#REF!,"Model",""&$S45&"","Dealer",""&$S$18&""),0) -> 0 | AK45: =AI45-AJ45-X45+AN45 -> 0 | AL45: =IFERROR(GETPIVOTDATA("Area AGM",'Pvt OS'!#REF!,"Dealer",""&$S$18&"","Model",""&$S45&""),0) -> 0 | AM45: =AK45+AL45 -> 0 | AN45: =IFERROR(GETPIVOTDATA("Row Labels",#REF!,"Dealer",""&$S$18&"","Model",""&$S45&""),0) -> 0 | AO45: =IFERROR(GETPIVOTDATA("RS Afi",#REF!,"Dealer",""&$S$18&"","Model",""&$S45&""),0) -> 0 | AP45: =IFERROR(GETPIVOTDATA("qty",#REF!,"Model",""&$S45&"","Dealer",""&$S$18&""),0) -> 0 | AQ45: =IFERROR(GETPIVOTDATA("volume_rs",#REF!,"Model",""&$S45&"","Dealer",""&$S$18&""),0) -> 0 | AR45: =AP45-AQ45 -> 0 | AS45: =IFERROR(GETPIVOTDATA("Area AGM",'Pvt OS'!#REF!,"Dealer",""&$S$18&"","Model",""&$S45&""),0) -> 0 | AT45: =AR45-AS45 -> 0
B46: CROWN | C46: =SUM(D46:G46) -> 0 | D46: =IFERROR(GETPIVOTDATA("Area AGM",#REF!,"Dealer",""&$S$18&"","Model",""&$B46&"","Umur Outstansing",""&D$2&""),0) -> 0 | E46: =IFERROR(GETPIVOTDATA("Area AGM",#REF!,"Dealer",""&$S$18&"","Model",""&$B46&"","Umur Outstansing",""&E$2&""),0) -> 0 | F46: =IFERROR(GETPIVOTDATA("Area AGM",#REF!,"Dealer",""&$S$18&"","Model",""&$B46&"","Umur Outstansing",""&F$2&""),0) -> 0 | G46: =IFERROR(GETPIVOTDATA("Area AGM",#REF!,"Dealer",""&$S$18&"","Model",""&$B46&"","Umur Outstansing",""&G$2&""),0) -> 0 | H46: =IFERROR(GETPIVOTDATA("Area AGM",#REF!,"Dealer",""&$S$18&"","Model",""&$B46&"","Umur Outstansing",""&H$2&""),0) -> 0 | J46: =IFERROR(GETPIVOTDATA("Area AGM",#REF!,"Dealer",""&$S$18&"","Model",""&$B46&""),0) -> 0 | K46: =IFERROR(GETPIVOTDATA("Area AGM",#REF!,"Dealer",""&$S$18&"","Model",""&$B46&""),0) -> 0 | P46: TRANSMOVER | Q46: =IFERROR(R46/AI46,0) -> 0 | R46: =IFERROR(GETPIVOTDATA("RS Target",#REF!,"Dealer",""&$S$18&"","Model",""&$P46&""),0) -> 0 | S46: TRANSMOVER | T46: =SUM(Y46:AB46,AO46) -> 0 | U46: =IFERROR(GETPIVOTDATA("Area AGM",'Pvt OS'!#REF!,"Dealer",""&$S$18&"","Model",""&$S46&""),0) -> 0 | V46: =W46-X46 -> 0 | W46: =IFERROR(GETPIVOTDATA("Area AGM",'Pvt OS'!#REF!,"Dealer",""&$S$18&"","Model",""&$S46&""),0)+IFERROR(GETPIVOTDATA("Area AGM",'Pvt OS'!$A$8,"Dealer",""&$S$18&"","Model",""&$S46&""),0) -> 0 | X46: =SUM(Y46:AB46) -> 0 | Y46: =IFERROR(GETPIVOTDATA("Area AGM",'Pvt OS'!$U$8,"Dealer",""&$S$18&"","Model",""&$S46&""),0) -> 0 | Z46: =IFERROR(GETPIVOTDATA("Area AGM",'Pvt OS'!$M$8,"Dealer",""&$S$18&"","Model",""&$S46&""),0) -> 0 | AA46: =IFERROR(GETPIVOTDATA("Area AGM",'Pvt OS'!#REF!,"Dealer",""&$S$18&"","Model",""&$S46&""),0) -> 0 | AB46: =IFERROR(GETPIVOTDATA("Area AGM",'Pvt OS'!$AO$8,"Dealer",""&$S$18&"","Model",""&$S46&""),0) -> 0 | AC46: =IFERROR(GETPIVOTDATA("Stock",#REF!,"Dealer",""&$S$18&"","Model",""&$S46&""),0) -> 0 | AD46: =IFERROR(GETPIVOTDATA("MDP",#REF!,"Dealer",""&$S$18&"","Model",""&$S46&""),0) -> 0 | AE46: =IFERROR(GETPIVOTDATA("RRN",#REF!,"Model2",""&$S46&"","Dealer",""&$S$18&""),0) -> 0 | AF46: =IFERROR(GETPIVOTDATA("CO",#REF!,"Dealer Name",""&$S$18&"","Model",""&$S46&""),0) -> 0 | AG46: =IFERROR(GETPIVOTDATA("Sum of Distplan Final",#REF!,"Dealer",""&$S$18&"","Model",""&$S46&""),0) -> 0 | AH46: =IFERROR(GETPIVOTDATA("RRN",#REF!,"Model",""&$S46&"","Dealer",""&$S$18&""),0) -> 0 | AI46: =AC46+AD46+AF46+AG46-AH46 -> 0 | AJ46: =IFERROR(GETPIVOTDATA("volume_rs",#REF!,"Model",""&$S46&"","Dealer",""&$S$18&""),0) -> 0 | AK46: =AI46-AJ46-X46+AN46 -> 0 | AL46: =IFERROR(GETPIVOTDATA("Area AGM",'Pvt OS'!#REF!,"Dealer",""&$S$18&"","Model",""&$S46&""),0) -> 0 | AM46: =AK46+AL46 -> 0 | AN46: =IFERROR(GETPIVOTDATA("Row Labels",#REF!,"Dealer",""&$S$18&"","Model",""&$S46&""),0) -> 0 | AO46: =IFERROR(GETPIVOTDATA("RS Afi",#REF!,"Dealer",""&$S$18&"","Model",""&$S46&""),0) -> 0 | AP46: =IFERROR(GETPIVOTDATA("qty",#REF!,"Model",""&$S46&"","Dealer",""&$S$18&""),0) -> 0 | AQ46: =IFERROR(GETPIVOTDATA("volume_rs",#REF!,"Model",""&$S46&"","Dealer",""&$S$18&""),0) -> 0 | AR46: =AP46-AQ46 -> 0 | AS46: =IFERROR(GETPIVOTDATA("Area AGM",'Pvt OS'!#REF!,"Dealer",""&$S$18&"","Model",""&$S46&""),0) -> 0 | AT46: =AR46-AS46 -> 0
... B53: LANDCRUISER 300 | C53: =SUM(D53:G53) -> 0 | D53: =IFERROR(GETPIVOTDATA("Area AGM",#REF!,"Dealer",""&$S$18&"","Model",""&$B53&"","Umur Outstansing",""&D$2&""),0) -> 0 | E53: =IFERROR(GETPIVOTDATA("Area AGM",#REF!,"Dealer",""&$S$18&"","Model",""&$B53&"","Umur Outstansing",""&E$2&""),0) -> 0 | F53: =IFERROR(GETPIVOTDATA("Area AGM",#REF!,"Dealer",""&$S$18&"","Model",""&$B53&"","Umur Outstansing",""&F$2&""),0) -> 0 | G53: =IFERROR(GETPIVOTDATA("Area AGM",#REF!,"Dealer",""&$S$18&"","Model",""&$B53&"","Umur Outstansing",""&G$2&""),0) -> 0 | H53: =IFERROR(GETPIVOTDATA("Area AGM",#REF!,"Dealer",""&$S$18&"","Model",""&$B53&"","Umur Outstansing",""&H$2&""),0) -> 0 | J53: =IFERROR(GETPIVOTDATA("Area AGM",#REF!,"Dealer",""&$S$18&"","Model",""&$B53&""),0) -> 0 | K53: =IFERROR(GETPIVOTDATA("Area AGM",#REF!,"Dealer",""&$S$18&"","Model",""&$B53&""),0) -> 0 | P53: COROLLA CROSS HYBRID | Q53: =IFERROR(R53/AI53,0) -> 0 | R53: =IFERROR(GETPIVOTDATA("RS Target",#REF!,"Dealer",""&$S$18&"","Model",""&$P53&""),0) -> 0 | S53: COROLLA CROSS HYBRID | T53: =SUM(Y53:AB53,AO53) -> 0 | U53: =IFERROR(GETPIVOTDATA("Area AGM",'Pvt OS'!#REF!,"Dealer",""&$S$18&"","Model",""&$S53&""),0) -> 0 | V53: =W53-X53 -> 0 | W53: =IFERROR(GETPIVOTDATA("Area AGM",'Pvt OS'!#REF!,"Dealer",""&$S$18&"","Model",""&$S53&""),0)+IFERROR(GETPIVOTDATA("Area AGM",'Pvt OS'!$A$8,"Dealer",""&$S$18&"","Model",""&$S53&""),0) -> 0 | X53: =SUM(Y53:AB53) -> 0 | Y53: =IFERROR(GETPIVOTDATA("Area AGM",'Pvt OS'!$U$8,"Dealer",""&$S$18&"","Model",""&$S53&""),0) -> 0 | Z53: =IFERROR(GETPIVOTDATA("Area AGM",'Pvt OS'!$M$8,"Dealer",""&$S$18&"","Model",""&$S53&""),0) -> 0 | AA53: =IFERROR(GETPIVOTDATA("Area AGM",'Pvt OS'!#REF!,"Dealer",""&$S$18&"","Model",""&$S53&""),0) -> 0 | AB53: =IFERROR(GETPIVOTDATA("Area AGM",'Pvt OS'!$AO$8,"Dealer",""&$S$18&"","Model",""&$S53&""),0) -> 0 | AC53: =IFERROR(GETPIVOTDATA("Stock",#REF!,"Dealer",""&$S$18&"","Model",""&$S53&""),0) -> 0 | AD53: =IFERROR(GETPIVOTDATA("MDP",#REF!,"Dealer",""&$S$18&"","Model",""&$S53&""),0) -> 0 | AE53: =IFERROR(GETPIVOTDATA("RRN",#REF!,"Model2",""&$S53&"","Dealer",""&$S$18&""),0) -> 0 | AF53: =IFERROR(GETPIVOTDATA("CO",#REF!,"Dealer Name",""&$S$18&"","Model",""&$S53&""),0) -> 0 | AG53: =IFERROR(GETPIVOTDATA("Sum of Distplan Final",#REF!,"Dealer",""&$S$18&"","Model",""&$S53&""),0) -> 0 | AH53: =IFERROR(GETPIVOTDATA("RRN",#REF!,"Model",""&$S53&"","Dealer",""&$S$18&""),0) -> 0 | AI53: =AC53+AD53+AF53+AG53-AH53 -> 0 | AJ53: =IFERROR(GETPIVOTDATA("volume_rs",#REF!,"Model",""&$S53&"","Dealer",""&$S$18&""),0) -> 0 | AK53: =AI53-AJ53-X53+AN53 -> 0 | AL53: =IFERROR(GETPIVOTDATA("Area AGM",'Pvt OS'!#REF!,"Dealer",""&$S$18&"","Model",""&$S53&""),0) -> 0 | AM53: =AK53+AL53 -> 0 | AN53: =IFERROR(GETPIVOTDATA("Row Labels",#REF!,"Dealer",""&$S$18&"","Model",""&$S53&""),0) -> 0 | AO53: =IFERROR(GETPIVOTDATA("RS Afi",#REF!,"Dealer",""&$S$18&"","Model",""&$S53&""),0) -> 0 | AP53: =IFERROR(GETPIVOTDATA("qty",#REF!,"Model",""&$S53&"","Dealer",""&$S$18&""),0) -> 0 | AQ53: =IFERROR(GETPIVOTDATA("volume_rs",#REF!,"Model",""&$S53&"","Dealer",""&$S$18&""),0) -> 0 | AR53: =AP53-AQ53 -> 0 | AS53: =IFERROR(GETPIVOTDATA("Area AGM",'Pvt OS'!#REF!,"Dealer",""&$S$18&"","Model",""&$S53&""),0) -> 0 | AT53: =AR53-AS53 -> 0
P54: COROLLA CROSS | Q54: =IFERROR(R54/AI54,0) -> 0 | R54: =IFERROR(GETPIVOTDATA("RS Target",#REF!,"Dealer",""&$S$18&"","Model",""&$P54&""),0) -> 0 | S54: COROLLA CROSS | T54: =SUM(Y54:AB54,AO54) -> 0 | U54: =IFERROR(GETPIVOTDATA("Area AGM",'Pvt OS'!#REF!,"Dealer",""&$S$18&"","Model",""&$S54&""),0) -> 0 | V54: =W54-X54 -> 0 | W54: =IFERROR(GETPIVOTDATA("Area AGM",'Pvt OS'!#REF!,"Dealer",""&$S$18&"","Model",""&$S54&""),0)+IFERROR(GETPIVOTDATA("Area AGM",'Pvt OS'!$A$8,"Dealer",""&$S$18&"","Model",""&$S54&""),0) -> 0 | X54: =SUM(Y54:AB54) -> 0 | Y54: =IFERROR(GETPIVOTDATA("Area AGM",'Pvt OS'!$U$8,"Dealer",""&$S$18&"","Model",""&$S54&""),0) -> 0 | Z54: =IFERROR(GETPIVOTDATA("Area AGM",'Pvt OS'!$M$8,"Dealer",""&$S$18&"","Model",""&$S54&""),0) -> 0 | AA54: =IFERROR(GETPIVOTDATA("Area AGM",'Pvt OS'!#REF!,"Dealer",""&$S$18&"","Model",""&$S54&""),0) -> 0 | AB54: =IFERROR(GETPIVOTDATA("Area AGM",'Pvt OS'!$AO$8,"Dealer",""&$S$18&"","Model",""&$S54&""),0) -> 0 | AC54: =IFERROR(GETPIVOTDATA("Stock",#REF!,"Dealer",""&$S$18&"","Model",""&$S54&""),0) -> 0 | AD54: =IFERROR(GETPIVOTDATA("MDP",#REF!,"Dealer",""&$S$18&"","Model",""&$S54&""),0) -> 0 | AE54: =IFERROR(GETPIVOTDATA("RRN",#REF!,"Model2",""&$S54&"","Dealer",""&$S$18&""),0) -> 0 | AF54: =IFERROR(GETPIVOTDATA("CO",#REF!,"Dealer Name",""&$S$18&"","Model",""&$S54&""),0) -> 0 | AG54: =IFERROR(GETPIVOTDATA("Sum of Distplan Final",#REF!,"Dealer",""&$S$18&"","Model",""&$S54&""),0) -> 0 | AH54: =IFERROR(GETPIVOTDATA("RRN",#REF!,"Model",""&$S54&"","Dealer",""&$S$18&""),0) -> 0 | AI54: =AC54+AD54+AF54+AG54-AH54 -> 0 | AJ54: =IFERROR(GETPIVOTDATA("volume_rs",#REF!,"Model",""&$S54&"","Dealer",""&$S$18&""),0) -> 0 | AK54: =AI54-AJ54-X54+AN54 -> 0 | AL54: =IFERROR(GETPIVOTDATA("Area AGM",'Pvt OS'!#REF!,"Dealer",""&$S$18&"","Model",""&$S54&""),0) -> 0 | AM54: =AK54+AL54 -> 0 | AN54: =IFERROR(GETPIVOTDATA("Row Labels",#REF!,"Dealer",""&$S$18&"","Model",""&$S54&""),0) -> 0 | AO54: =IFERROR(GETPIVOTDATA("RS Afi",#REF!,"Dealer",""&$S$18&"","Model",""&$S54&""),0) -> 0 | AP54: =IFERROR(GETPIVOTDATA("qty",#REF!,"Model",""&$S54&"","Dealer",""&$S$18&""),0) -> 0 | AQ54: =IFERROR(GETPIVOTDATA("volume_rs",#REF!,"Model",""&$S54&"","Dealer",""&$S$18&""),0) -> 0 | AR54: =AP54-AQ54 -> 0 | AS54: =IFERROR(GETPIVOTDATA("Area AGM",'Pvt OS'!#REF!,"Dealer",""&$S$18&"","Model",""&$S54&""),0) -> 0 | AT54: =AR54-AS54 -> 0
P55: COROLLA | Q55: =IFERROR(R55/AI55,0) -> 0 | R55: =IFERROR(GETPIVOTDATA("RS Target",#REF!,"Dealer",""&$S$18&"","Model",""&$P55&""),0) -> 0 | S55: COROLLA | T55: =SUM(Y55:AB55,AO55) -> 0 | U55: =IFERROR(GETPIVOTDATA("Area AGM",'Pvt OS'!#REF!,"Dealer",""&$S$18&"","Model",""&$S55&""),0) -> 0 | V55: =W55-X55 -> 0 | W55: =IFERROR(GETPIVOTDATA("Area AGM",'Pvt OS'!#REF!,"Dealer",""&$S$18&"","Model",""&$S55&""),0)+IFERROR(GETPIVOTDATA("Area AGM",'Pvt OS'!$A$8,"Dealer",""&$S$18&"","Model",""&$S55&""),0) -> 0 | X55: =SUM(Y55:AB55) -> 0 | Y55: =IFERROR(GETPIVOTDATA("Area AGM",'Pvt OS'!$U$8,"Dealer",""&$S$18&"","Model",""&$S55&""),0) -> 0 | Z55: =IFERROR(GETPIVOTDATA("Area AGM",'Pvt OS'!$M$8,"Dealer",""&$S$18&"","Model",""&$S55&""),0) -> 0 | AA55: =IFERROR(GETPIVOTDATA("Area AGM",'Pvt OS'!#REF!,"Dealer",""&$S$18&"","Model",""&$S55&""),0) -> 0 | AB55: =IFERROR(GETPIVOTDATA("Area AGM",'Pvt OS'!$AO$8,"Dealer",""&$S$18&"","Model",""&$S55&""),0) -> 0 | AC55: =IFERROR(GETPIVOTDATA("Stock",#REF!,"Dealer",""&$S$18&"","Model",""&$S55&""),0) -> 0 | AD55: =IFERROR(GETPIVOTDATA("MDP",#REF!,"Dealer",""&$S$18&"","Model",""&$S55&""),0) -> 0 | AE55: =IFERROR(GETPIVOTDATA("RRN",#REF!,"Model2",""&$S55&"","Dealer",""&$S$18&""),0) -> 0 | AF55: =IFERROR(GETPIVOTDATA("CO",#REF!,"Dealer Name",""&$S$18&"","Model",""&$S55&""),0) -> 0 | AG55: =IFERROR(GETPIVOTDATA("Sum of Distplan Final",#REF!,"Dealer",""&$S$18&"","Model",""&$S55&""),0) -> 0 | AH55: =IFERROR(GETPIVOTDATA("RRN",#REF!,"Model",""&$S55&"","Dealer",""&$S$18&""),0) -> 0 | AI55: =AC55+AD55+AF55+AG55-AH55 -> 0 | AJ55: =IFERROR(GETPIVOTDATA("volume_rs",#REF!,"Model",""&$S55&"","Dealer",""&$S$18&""),0) -> 0 | AK55: =AI55-AJ55-X55+AN55 -> 0 | AL55: =IFERROR(GETPIVOTDATA("Area AGM",'Pvt OS'!#REF!,"Dealer",""&$S$18&"","Model",""&$S55&""),0) -> 0 | AM55: =AK55+AL55 -> 0 | AN55: =IFERROR(GETPIVOTDATA("Row Labels",#REF!,"Dealer",""&$S$18&"","Model",""&$S55&""),0) -> 0 | AO55: =IFERROR(GETPIVOTDATA("RS Afi",#REF!,"Dealer",""&$S$18&"","Model",""&$S55&""),0) -> 0 | AP55: =IFERROR(GETPIVOTDATA("qty",#REF!,"Model",""&$S55&"","Dealer",""&$S$18&""),0) -> 0 | AQ55: =IFERROR(GETPIVOTDATA("volume_rs",#REF!,"Model",""&$S55&"","Dealer",""&$S$18&""),0) -> 0 | AR55: =AP55-AQ55 -> 0 | AS55: =IFERROR(GETPIVOTDATA("Area AGM",'Pvt OS'!#REF!,"Dealer",""&$S$18&"","Model",""&$S55&""),0) -> 0 | AT55: =AR55-AS55 -> 0
P56: CAMRY HYBRID | Q56: =IFERROR(R56/AI56,0) -> 0 | R56: =IFERROR(GETPIVOTDATA("RS Target",#REF!,"Dealer",""&$S$18&"","Model",""&$P56&""),0) -> 0 | S56: CAMRY HYBRID | T56: =SUM(Y56:AB56,AO56) -> 0 | U56: =IFERROR(GETPIVOTDATA("Area AGM",'Pvt OS'!#REF!,"Dealer",""&$S$18&"","Model",""&$S56&""),0) -> 0 | V56: =W56-X56 -> 0 | W56: =IFERROR(GETPIVOTDATA("Area AGM",'Pvt OS'!#REF!,"Dealer",""&$S$18&"","Model",""&$S56&""),0)+IFERROR(GETPIVOTDATA("Area AGM",'Pvt OS'!$A$8,"Dealer",""&$S$18&"","Model",""&$S56&""),0) -> 0 | X56: =SUM(Y56:AB56) -> 0 | Y56: =IFERROR(GETPIVOTDATA("Area AGM",'Pvt OS'!$U$8,"Dealer",""&$S$18&"","Model",""&$S56&""),0) -> 0 | Z56: =IFERROR(GETPIVOTDATA("Area AGM",'Pvt OS'!$M$8,"Dealer",""&$S$18&"","Model",""&$S56&""),0) -> 0 | AA56: =IFERROR(GETPIVOTDATA("Area AGM",'Pvt OS'!#REF!,"Dealer",""&$S$18&"","Model",""&$S56&""),0) -> 0 | AB56: =IFERROR(GETPIVOTDATA("Area AGM",'Pvt OS'!$AO$8,"Dealer",""&$S$18&"","Model",""&$S56&""),0) -> 0 | AC56: =IFERROR(GETPIVOTDATA("Stock",#REF!,"Dealer",""&$S$18&"","Model",""&$S56&""),0) -> 0 | AD56: =IFERROR(GETPIVOTDATA("MDP",#REF!,"Dealer",""&$S$18&"","Model",""&$S56&""),0) -> 0 | AE56: =IFERROR(GETPIVOTDATA("RRN",#REF!,"Model2",""&$S56&"","Dealer",""&$S$18&""),0) -> 0 | AF56: =IFERROR(GETPIVOTDATA("CO",#REF!,"Dealer Name",""&$S$18&"","Model",""&$S56&""),0) -> 0 | AG56: =IFERROR(GETPIVOTDATA("Sum of Distplan Final",#REF!,"Dealer",""&$S$18&"","Model",""&$S56&""),0) -> 0 | AH56: =IFERROR(GETPIVOTDATA("RRN",#REF!,"Model",""&$S56&"","Dealer",""&$S$18&""),0) -> 0 | AI56: =AC56+AD56+AF56+AG56-AH56 -> 0 | AJ56: =IFERROR(GETPIVOTDATA("volume_rs",#REF!,"Model",""&$S56&"","Dealer",""&$S$18&""),0) -> 0 | AK56: =AI56-AJ56-X56+AN56 -> 0 | AL56: =IFERROR(GETPIVOTDATA("Area AGM",'Pvt OS'!#REF!,"Dealer",""&$S$18&"","Model",""&$S56&""),0) -> 0 | AM56: =AK56+AL56 -> 0 | AN56: =IFERROR(GETPIVOTDATA("Row Labels",#REF!,"Dealer",""&$S$18&"","Model",""&$S56&""),0) -> 0 | AO56: =IFERROR(GETPIVOTDATA("RS Afi",#REF!,"Dealer",""&$S$18&"","Model",""&$S56&""),0) -> 0 | AP56: =IFERROR(GETPIVOTDATA("qty",#REF!,"Model",""&$S56&"","Dealer",""&$S$18&""),0) -> 0 | AQ56: =IFERROR(GETPIVOTDATA("volume_rs",#REF!,"Model",""&$S56&"","Dealer",""&$S$18&""),0) -> 0 | AR56: =AP56-AQ56 -> 0 | AS56: =IFERROR(GETPIVOTDATA("Area AGM",'Pvt OS'!#REF!,"Dealer",""&$S$18&"","Model",""&$S56&""),0) -> 0 | AT56: =AR56-AS56 -> 0
P57: COROLLA HYBRID | Q57: =IFERROR(R57/AI57,0) -> 0 | R57: =IFERROR(GETPIVOTDATA("RS Target",#REF!,"Dealer",""&$S$18&"","Model",""&$P57&""),0) -> 0 | S57: COROLLA HYBRID | T57: =SUM(Y57:AB57,AO57) -> 0 | U57: =IFERROR(GETPIVOTDATA("Area AGM",'Pvt OS'!#REF!,"Dealer",""&$S$18&"","Model",""&$S57&""),0) -> 0 | V57: =W57-X57 -> 0 | W57: =IFERROR(GETPIVOTDATA("Area AGM",'Pvt OS'!#REF!,"Dealer",""&$S$18&"","Model",""&$S57&""),0)+IFERROR(GETPIVOTDATA("Area AGM",'Pvt OS'!$A$8,"Dealer",""&$S$18&"","Model",""&$S57&""),0) -> 0 | X57: =SUM(Y57:AB57) -> 0 | Y57: =IFERROR(GETPIVOTDATA("Area AGM",'Pvt OS'!$U$8,"Dealer",""&$S$18&"","Model",""&$S57&""),0) -> 0 | Z57: =IFERROR(GETPIVOTDATA("Area AGM",'Pvt OS'!$M$8,"Dealer",""&$S$18&"","Model",""&$S57&""),0) -> 0 | AA57: =IFERROR(GETPIVOTDATA("Area AGM",'Pvt OS'!#REF!,"Dealer",""&$S$18&"","Model",""&$S57&""),0) -> 0 | AB57: =IFERROR(GETPIVOTDATA("Area AGM",'Pvt OS'!$AO$8,"Dealer",""&$S$18&"","Model",""&$S57&""),0) -> 0 | AC57: =IFERROR(GETPIVOTDATA("Stock",#REF!,"Dealer",""&$S$18&"","Model",""&$S57&""),0) -> 0 | AD57: =IFERROR(GETPIVOTDATA("MDP",#REF!,"Dealer",""&$S$18&"","Model",""&$S57&""),0) -> 0 | AE57: =IFERROR(GETPIVOTDATA("RRN",#REF!,"Model2",""&$S57&"","Dealer",""&$S$18&""),0) -> 0 | AF57: =IFERROR(GETPIVOTDATA("CO",#REF!,"Dealer Name",""&$S$18&"","Model",""&$S57&""),0) -> 0 | AG57: =IFERROR(GETPIVOTDATA("Sum of Distplan Final",#REF!,"Dealer",""&$S$18&"","Model",""&$S57&""),0) -> 0 | AH57: =IFERROR(GETPIVOTDATA("RRN",#REF!,"Model",""&$S57&"","Dealer",""&$S$18&""),0) -> 0 | AI57: =AC57+AD57+AF57+AG57-AH57 -> 0 | AJ57: =IFERROR(GETPIVOTDATA("volume_rs",#REF!,"Model",""&$S57&"","Dealer",""&$S$18&""),0) -> 0 | AK57: =AI57-AJ57-X57+AN57 -> 0 | AL57: =IFERROR(GETPIVOTDATA("Area AGM",'Pvt OS'!#REF!,"Dealer",""&$S$18&"","Model",""&$S57&""),0) -> 0 | AM57: =AK57+AL57 -> 0 | AN57: =IFERROR(GETPIVOTDATA("Row Labels",#REF!,"Dealer",""&$S$18&"","Model",""&$S57&""),0) -> 0 | AO57: =IFERROR(GETPIVOTDATA("RS Afi",#REF!,"Dealer",""&$S$18&"","Model",""&$S57&""),0) -> 0 | AP57: =IFERROR(GETPIVOTDATA("qty",#REF!,"Model",""&$S57&"","Dealer",""&$S$18&""),0) -> 0 | AQ57: =IFERROR(GETPIVOTDATA("volume_rs",#REF!,"Model",""&$S57&"","Dealer",""&$S$18&""),0) -> 0 | AR57: =AP57-AQ57 -> 0 | AS57: =IFERROR(GETPIVOTDATA("Area AGM",'Pvt OS'!#REF!,"Dealer",""&$S$18&"","Model",""&$S57&""),0) -> 0 | AT57: =AR57-AS57 -> 0
P58: SUPRA | Q58: =IFERROR(R58/AI58,0) -> 0 | R58: =IFERROR(GETPIVOTDATA("RS Target",#REF!,"Dealer",""&$S$18&"","Model",""&$P58&""),0) -> 0 | S58: SUPRA | T58: =SUM(Y58:AB58,AO58) -> 0 | U58: =IFERROR(GETPIVOTDATA("Area AGM",'Pvt OS'!#REF!,"Dealer",""&$S$18&"","Model",""&$S58&""),0) -> 0 | V58: =W58-X58 -> 0 | W58: =IFERROR(GETPIVOTDATA("Area AGM",'Pvt OS'!#REF!,"Dealer",""&$S$18&"","Model",""&$S58&""),0)+IFERROR(GETPIVOTDATA("Area AGM",'Pvt OS'!$A$8,"Dealer",""&$S$18&"","Model",""&$S58&""),0) -> 0 | X58: =SUM(Y58:AB58) -> 0 | Y58: =IFERROR(GETPIVOTDATA("Area AGM",'Pvt OS'!$U$8,"Dealer",""&$S$18&"","Model",""&$S58&""),0) -> 0 | Z58: =IFERROR(GETPIVOTDATA("Area AGM",'Pvt OS'!$M$8,"Dealer",""&$S$18&"","Model",""&$S58&""),0) -> 0 | AA58: =IFERROR(GETPIVOTDATA("Area AGM",'Pvt OS'!#REF!,"Dealer",""&$S$18&"","Model",""&$S58&""),0) -> 0 | AB58: =IFERROR(GETPIVOTDATA("Area AGM",'Pvt OS'!$AO$8,"Dealer",""&$S$18&"","Model",""&$S58&""),0) -> 0 | AC58: =IFERROR(GETPIVOTDATA("Stock",#REF!,"Dealer",""&$S$18&"","Model",""&$S58&""),0) -> 0 | AD58: =IFERROR(GETPIVOTDATA("MDP",#REF!,"Dealer",""&$S$18&"","Model",""&$S58&""),0) -> 0 | AE58: =IFERROR(GETPIVOTDATA("RRN",#REF!,"Model2",""&$S58&"","Dealer",""&$S$18&""),0) -> 0 | AF58: =IFERROR(GETPIVOTDATA("CO",#REF!,"Dealer Name",""&$S$18&"","Model",""&$S58&""),0) -> 0 | AG58: =IFERROR(GETPIVOTDATA("Sum of Distplan Final",#REF!,"Dealer",""&$S$18&"","Model",""&$S58&""),0) -> 0 | AH58: =IFERROR(GETPIVOTDATA("RRN",#REF!,"Model",""&$S58&"","Dealer",""&$S$18&""),0) -> 0 | AI58: =AC58+AD58+AF58+AG58-AH58 -> 0 | AJ58: =IFERROR(GETPIVOTDATA("volume_rs",#REF!,"Model",""&$S58&"","Dealer",""&$S$18&""),0) -> 0 | AK58: =AI58-AJ58-X58+AN58 -> 0 | AL58: =IFERROR(GETPIVOTDATA("Area AGM",'Pvt OS'!#REF!,"Dealer",""&$S$18&"","Model",""&$S58&""),0) -> 0 | AM58: =AK58+AL58 -> 0 | AN58: =IFERROR(GETPIVOTDATA("Row Labels",#REF!,"Dealer",""&$S$18&"","Model",""&$S58&""),0) -> 0 | AO58: =IFERROR(GETPIVOTDATA("RS Afi",#REF!,"Dealer",""&$S$18&"","Model",""&$S58&""),0) -> 0 | AP58: =IFERROR(GETPIVOTDATA("qty",#REF!,"Model",""&$S58&"","Dealer",""&$S$18&""),0) -> 0 | AQ58: =IFERROR(GETPIVOTDATA("volume_rs",#REF!,"Model",""&$S58&"","Dealer",""&$S$18&""),0) -> 0 | AR58: =AP58-AQ58 -> 0 | AS58: =IFERROR(GETPIVOTDATA("Area AGM",'Pvt OS'!#REF!,"Dealer",""&$S$18&"","Model",""&$S58&""),0) -> 0 | AT58: =AR58-AS58 -> 0
P59: GR YARIS | Q59: =IFERROR(R59/AI59,0) -> 0 | R59: =IFERROR(GETPIVOTDATA("RS Target",#REF!,"Dealer",""&$S$18&"","Model",""&$P59&""),0) -> 0 | S59: GR YARIS | T59: =SUM(Y59:AB59,AO59) -> 0 | U59: =IFERROR(GETPIVOTDATA("Area AGM",'Pvt OS'!#REF!,"Dealer",""&$S$18&"","Model",""&$S59&""),0) -> 0 | V59: =W59-X59 -> 0 | W59: =IFERROR(GETPIVOTDATA("Area AGM",'Pvt OS'!#REF!,"Dealer",""&$S$18&"","Model",""&$S59&""),0)+IFERROR(GETPIVOTDATA("Area AGM",'Pvt OS'!$A$8,"Dealer",""&$S$18&"","Model",""&$S59&""),0) -> 0 | X59: =SUM(Y59:AB59) -> 0 | Y59: =IFERROR(GETPIVOTDATA("Area AGM",'Pvt OS'!$U$8,"Dealer",""&$S$18&"","Model",""&$S59&""),0) -> 0 | Z59: =IFERROR(GETPIVOTDATA("Area AGM",'Pvt OS'!$M$8,"Dealer",""&$S$18&"","Model",""&$S59&""),0) -> 0 | AA59: =IFERROR(GETPIVOTDATA("Area AGM",'Pvt OS'!#REF!,"Dealer",""&$S$18&"","Model",""&$S59&""),0) -> 0 | AB59: =IFERROR(GETPIVOTDATA("Area AGM",'Pvt OS'!$AO$8,"Dealer",""&$S$18&"","Model",""&$S59&""),0) -> 0 | AC59: =IFERROR(GETPIVOTDATA("Stock",#REF!,"Dealer",""&$S$18&"","Model",""&$S59&""),0) -> 0 | AD59: =IFERROR(GETPIVOTDATA("MDP",#REF!,"Dealer",""&$S$18&"","Model",""&$S59&""),0) -> 0 | AE59: =IFERROR(GETPIVOTDATA("RRN",#REF!,"Model2",""&$S59&"","Dealer",""&$S$18&""),0) -> 0 | AF59: =IFERROR(GETPIVOTDATA("CO",#REF!,"Dealer Name",""&$S$18&"","Model",""&$S59&""),0) -> 0 | AG59: =IFERROR(GETPIVOTDATA("Sum of Distplan Final",#REF!,"Dealer",""&$S$18&"","Model",""&$S59&""),0) -> 0 | AH59: =IFERROR(GETPIVOTDATA("RRN",#REF!,"Model",""&$S59&"","Dealer",""&$S$18&""),0) -> 0 | AI59: =AC59+AD59+AF59+AG59-AH59 -> 0 | AJ59: =IFERROR(GETPIVOTDATA("volume_rs",#REF!,"Model",""&$S59&"","Dealer",""&$S$18&""),0) -> 0 | AK59: =AI59-AJ59-X59+AN59 -> 0 | AL59: =IFERROR(GETPIVOTDATA("Area AGM",'Pvt OS'!#REF!,"Dealer",""&$S$18&"","Model",""&$S59&""),0) -> 0 | AM59: =AK59+AL59 -> 0 | AN59: =IFERROR(GETPIVOTDATA("Row Labels",#REF!,"Dealer",""&$S$18&"","Model",""&$S59&""),0) -> 0 | AO59: =IFERROR(GETPIVOTDATA("RS Afi",#REF!,"Dealer",""&$S$18&"","Model",""&$S59&""),0) -> 0 | AP59: =IFERROR(GETPIVOTDATA("qty",#REF!,"Model",""&$S59&"","Dealer",""&$S$18&""),0) -> 0 | AQ59: =IFERROR(GETPIVOTDATA("volume_rs",#REF!,"Model",""&$S59&"","Dealer",""&$S$18&""),0) -> 0 | AR59: =AP59-AQ59 -> 0 | AS59: =IFERROR(GETPIVOTDATA("Area AGM",'Pvt OS'!#REF!,"Dealer",""&$S$18&"","Model",""&$S59&""),0) -> 0 | AT59: =AR59-AS59 -> 0
P60: CROWN | Q60: =IFERROR(R60/AI60,0) -> 0 | R60: =IFERROR(GETPIVOTDATA("RS Target",#REF!,"Dealer",""&$S$18&"","Model",""&$P60&""),0) -> 0 | S60: CROWN | T60: =SUM(Y60:AB60,AO60) -> 0 | U60: =IFERROR(GETPIVOTDATA("Area AGM",'Pvt OS'!#REF!,"Dealer",""&$S$18&"","Model",""&$S60&""),0) -> 0 | V60: =W60-X60 -> 0 | W60: =IFERROR(GETPIVOTDATA("Area AGM",'Pvt OS'!#REF!,"Dealer",""&$S$18&"","Model",""&$S60&""),0)+IFERROR(GETPIVOTDATA("Area AGM",'Pvt OS'!$A$8,"Dealer",""&$S$18&"","Model",""&$S60&""),0) -> 0 | X60: =SUM(Y60:AB60) -> 0 | Y60: =IFERROR(GETPIVOTDATA("Area AGM",'Pvt OS'!$U$8,"Dealer",""&$S$18&"","Model",""&$S60&""),0) -> 0 | Z60: =IFERROR(GETPIVOTDATA("Area AGM",'Pvt OS'!$M$8,"Dealer",""&$S$18&"","Model",""&$S60&""),0) -> 0 | AA60: =IFERROR(GETPIVOTDATA("Area AGM",'Pvt OS'!#REF!,"Dealer",""&$S$18&"","Model",""&$S60&""),0) -> 0 | AB60: =IFERROR(GETPIVOTDATA("Area AGM",'Pvt OS'!$AO$8,"Dealer",""&$S$18&"","Model",""&$S60&""),0) -> 0 | AC60: =IFERROR(GETPIVOTDATA("Stock",#REF!,"Dealer",""&$S$18&"","Model",""&$S60&""),0) -> 0 | AD60: =IFERROR(GETPIVOTDATA("MDP",#REF!,"Dealer",""&$S$18&"","Model",""&$S60&""),0) -> 0 | AE60: =IFERROR(GETPIVOTDATA("RRN",#REF!,"Model2",""&$S60&"","Dealer",""&$S$18&""),0) -> 0 | AF60: =IFERROR(GETPIVOTDATA("CO",#REF!,"Dealer Name",""&$S$18&"","Model",""&$S60&""),0) -> 0 | AG60: =IFERROR(GETPIVOTDATA("Sum of Distplan Final",#REF!,"Dealer",""&$S$18&"","Model",""&$S60&""),0) -> 0 | AH60: =IFERROR(GETPIVOTDATA("RRN",#REF!,"Model",""&$S60&"","Dealer",""&$S$18&""),0) -> 0 | AI60: =AC60+AD60+AF60+AG60-AH60 -> 0 | AJ60: =IFERROR(GETPIVOTDATA("volume_rs",#REF!,"Model",""&$S60&"","Dealer",""&$S$18&""),0) -> 0 | AK60: =AI60-AJ60-X60+AN60 -> 0 | AL60: =IFERROR(GETPIVOTDATA("Area AGM",'Pvt OS'!#REF!,"Dealer",""&$S$18&"","Model",""&$S60&""),0) -> 0 | AM60: =AK60+AL60 -> 0 | AN60: =IFERROR(GETPIVOTDATA("Row Labels",#REF!,"Dealer",""&$S$18&"","Model",""&$S60&""),0) -> 0 | AO60: =IFERROR(GETPIVOTDATA("RS Afi",#REF!,"Dealer",""&$S$18&"","Model",""&$S60&""),0) -> 0 | AP60: =IFERROR(GETPIVOTDATA("qty",#REF!,"Model",""&$S60&"","Dealer",""&$S$18&""),0) -> 0 | AQ60: =IFERROR(GETPIVOTDATA("volume_rs",#REF!,"Model",""&$S60&"","Dealer",""&$S$18&""),0) -> 0 | AR60: =AP60-AQ60 -> 0 | AS60: =IFERROR(GETPIVOTDATA("Area AGM",'Pvt OS'!#REF!,"Dealer",""&$S$18&"","Model",""&$S60&""),0) -> 0 | AT60: =AR60-AS60 -> 0
P61: ETIOS | Q61: =IFERROR(R61/AI61,0) -> 0 | R61: =IFERROR(GETPIVOTDATA("RS Target",#REF!,"Dealer",""&$S$18&"","Model",""&$P61&""),0) -> 0 | S61: ETIOS | T61: =SUM(Y61:AB61,AO61) -> 0 | U61: =IFERROR(GETPIVOTDATA("Area AGM",'Pvt OS'!#REF!,"Dealer",""&$S$18&"","Model",""&$S61&""),0) -> 0 | V61: =W61-X61 -> 0 | W61: =IFERROR(GETPIVOTDATA("Area AGM",'Pvt OS'!#REF!,"Dealer",""&$S$18&"","Model",""&$S61&""),0)+IFERROR(GETPIVOTDATA("Area AGM",'Pvt OS'!$A$8,"Dealer",""&$S$18&"","Model",""&$S61&""),0) -> 0 | X61: =SUM(Y61:AB61) -> 0 | Y61: =IFERROR(GETPIVOTDATA("Area AGM",'Pvt OS'!$U$8,"Dealer",""&$S$18&"","Model",""&$S61&""),0) -> 0 | Z61: =IFERROR(GETPIVOTDATA("Area AGM",'Pvt OS'!$M$8,"Dealer",""&$S$18&"","Model",""&$S61&""),0) -> 0 | AA61: =IFERROR(GETPIVOTDATA("Area AGM",'Pvt OS'!#REF!,"Dealer",""&$S$18&"","Model",""&$S61&""),0) -> 0 | AB61: =IFERROR(GETPIVOTDATA("Area AGM",'Pvt OS'!$AO$8,"Dealer",""&$S$18&"","Model",""&$S61&""),0) -> 0 | AC61: =IFERROR(GETPIVOTDATA("Stock",#REF!,"Dealer",""&$S$18&"","Model",""&$S61&""),0) -> 0 | AD61: =IFERROR(GETPIVOTDATA("MDP",#REF!,"Dealer",""&$S$18&"","Model",""&$S61&""),0) -> 0 | AE61: =IFERROR(GETPIVOTDATA("RRN",#REF!,"Model2",""&$S61&"","Dealer",""&$S$18&""),0) -> 0 | AF61: =IFERROR(GETPIVOTDATA("CO",#REF!,"Dealer Name",""&$S$18&"","Model",""&$S61&""),0) -> 0 | AG61: =IFERROR(GETPIVOTDATA("Sum of Distplan Final",#REF!,"Dealer",""&$S$18&"","Model",""&$S61&""),0) -> 0 | AH61: =IFERROR(GETPIVOTDATA("RRN",#REF!,"Model",""&$S61&"","Dealer",""&$S$18&""),0) -> 0 | AI61: =AC61+AD61+AF61+AG61-AH61 -> 0 | AJ61: =IFERROR(GETPIVOTDATA("volume_rs",#REF!,"Model",""&$S61&"","Dealer",""&$S$18&""),0) -> 0 | AK61: =AI61-AJ61-X61+AN61 -> 0 | AL61: =IFERROR(GETPIVOTDATA("Area AGM",'Pvt OS'!#REF!,"Dealer",""&$S$18&"","Model",""&$S61&""),0) -> 0 | AM61: =AK61+AL61 -> 0 | AN61: =IFERROR(GETPIVOTDATA("Row Labels",#REF!,"Dealer",""&$S$18&"","Model",""&$S61&""),0) -> 0 | AO61: =IFERROR(GETPIVOTDATA("RS Afi",#REF!,"Dealer",""&$S$18&"","Model",""&$S61&""),0) -> 0 | AP61: =IFERROR(GETPIVOTDATA("qty",#REF!,"Model",""&$S61&"","Dealer",""&$S$18&""),0) -> 0 | AQ61: =IFERROR(GETPIVOTDATA("volume_rs",#REF!,"Model",""&$S61&"","Dealer",""&$S$18&""),0) -> 0 | AR61: =AP61-AQ61 -> 0 | AS61: =IFERROR(GETPIVOTDATA("Area AGM",'Pvt OS'!#REF!,"Dealer",""&$S$18&"","Model",""&$S61&""),0) -> 0 | AT61: =AR61-AS61 -> 0
P62: FT-86 | Q62: =IFERROR(R62/AI62,0) -> 0 | R62: =IFERROR(GETPIVOTDATA("RS Target",#REF!,"Dealer",""&$S$18&"","Model",""&$P62&""),0) -> 0 | S62: FT-86 | T62: =SUM(Y62:AB62,AO62) -> 0 | U62: =IFERROR(GETPIVOTDATA("Area AGM",'Pvt OS'!#REF!,"Dealer",""&$S$18&"","Model",""&$S62&""),0) -> 0 | V62: =W62-X62 -> 0 | W62: =IFERROR(GETPIVOTDATA("Area AGM",'Pvt OS'!#REF!,"Dealer",""&$S$18&"","Model",""&$S62&""),0)+IFERROR(GETPIVOTDATA("Area AGM",'Pvt OS'!$A$8,"Dealer",""&$S$18&"","Model",""&$S62&""),0) -> 0 | X62: =SUM(Y62:AB62) -> 0 | Y62: =IFERROR(GETPIVOTDATA("Area AGM",'Pvt OS'!$U$8,"Dealer",""&$S$18&"","Model",""&$S62&""),0) -> 0 | Z62: =IFERROR(GETPIVOTDATA("Area AGM",'Pvt OS'!$M$8,"Dealer",""&$S$18&"","Model",""&$S62&""),0) -> 0 | AA62: =IFERROR(GETPIVOTDATA("Area AGM",'Pvt OS'!#REF!,"Dealer",""&$S$18&"","Model",""&$S62&""),0) -> 0 | AB62: =IFERROR(GETPIVOTDATA("Area AGM",'Pvt OS'!$AO$8,"Dealer",""&$S$18&"","Model",""&$S62&""),0) -> 0 | AC62: =IFERROR(GETPIVOTDATA("Stock",#REF!,"Dealer",""&$S$18&"","Model",""&$S62&""),0) -> 0 | AD62: =IFERROR(GETPIVOTDATA("MDP",#REF!,"Dealer",""&$S$18&"","Model",""&$S62&""),0) -> 0 | AE62: =IFERROR(GETPIVOTDATA("RRN",#REF!,"Model2",""&$S62&"","Dealer",""&$S$18&""),0) -> 0 | AF62: =IFERROR(GETPIVOTDATA("CO",#REF!,"Dealer Name",""&$S$18&"","Model",""&$S62&""),0) -> 0 | AG62: =IFERROR(GETPIVOTDATA("Sum of Distplan Final",#REF!,"Dealer",""&$S$18&"","Model",""&$S62&""),0) -> 0 | AH62: =IFERROR(GETPIVOTDATA("RRN",#REF!,"Model",""&$S62&"","Dealer",""&$S$18&""),0) -> 0 | AI62: =AC62+AD62+AF62+AG62-AH62 -> 0 | AJ62: =IFERROR(GETPIVOTDATA("volume_rs",#REF!,"Model",""&$S62&"","Dealer",""&$S$18&""),0) -> 0 | AK62: =AI62-AJ62-X62+AN62 -> 0 | AL62: =IFERROR(GETPIVOTDATA("Area AGM",'Pvt OS'!#REF!,"Dealer",""&$S$18&"","Model",""&$S62&""),0) -> 0 | AM62: =AK62+AL62 -> 0 | AN62: =IFERROR(GETPIVOTDATA("Row Labels",#REF!,"Dealer",""&$S$18&"","Model",""&$S62&""),0) -> 0 | AO62: =IFERROR(GETPIVOTDATA("RS Afi",#REF!,"Dealer",""&$S$18&"","Model",""&$S62&""),0) -> 0 | AP62: =IFERROR(GETPIVOTDATA("qty",#REF!,"Model",""&$S62&"","Dealer",""&$S$18&""),0) -> 0 | AQ62: =IFERROR(GETPIVOTDATA("volume_rs",#REF!,"Model",""&$S62&"","Dealer",""&$S$18&""),0) -> 0 | AR62: =AP62-AQ62 -> 0 | AS62: =IFERROR(GETPIVOTDATA("Area AGM",'Pvt OS'!#REF!,"Dealer",""&$S$18&"","Model",""&$S62&""),0) -> 0 | AT62: =AR62-AS62 -> 0
P63: HILUX C-CAB | Q63: =IFERROR(R63/AI63,0) -> 0 | R63: =IFERROR(GETPIVOTDATA("RS Target",#REF!,"Dealer",""&$S$18&"","Model",""&$P63&""),0) -> 0 | S63: HILUX C-CAB | T63: =SUM(Y63:AB63,AO63) -> 0 | U63: =IFERROR(GETPIVOTDATA("Area AGM",'Pvt OS'!#REF!,"Dealer",""&$S$18&"","Model",""&$S63&""),0) -> 0 | V63: =W63-X63 -> 0 | W63: =IFERROR(GETPIVOTDATA("Area AGM",'Pvt OS'!#REF!,"Dealer",""&$S$18&"","Model",""&$S63&""),0)+IFERROR(GETPIVOTDATA("Area AGM",'Pvt OS'!$A$8,"Dealer",""&$S$18&"","Model",""&$S63&""),0) -> 0 | X63: =SUM(Y63:AB63) -> 0 | Y63: =IFERROR(GETPIVOTDATA("Area AGM",'Pvt OS'!$U$8,"Dealer",""&$S$18&"","Model",""&$S63&""),0) -> 0 | Z63: =IFERROR(GETPIVOTDATA("Area AGM",'Pvt OS'!$M$8,"Dealer",""&$S$18&"","Model",""&$S63&""),0) -> 0 | AA63: =IFERROR(GETPIVOTDATA("Area AGM",'Pvt OS'!#REF!,"Dealer",""&$S$18&"","Model",""&$S63&""),0) -> 0 | AB63: =IFERROR(GETPIVOTDATA("Area AGM",'Pvt OS'!$AO$8,"Dealer",""&$S$18&"","Model",""&$S63&""),0) -> 0 | AC63: =IFERROR(GETPIVOTDATA("Stock",#REF!,"Dealer",""&$S$18&"","Model",""&$S63&""),0) -> 0 | AD63: =IFERROR(GETPIVOTDATA("MDP",#REF!,"Dealer",""&$S$18&"","Model",""&$S63&""),0) -> 0 | AE63: =IFERROR(GETPIVOTDATA("RRN",#REF!,"Model2",""&$S63&"","Dealer",""&$S$18&""),0) -> 0 | AF63: =IFERROR(GETPIVOTDATA("CO",#REF!,"Dealer Name",""&$S$18&"","Model",""&$S63&""),0) -> 0 | AG63: =IFERROR(GETPIVOTDATA("Sum of Distplan Final",#REF!,"Dealer",""&$S$18&"","Model",""&$S63&""),0) -> 0 | AH63: =IFERROR(GETPIVOTDATA("RRN",#REF!,"Model",""&$S63&"","Dealer",""&$S$18&""),0) -> 0 | AI63: =AC63+AD63+AF63+AG63-AH63 -> 0 | AJ63: =IFERROR(GETPIVOTDATA("volume_rs",#REF!,"Model",""&$S63&"","Dealer",""&$S$18&""),0) -> 0 | AK63: =AI63-AJ63-X63+AN63 -> 0 | AL63: =IFERROR(GETPIVOTDATA("Area AGM",'Pvt OS'!#REF!,"Dealer",""&$S$18&"","Model",""&$S63&""),0) -> 0 | AM63: =AK63+AL63 -> 0 | AN63: =IFERROR(GETPIVOTDATA("Row Labels",#REF!,"Dealer",""&$S$18&"","Model",""&$S63&""),0) -> 0 | AO63: =IFERROR(GETPIVOTDATA("RS Afi",#REF!,"Dealer",""&$S$18&"","Model",""&$S63&""),0) -> 0 | AP63: =IFERROR(GETPIVOTDATA("qty",#REF!,"Model",""&$S63&"","Dealer",""&$S$18&""),0) -> 0 | AQ63: =IFERROR(GETPIVOTDATA("volume_rs",#REF!,"Model",""&$S63&"","Dealer",""&$S$18&""),0) -> 0 | AR63: =AP63-AQ63 -> 0 | AS63: =IFERROR(GETPIVOTDATA("Area AGM",'Pvt OS'!#REF!,"Dealer",""&$S$18&"","Model",""&$S63&""),0) -> 0 | AT63: =AR63-AS63 -> 0
P64: LANDCRUISER 70 | Q64: =IFERROR(R64/AI64,0) -> 0 | R64: =IFERROR(GETPIVOTDATA("RS Target",#REF!,"Dealer",""&$S$18&"","Model",""&$P64&""),0) -> 0 | S64: LANDCRUISER 70 | T64: =SUM(Y64:AB64,AO64) -> 0 | U64: =IFERROR(GETPIVOTDATA("Area AGM",'Pvt OS'!#REF!,"Dealer",""&$S$18&"","Model",""&$S64&""),0) -> 0 | V64: =W64-X64 -> 0 | W64: =IFERROR(GETPIVOTDATA("Area AGM",'Pvt OS'!#REF!,"Dealer",""&$S$18&"","Model",""&$S64&""),0)+IFERROR(GETPIVOTDATA("Area AGM",'Pvt OS'!$A$8,"Dealer",""&$S$18&"","Model",""&$S64&""),0) -> 0 | X64: =SUM(Y64:AB64) -> 0 | Y64: =IFERROR(GETPIVOTDATA("Area AGM",'Pvt OS'!$U$8,"Dealer",""&$S$18&"","Model",""&$S64&""),0) -> 0 | Z64: =IFERROR(GETPIVOTDATA("Area AGM",'Pvt OS'!$M$8,"Dealer",""&$S$18&"","Model",""&$S64&""),0) -> 0 | AA64: =IFERROR(GETPIVOTDATA("Area AGM",'Pvt OS'!#REF!,"Dealer",""&$S$18&"","Model",""&$S64&""),0) -> 0 | AB64: =IFERROR(GETPIVOTDATA("Area AGM",'Pvt OS'!$AO$8,"Dealer",""&$S$18&"","Model",""&$S64&""),0) -> 0 | AC64: =IFERROR(GETPIVOTDATA("Stock",#REF!,"Dealer",""&$S$18&"","Model",""&$S64&""),0) -> 0 | AD64: =IFERROR(GETPIVOTDATA("MDP",#REF!,"Dealer",""&$S$18&"","Model",""&$S64&""),0) -> 0 | AE64: =IFERROR(GETPIVOTDATA("RRN",#REF!,"Model2",""&$S64&"","Dealer",""&$S$18&""),0) -> 0 | AF64: =IFERROR(GETPIVOTDATA("CO",#REF!,"Dealer Name",""&$S$18&"","Model",""&$S64&""),0) -> 0 | AG64: =IFERROR(GETPIVOTDATA("Sum of Distplan Final",#REF!,"Dealer",""&$S$18&"","Model",""&$S64&""),0) -> 0 | AH64: =IFERROR(GETPIVOTDATA("RRN",#REF!,"Model",""&$S64&"","Dealer",""&$S$18&""),0) -> 0 | AI64: =AC64+AD64+AF64+AG64-AH64 -> 0 | AJ64: =IFERROR(GETPIVOTDATA("volume_rs",#REF!,"Model",""&$S64&"","Dealer",""&$S$18&""),0) -> 0 | AK64: =AI64-AJ64-X64+AN64 -> 0 | AL64: =IFERROR(GETPIVOTDATA("Area AGM",'Pvt OS'!#REF!,"Dealer",""&$S$18&"","Model",""&$S64&""),0) -> 0 | AM64: =AK64+AL64 -> 0 | AN64: =IFERROR(GETPIVOTDATA("Row Labels",#REF!,"Dealer",""&$S$18&"","Model",""&$S64&""),0) -> 0 | AO64: =IFERROR(GETPIVOTDATA("RS Afi",#REF!,"Dealer",""&$S$18&"","Model",""&$S64&""),0) -> 0 | AP64: =IFERROR(GETPIVOTDATA("qty",#REF!,"Model",""&$S64&"","Dealer",""&$S$18&""),0) -> 0 | AQ64: =IFERROR(GETPIVOTDATA("volume_rs",#REF!,"Model",""&$S64&"","Dealer",""&$S$18&""),0) -> 0 | AR64: =AP64-AQ64 -> 0 | AS64: =IFERROR(GETPIVOTDATA("Area AGM",'Pvt OS'!#REF!,"Dealer",""&$S$18&"","Model",""&$S64&""),0) -> 0 | AT64: =AR64-AS64 -> 0
P65: NAV1 | Q65: =IFERROR(R65/AI65,0) -> 0 | R65: =IFERROR(GETPIVOTDATA("RS Target",#REF!,"Dealer",""&$S$18&"","Model",""&$P65&""),0) -> 0 | S65: NAV1 | T65: =SUM(Y65:AB65,AO65) -> 0 | U65: =IFERROR(GETPIVOTDATA("Area AGM",'Pvt OS'!#REF!,"Dealer",""&$S$18&"","Model",""&$S65&""),0) -> 0 | V65: =W65-X65 -> 0 | W65: =IFERROR(GETPIVOTDATA("Area AGM",'Pvt OS'!#REF!,"Dealer",""&$S$18&"","Model",""&$S65&""),0)+IFERROR(GETPIVOTDATA("Area AGM",'Pvt OS'!$A$8,"Dealer",""&$S$18&"","Model",""&$S65&""),0) -> 0 | X65: =SUM(Y65:AB65) -> 0 | Y65: =IFERROR(GETPIVOTDATA("Area AGM",'Pvt OS'!$U$8,"Dealer",""&$S$18&"","Model",""&$S65&""),0) -> 0 | Z65: =IFERROR(GETPIVOTDATA("Area AGM",'Pvt OS'!$M$8,"Dealer",""&$S$18&"","Model",""&$S65&""),0) -> 0 | AA65: =IFERROR(GETPIVOTDATA("Area AGM",'Pvt OS'!#REF!,"Dealer",""&$S$18&"","Model",""&$S65&""),0) -> 0 | AB65: =IFERROR(GETPIVOTDATA("Area AGM",'Pvt OS'!$AO$8,"Dealer",""&$S$18&"","Model",""&$S65&""),0) -> 0 | AC65: =IFERROR(GETPIVOTDATA("Stock",#REF!,"Dealer",""&$S$18&"","Model",""&$S65&""),0) -> 0 | AD65: =IFERROR(GETPIVOTDATA("MDP",#REF!,"Dealer",""&$S$18&"","Model",""&$S65&""),0) -> 0 | AE65: =IFERROR(GETPIVOTDATA("RRN",#REF!,"Model2",""&$S65&"","Dealer",""&$S$18&""),0) -> 0 | AF65: =IFERROR(GETPIVOTDATA("CO",#REF!,"Dealer Name",""&$S$18&"","Model",""&$S65&""),0) -> 0 | AG65: =IFERROR(GETPIVOTDATA("Sum of Distplan Final",#REF!,"Dealer",""&$S$18&"","Model",""&$S65&""),0) -> 0 | AH65: =IFERROR(GETPIVOTDATA("RRN",#REF!,"Model",""&$S65&"","Dealer",""&$S$18&""),0) -> 0 | AI65: =AC65+AD65+AF65+AG65-AH65 -> 0 | AJ65: =IFERROR(GETPIVOTDATA("volume_rs",#REF!,"Model",""&$S65&"","Dealer",""&$S$18&""),0) -> 0 | AK65: =AI65-AJ65-X65+AN65 -> 0 | AL65: =IFERROR(GETPIVOTDATA("Area AGM",'Pvt OS'!#REF!,"Dealer",""&$S$18&"","Model",""&$S65&""),0) -> 0 | AM65: =AK65+AL65 -> 0 | AN65: =IFERROR(GETPIVOTDATA("Row Labels",#REF!,"Dealer",""&$S$18&"","Model",""&$S65&""),0) -> 0 | AO65: =IFERROR(GETPIVOTDATA("RS Afi",#REF!,"Dealer",""&$S$18&"","Model",""&$S65&""),0) -> 0 | AP65: =IFERROR(GETPIVOTDATA("qty",#REF!,"Model",""&$S65&"","Dealer",""&$S$18&""),0) -> 0 | AQ65: =IFERROR(GETPIVOTDATA("volume_rs",#REF!,"Model",""&$S65&"","Dealer",""&$S$18&""),0) -> 0 | AR65: =AP65-AQ65 -> 0 | AS65: =IFERROR(GETPIVOTDATA("Area AGM",'Pvt OS'!#REF!,"Dealer",""&$S$18&"","Model",""&$S65&""),0) -> 0 | AT65: =AR65-AS65 -> 0
... P67: LANDCRUISER 300 | Q67: =IFERROR(R67/AI67,0) -> 0 | R67: =IFERROR(GETPIVOTDATA("RS Target",#REF!,"Dealer",""&$S$18&"","Model",""&$P67&""),0) -> 0 | S67: LANDCRUISER 300 | T67: =SUM(Y67:AB67,AO67) -> 0 | U67: =IFERROR(GETPIVOTDATA("Area AGM",'Pvt OS'!#REF!,"Dealer",""&$S$18&"","Model",""&$S67&""),0) -> 0 | V67: =W67-X67 -> 0 | W67: =IFERROR(GETPIVOTDATA("Area AGM",'Pvt OS'!#REF!,"Dealer",""&$S$18&"","Model",""&$S67&""),0)+IFERROR(GETPIVOTDATA("Area AGM",'Pvt OS'!$A$8,"Dealer",""&$S$18&"","Model",""&$S67&""),0) -> 0 | X67: =SUM(Y67:AB67) -> 0 | Y67: =IFERROR(GETPIVOTDATA("Area AGM",'Pvt OS'!$U$8,"Dealer",""&$S$18&"","Model",""&$S67&""),0) -> 0 | Z67: =IFERROR(GETPIVOTDATA("Area AGM",'Pvt OS'!$M$8,"Dealer",""&$S$18&"","Model",""&$S67&""),0) -> 0 | AA67: =IFERROR(GETPIVOTDATA("Area AGM",'Pvt OS'!#REF!,"Dealer",""&$S$18&"","Model",""&$S67&""),0) -> 0 | AB67: =IFERROR(GETPIVOTDATA("Area AGM",'Pvt OS'!$AO$8,"Dealer",""&$S$18&"","Model",""&$S67&""),0) -> 0 | AC67: =IFERROR(GETPIVOTDATA("Stock",#REF!,"Dealer",""&$S$18&"","Model",""&$S67&""),0) -> 0 | AD67: =IFERROR(GETPIVOTDATA("MDP",#REF!,"Dealer",""&$S$18&"","Model",""&$S67&""),0) -> 0 | AE67: =IFERROR(GETPIVOTDATA("RRN",#REF!,"Model2",""&$S67&"","Dealer",""&$S$18&""),0) -> 0 | AF67: =IFERROR(GETPIVOTDATA("CO",#REF!,"Dealer Name",""&$S$18&"","Model",""&$S67&""),0) -> 0 | AG67: =IFERROR(GETPIVOTDATA("Sum of Distplan Final",#REF!,"Dealer",""&$S$18&"","Model",""&$S67&""),0) -> 0 | AH67: =IFERROR(GETPIVOTDATA("RRN",#REF!,"Model",""&$S67&"","Dealer",""&$S$18&""),0) -> 0 | AI67: =AC67+AD67+AF67+AG67-AH67 -> 0 | AJ67: =IFERROR(GETPIVOTDATA("volume_rs",#REF!,"Model",""&$S67&"","Dealer",""&$S$18&""),0) -> 0 | AK67: =AI67-AJ67-X67+AN67 -> 0 | AL67: =IFERROR(GETPIVOTDATA("Area AGM",'Pvt OS'!#REF!,"Dealer",""&$S$18&"","Model",""&$S67&""),0) -> 0 | AM67: =AK67+AL67 -> 0 | AN67: =IFERROR(GETPIVOTDATA("Row Labels",#REF!,"Dealer",""&$S$18&"","Model",""&$S67&""),0) -> 0 | AO67: =IFERROR(GETPIVOTDATA("RS Afi",#REF!,"Dealer",""&$S$18&"","Model",""&$S67&""),0) -> 0 | AP67: =IFERROR(GETPIVOTDATA("qty",#REF!,"Model",""&$S67&"","Dealer",""&$S$18&""),0) -> 0 | AQ67: =IFERROR(GETPIVOTDATA("volume_rs",#REF!,"Model",""&$S67&"","Dealer",""&$S$18&""),0) -> 0 | AR67: =AP67-AQ67 -> 0 | AS67: =IFERROR(GETPIVOTDATA("Area AGM",'Pvt OS'!#REF!,"Dealer",""&$S$18&"","Model",""&$S67&""),0) -> 0 | AT67: =AR67-AS67 -> 0

Sheet OS
A1: Pilih Nama Dealer | D1: Tunas Toyota | F1: Isi Terlebih Dahulu, Pilih Dealer & Outlet Disini
A2: Pilih Nama Outlet
R3: PILIH LIST YANG DISEDIAKAN SESUAI STATUS SPK | S3: Pilih Status Supply
A4: JANGAN LUPA UPDATE TANGGAL CUT OFF INI | D4: TIDAK PERLU DIISI, ISI PILIHAN DIATAS, KOLOM INI AKAN OTOMATIS TERISI | G4: TIDAK PERLU DIISI | I4: Follow 'Katashiki Suffix' pada sheet 'List Model' | J4: TIDAK PERLU DIISI OLEH DEALER [AUTOMATIC RUMUS JIKA MENGISI KATASHIKI SUFFIX] | N4: TIDAk PERLU DIISI. OTOMATIS TERISI SAAT ISI TANGGAL SPK | Q4: ISI TANGGAL SPK DISINI | R4: - Firmed Ketentuan Firmed : a. Leasing telah disetujui b. Pembayaran Cash c. Fleet / GSO sudah ada PO dan TOP yang telah disepakati - Pending Loan (Ketentuan : jika leasing masih diproses) - Already DO - Cancel - Customer Payment Issue (Ketentuan : jika customer tidak bisa bayar/menunggu diskon) | S4: - Match MDP - Match Supply Stock On Hand - UNMATCH | U4: WAJIB DIISI | V4: WAJIB DIISI | W4: WAJIB DIISI | X4: WAJIB DIISI | Y4: WAJIB DIISI | Z4: WAJIB DIISI | AA4: WAJIB DIISI | AB4: WAJIB DIISI [NEW] | AC4: WAJIB DIISI | AD4: WAJIB DIISI | AE4: ISI NAMA CUSTOMER DISINI
A5: Tanggal Cut Off | C5: No | D5: Dealer | E5: Outlet Code (Sales Code) | F5: Outlet Name | G5: Area AGM | H5: Area Region | I5: Katashiki Suffix | J5: Katashiki | K5: Suffix | L5: Model | M5: Type Model | N5: Outstanding Days | O5: Umur Outstansing | P5: OS Category | Q5: Tanggal SPK | R5: Status SPK | S5: Status Supply | T5: Month | U5: No RRN | V5: Estimasi tanggal DO/AFI [Untuk OS Firmed & Match] | W5: Pekerjaan customer | X5: Demand Structure | Y5: Proses Trade In (WAJIB DIISI JIKA REPLACEMENT) | Z5: Financial Type | AA5: Jenis Leasing | AB5: Tanggal approval by Leasing | AC5: Paket Leasing TVC yang digunakan | AD5: DP Rate | AE5: Customer Name | AF5: Salesname | AG5: NO SO | AH5: Color | AI5: Color Code | AJ5: Leasing | AK5: C/C | AL5: Leasing
A6: 46244 | C6: 1 | D6: Tunas Toyota | F6: Tunas Toyota Kiara Condong | G6: =VLOOKUP($F6,List!$D$5:$G$35,3,0) -> Area 1 | H6: =VLOOKUP($F6,List!$D$5:$G$35,4,0) -> Area 1 - West Java | I6: =J6&K6 -> NGC200R-DHXHKD00 | J6: NGC200R-DHXHKD | K6: 00 | L6: =VLOOKUP(I6,'List Model'!A:E,4,0) -> YARIS CROSS GASOLINE | M6: =VLOOKUP(I6,'List Model'!A:E,5,0) -> YARIS CROSS GASOLINE 1.5S CVT TSS | N6: =IF($Q6="",0,_xlfn.DAYS($A$6,$Q6)+1) -> 90 | O6: =IF($N6=0,"0",IF(AND($N6>=1,$N6<=7),"1 Minggu",IF(AND($N6>=8,$N6<=14),"2 Minggu",IF(AND($N6>=15,$N6<=21),"3 Minggu",IF(AND($N6>=22,$N6<=28),"4 Minggu",IF($N6>=29,"> 4 Minggu",0)))))) -> > 4 Minggu | P6: =IF($N6=0,"0",IF(AND($N6>=0,$N6<30),"<30D",IF(AND($N6>=30,$N6<=60),"30D-60D",IF($N6>60,">60D",0)))) -> >60D | Q6: 46155 | R6: PENDING LOAN | S6: UNMATCH | AE6: DENDI HOLIUS | AF6: TOPIK HIDAYAT | AH6: ATTITUDE BLACK MICA | AJ6: MTF | AK6: 2026 | AM6: 0.2
C7: 2 | D7: Tunas Toyota | F7: Tunas Toyota Kiara Condong | G7: =VLOOKUP($F7,List!$D$5:$G$35,3,0) -> Area 1 | H7: =VLOOKUP($F7,List!$D$5:$G$35,4,0) -> Area 1 - West Java | I7: =J7&K7 -> KDH223R-LEMDY00 | J7: KDH223R-LEMDY | K7: 00 | L7: =VLOOKUP(I7,'List Model'!A:E,4,0) -> HIACE | M7: =VLOOKUP(I7,'List Model'!A:E,5,0) -> HI ACE COMMUTER M/T | N7: =IF($Q7="",0,_xlfn.DAYS($A$6,$Q7)+1) -> 33 | O7: =IF($N7=0,"0",IF(AND($N7>=1,$N7<=7),"1 Minggu",IF(AND($N7>=8,$N7<=14),"2 Minggu",IF(AND($N7>=15,$N7<=21),"3 Minggu",IF(AND($N7>=22,$N7<=28),"4 Minggu",IF($N7>=29,"> 4 Minggu",0)))))) -> > 4 Minggu | P7: =IF($N7=0,"0",IF(AND($N7>=0,$N7<30),"<30D",IF(AND($N7>=30,$N7<=60),"30D-60D",IF($N7>60,">60D",0)))) -> 30D-60D | Q7: 46212 | R7: PENDING LOAN | S7: UNMATCH | AE7: ATANG | AF7: TOPIK HIDAYAT | AH7: WHITE | AJ7: TAF | AK7: 2026 | AM7: 0.2
C8: 3 | D8: Tunas Toyota | F8: Tunas Toyota Kiara Condong | G8: =VLOOKUP($F8,List!$D$5:$G$35,3,0) -> Area 1 | H8: =VLOOKUP($F8,List!$D$5:$G$35,4,0) -> Area 1 - West Java | I8: =J8&K8 -> KDH223R-LEMDY00 | J8: KDH223R-LEMDY | K8: 00 | L8: =VLOOKUP(I8,'List Model'!A:E,4,0) -> HIACE | M8: =VLOOKUP(I8,'List Model'!A:E,5,0) -> HI ACE COMMUTER M/T | N8: =IF($Q8="",0,_xlfn.DAYS($A$6,$Q8)+1) -> 33 | O8: =IF($N8=0,"0",IF(AND($N8>=1,$N8<=7),"1 Minggu",IF(AND($N8>=8,$N8<=14),"2 Minggu",IF(AND($N8>=15,$N8<=21),"3 Minggu",IF(AND($N8>=22,$N8<=28),"4 Minggu",IF($N8>=29,"> 4 Minggu",0)))))) -> > 4 Minggu | P8: =IF($N8=0,"0",IF(AND($N8>=0,$N8<30),"<30D",IF(AND($N8>=30,$N8<=60),"30D-60D",IF($N8>60,">60D",0)))) -> 30D-60D | Q8: 46212 | R8: PENDING LOAN | S8: UNMATCH | AE8: ANI LESTARI | AF8: INDAH PITALOKA | AH8: WHITE | AJ8: TAF | AK8: 2026 | AM8: 0.2
C9: 4 | D9: Tunas Toyota | F9: Tunas Toyota Kiara Condong | G9: =VLOOKUP($F9,List!$D$5:$G$35,3,0) -> Area 1 | H9: =VLOOKUP($F9,List!$D$5:$G$35,4,0) -> Area 1 - West Java | I9: =J9&K9 -> MAGH10R-BPXHBD10 | J9: MAGH10R-BPXHBD | K9: 10 | L9: =VLOOKUP(I9,'List Model'!A:E,4,0) -> INNOVA ZENIX HYBRID | M9: =VLOOKUP(I9,'List Model'!A:E,5,0) -> INNOVA ZENIX HYBRID 2.0Q HV CVT TSS | N9: =IF($Q9="",0,_xlfn.DAYS($A$6,$Q9)+1) -> 32 | O9: =IF($N9=0,"0",IF(AND($N9>=1,$N9<=7),"1 Minggu",IF(AND($N9>=8,$N9<=14),"2 Minggu",IF(AND($N9>=15,$N9<=21),"3 Minggu",IF(AND($N9>=22,$N9<=28),"4 Minggu",IF($N9>=29,"> 4 Minggu",0)))))) -> > 4 Minggu | P9: =IF($N9=0,"0",IF(AND($N9>=0,$N9<30),"<30D",IF(AND($N9>=30,$N9<=60),"30D-60D",IF($N9>60,">60D",0)))) -> 30D-60D | Q9: 46213 | R9: PENDING LOAN | S9: UNMATCH | AE9: ELANG GARDA UTAMA | AF9: JAJANG NURJAMAN | AH9: ATTITUDE BLACK MICA | AJ9: TAF | AK9: 2026 | AM9: 0.2
C10: 5 | D10: Tunas Toyota | F10: Tunas Toyota Kiara Condong | G10: =VLOOKUP($F10,List!$D$5:$G$35,3,0) -> Area 1 | H10: =VLOOKUP($F10,List!$D$5:$G$35,4,0) -> Area 1 - West Java | I10: =J10&K10 -> GUN126R-DTTHXT00 | J10: GUN126R-DTTHXT | K10: 00 | L10: =VLOOKUP(I10,'List Model'!A:E,4,0) -> HILUX D-CAB | M10: =VLOOKUP(I10,'List Model'!A:E,5,0) -> HILUX 2.8 GR-S DOUBLE CABIN 4X4 A/T | N10: =IF($Q10="",0,_xlfn.DAYS($A$6,$Q10)+1) -> 32 | O10: =IF($N10=0,"0",IF(AND($N10>=1,$N10<=7),"1 Minggu",IF(AND($N10>=8,$N10<=14),"2 Minggu",IF(AND($N10>=15,$N10<=21),"3 Minggu",IF(AND($N10>=22,$N10<=28),"4 Minggu",IF($N10>=29,"> 4 Minggu",0)))))) -> > 4 Minggu | P10: =IF($N10=0,"0",IF(AND($N10>=0,$N10<30),"<30D",IF(AND($N10>=30,$N10<=60),"30D-60D",IF($N10>60,">60D",0)))) -> 30D-60D | Q10: 46213 | R10: PENDING LOAN | S10: UNMATCH | AE10: ELANG GARDA UTAMA | AF10: JAJANG NURJAMAN | AH10: SUPER WHITE II | AJ10: TAF | AK10: 2026 | AM10: 0.2
C11: 6 | D11: Tunas Toyota | F11: Tunas Toyota Kiara Condong | G11: =VLOOKUP($F11,List!$D$5:$G$35,3,0) -> Area 1 | H11: =VLOOKUP($F11,List!$D$5:$G$35,4,0) -> Area 1 - West Java | I11: =J11&K11 -> GUN166R-SDTHXD31 | J11: GUN166R-SDTHXD | K11: 31 | L11: =VLOOKUP(I11,'List Model'!A:E,4,0) -> FORTUNER 4X2 | M11: =VLOOKUP(I11,'List Model'!A:E,5,0) -> Fortuner 2.8 VRZ 4X2 A/T | N11: =IF($Q11="",0,_xlfn.DAYS($A$6,$Q11)+1) -> 28 | O11: =IF($N11=0,"0",IF(AND($N11>=1,$N11<=7),"1 Minggu",IF(AND($N11>=8,$N11<=14),"2 Minggu",IF(AND($N11>=15,$N11<=21),"3 Minggu",IF(AND($N11>=22,$N11<=28),"4 Minggu",IF($N11>=29,"> 4 Minggu",0)))))) -> 4 Minggu | P11: =IF($N11=0,"0",IF(AND($N11>=0,$N11<30),"<30D",IF(AND($N11>=30,$N11<=60),"30D-60D",IF($N11>60,">60D",0)))) -> <30D | Q11: 46217 | R11: FIRMED | S11: MATCH SUPPLY STOCK ON HAND | AE11: TENARDO PUTRA JAYA SINAGA | AF11: DERI NURSANDI | AH11: ATTITUDE BLACK MICA | AJ11: TAF | AK11: 2026 | AM11: 0.2
C12: 7 | D12: Tunas Toyota | F12: Tunas Toyota Kiara Condong | G12: =VLOOKUP($F12,List!$D$5:$G$35,3,0) -> Area 1 | H12: =VLOOKUP($F12,List!$D$5:$G$35,4,0) -> Area 1 - West Java | I12: =J12&K12 -> W101RE-LBMFJ00 | J12: W101RE-LBMFJ | K12: 00 | L12: =VLOOKUP(I12,'List Model'!A:E,4,0) -> AVANZA NEW | M12: =VLOOKUP(I12,'List Model'!A:E,5,0) -> NEW AVANZA 1.5G CVT | N12: =IF($Q12="",0,_xlfn.DAYS($A$6,$Q12)+1) -> 25 | O12: =IF($N12=0,"0",IF(AND($N12>=1,$N12<=7),"1 Minggu",IF(AND($N12>=8,$N12<=14),"2 Minggu",IF(AND($N12>=15,$N12<=21),"3 Minggu",IF(AND($N12>=22,$N12<=28),"4 Minggu",IF($N12>=29,"> 4 Minggu",0)))))) -> 4 Minggu | P12: =IF($N12=0,"0",IF(AND($N12>=0,$N12<30),"<30D",IF(AND($N12>=30,$N12<=60),"30D-60D",IF($N12>60,">60D",0)))) -> <30D | Q12: 46220 | R12: PENDING LOAN | S12: MATCH SUPPLY STOCK ON HAND | AE12: DERRY ARIANDI SAPTURA RUDIANA | AF12: DERI NURSANDI | AH12: Purplish Silver Mica Metallic | AJ12: ACC | AK12: 2026 | AM12: 0.2
C13: 8 | D13: Tunas Toyota | F13: Tunas Toyota Kiara Condong | G13: =VLOOKUP($F13,List!$D$5:$G$35,3,0) -> Area 1 | H13: =VLOOKUP($F13,List!$D$5:$G$35,4,0) -> Area 1 - West Java | I13: =J13&K13 -> GDH321R-EDFDYD10 | J13: GDH321R-EDFDYD | K13: 10 | L13: =VLOOKUP(I13,'List Model'!A:E,4,0) -> HIACE PREMIO | M13: =VLOOKUP(I13,'List Model'!A:E,5,0) -> HIACE 2.8 M/T | N13: =IF($Q13="",0,_xlfn.DAYS($A$6,$Q13)+1) -> 20 | O13: =IF($N13=0,"0",IF(AND($N13>=1,$N13<=7),"1 Minggu",IF(AND($N13>=8,$N13<=14),"2 Minggu",IF(AND($N13>=15,$N13<=21),"3 Minggu",IF(AND($N13>=22,$N13<=28),"4 Minggu",IF($N13>=29,"> 4 Minggu",0)))))) -> 3 Minggu | P13: =IF($N13=0,"0",IF(AND($N13>=0,$N13<30),"<30D",IF(AND($N13>=30,$N13<=60),"30D-60D",IF($N13>60,">60D",0)))) -> <30D | Q13: 46225 | R13: PENDING LOAN | S13: UNMATCH | AE13: FAUDRIE MOHAMADIVA, SE | AF13: DENI ALFIAN | AH13: WHITE | AJ13: OTHERS | AK13: 2026 | AM13: 0.2
C14: 9 | D14: Tunas Toyota | F14: Tunas Toyota Kiara Condong | G14: =VLOOKUP($F14,List!$D$5:$G$35,3,0) -> Area 1 | H14: =VLOOKUP($F14,List!$D$5:$G$35,4,0) -> Area 1 - West Java | I14: =J14&K14 -> W101RE-LMMFJ00 | J14: W101RE-LMMFJ | K14: 00 | L14: =VLOOKUP(I14,'List Model'!A:E,4,0) -> AVANZA NEW | M14: =VLOOKUP(I14,'List Model'!A:E,5,0) -> NEW AVANZA 1.5G M/T | N14: =IF($Q14="",0,_xlfn.DAYS($A$6,$Q14)+1) -> 19 | O14: =IF($N14=0,"0",IF(AND($N14>=1,$N14<=7),"1 Minggu",IF(AND($N14>=8,$N14<=14),"2 Minggu",IF(AND($N14>=15,$N14<=21),"3 Minggu",IF(AND($N14>=22,$N14<=28),"4 Minggu",IF($N14>=29,"> 4 Minggu",0)))))) -> 3 Minggu | P14: =IF($N14=0,"0",IF(AND($N14>=0,$N14<30),"<30D",IF(AND($N14>=30,$N14<=60),"30D-60D",IF($N14>60,">60D",0)))) -> <30D | Q14: 46226 | R14: PAYMENT ISSUE | S14: MATCH SUPPLY STOCK ON HAND | AE14: DEDE DINDIN | AF14: YENI | AH14: WHITE | AK14: 2026 | AM14: 0.2
C15: 10 | D15: Tunas Toyota | F15: Tunas Toyota Kiara Condong | G15: =VLOOKUP($F15,List!$D$5:$G$35,3,0) -> Area 1 | H15: =VLOOKUP($F15,List!$D$5:$G$35,4,0) -> Area 1 - West Java | I15: =J15&K15 -> B401RA-GMZFJ20 | J15: B401RA-GMZFJ | K15: 20 | L15: =VLOOKUP(I15,'List Model'!A:E,4,0) -> CALYA | M15: =VLOOKUP(I15,'List Model'!A:E,5,0) -> CALYA 1.2G M/T | N15: =IF($Q15="",0,_xlfn.DAYS($A$6,$Q15)+1) -> 18 | O15: =IF($N15=0,"0",IF(AND($N15>=1,$N15<=7),"1 Minggu",IF(AND($N15>=8,$N15<=14),"2 Minggu",IF(AND($N15>=15,$N15<=21),"3 Minggu",IF(AND($N15>=22,$N15<=28),"4 Minggu",IF($N15>=29,"> 4 Minggu",0)))))) -> 3 Minggu | P15: =IF($N15=0,"0",IF(AND($N15>=0,$N15<30),"<30D",IF(AND($N15>=30,$N15<=60),"30D-60D",IF($N15>60,">60D",0)))) -> <30D | Q15: 46227 | R15: PENDING LOAN | S15: MATCH SUPPLY STOCK ON HAND | AE15: IMAM NUR HAKIM | AF15: ERICK JANUAR LISAPALY | AH15: BLACK | AK15: 2026 | AM15: 0.2
C16: 11 | D16: Tunas Toyota | F16: Tunas Toyota Kiara Condong | G16: =VLOOKUP($F16,List!$D$5:$G$35,3,0) -> Area 1 | H16: =VLOOKUP($F16,List!$D$5:$G$35,4,0) -> Area 1 - West Java | I16: =J16&K16 -> GUN166R-SDTHXD33 | J16: GUN166R-SDTHXD | K16: 33 | L16: =VLOOKUP(I16,'List Model'!A:E,4,0) -> FORTUNER 4X2 | M16: =VLOOKUP(I16,'List Model'!A:E,5,0) -> Fortuner 2.8 VRZ 4X2 A/T | N16: =IF($Q16="",0,_xlfn.DAYS($A$6,$Q16)+1) -> 18 | O16: =IF($N16=0,"0",IF(AND($N16>=1,$N16<=7),"1 Minggu",IF(AND($N16>=8,$N16<=14),"2 Minggu",IF(AND($N16>=15,$N16<=21),"3 Minggu",IF(AND($N16>=22,$N16<=28),"4 Minggu",IF($N16>=29,"> 4 Minggu",0)))))) -> 3 Minggu | P16: =IF($N16=0,"0",IF(AND($N16>=0,$N16<30),"<30D",IF(AND($N16>=30,$N16<=60),"30D-60D",IF($N16>60,">60D",0)))) -> <30D | Q16: 46227 | R16: PENDING LOAN | S16: UNMATCH | AE16: ARIF NURPERMANA, S.PD.I | AF16: NOVA KHAIRUNNISA SUMARNA | AH16: PLATINUM WHITE PEARL | AK16: 2026 | AM16: 0.2
C17: 12 | D17: Tunas Toyota | F17: Tunas Toyota Kiara Condong | G17: =VLOOKUP($F17,List!$D$5:$G$35,3,0) -> Area 1 | H17: =VLOOKUP($F17,List!$D$5:$G$35,4,0) -> Area 1 - West Java | I17: =J17&K17 -> W100RE-LMDFJ00 | J17: W100RE-LMDFJ | K17: 00 | L17: =VLOOKUP(I17,'List Model'!A:E,4,0) -> AVANZA NEW | M17: =VLOOKUP(I17,'List Model'!A:E,5,0) -> NEW AVANZA 1.3E M/T | N17: =IF($Q17="",0,_xlfn.DAYS($A$6,$Q17)+1) -> 15 | O17: =IF($N17=0,"0",IF(AND($N17>=1,$N17<=7),"1 Minggu",IF(AND($N17>=8,$N17<=14),"2 Minggu",IF(AND($N17>=15,$N17<=21),"3 Minggu",IF(AND($N17>=22,$N17<=28),"4 Minggu",IF($N17>=29,"> 4 Minggu",0)))))) -> 3 Minggu | P17: =IF($N17=0,"0",IF(AND($N17>=0,$N17<30),"<30D",IF(AND($N17>=30,$N17<=60),"30D-60D",IF($N17>60,">60D",0)))) -> <30D | Q17: 46230 | R17: PENDING LOAN | S17: MATCH SUPPLY STOCK ON HAND | AE17: DIDIN SAEFUDIN | AF17: REGYAWAN KURNIA | AH17: WHITE | AK17: 2026 | AM17: 0.2
C18: 13 | D18: Tunas Toyota | F18: Tunas Toyota Kiara Condong | G18: =VLOOKUP($F18,List!$D$5:$G$35,3,0) -> Area 1 | H18: =VLOOKUP($F18,List!$D$5:$G$35,4,0) -> Area 1 - West Java | I18: =J18&K18 -> B401RA-GMZFJ20 | J18: B401RA-GMZFJ | K18: 20 | L18: =VLOOKUP(I18,'List Model'!A:E,4,0) -> CALYA | M18: =VLOOKUP(I18,'List Model'!A:E,5,0) -> CALYA 1.2G M/T | N18: =IF($Q18="",0,_xlfn.DAYS($A$6,$Q18)+1) -> 15 | O18: =IF($N18=0,"0",IF(AND($N18>=1,$N18<=7),"1 Minggu",IF(AND($N18>=8,$N18<=14),"2 Minggu",IF(AND($N18>=15,$N18<=21),"3 Minggu",IF(AND($N18>=22,$N18<=28),"4 Minggu",IF($N18>=29,"> 4 Minggu",0)))))) -> 3 Minggu | P18: =IF($N18=0,"0",IF(AND($N18>=0,$N18<30),"<30D",IF(AND($N18>=30,$N18<=60),"30D-60D",IF($N18>60,">60D",0)))) -> <30D | Q18: 46230 | R18: PENDING LOAN | S18: MATCH SUPPLY STOCK ON HAND | AE18: THOMAS MARIUS EDISON | AF18: DENO | AH18: BLACK | AK18: 2026 | AM18: 0.2
C19: 14 | D19: Tunas Toyota | F19: Tunas Toyota Kiara Condong | G19: =VLOOKUP($F19,List!$D$5:$G$35,3,0) -> Area 1 | H19: =VLOOKUP($F19,List!$D$5:$G$35,4,0) -> Area 1 - West Java | I19: =J19&K19 -> MAGA10R-BRXLBD01 | J19: MAGA10R-BRXLBD | K19: 01 | L19: =VLOOKUP(I19,'List Model'!A:E,4,0) -> INNOVA ZENIX | M19: =VLOOKUP(I19,'List Model'!A:E,5,0) -> INNOVA ZENIX 2.0G CVT | N19: =IF($Q19="",0,_xlfn.DAYS($A$6,$Q19)+1) -> 15 | O19: =IF($N19=0,"0",IF(AND($N19>=1,$N19<=7),"1 Minggu",IF(AND($N19>=8,$N19<=14),"2 Minggu",IF(AND($N19>=15,$N19<=21),"3 Minggu",IF(AND($N19>=22,$N19<=28),"4 Minggu",IF($N19>=29,"> 4 Minggu",0)))))) -> 3 Minggu | P19: =IF($N19=0,"0",IF(AND($N19>=0,$N19<30),"<30D",IF(AND($N19>=30,$N19<=60),"30D-60D",IF($N19>60,">60D",0)))) -> <30D | Q19: 46230 | R19: PENDING LOAN | S19: MATCH SUPPLY STOCK ON HAND | AE19: SUPRIADI, DRS | AF19: KHARISMA GALIH PUTRA | AH19: PLATINUM WHITE PEARL | AJ19: TAF | AK19: 2026 | AM19: 0.2
C20: 15 | D20: Tunas Toyota | F20: Tunas Toyota Kiara Condong | G20: =VLOOKUP($F20,List!$D$5:$G$35,3,0) -> Area 1 | H20: =VLOOKUP($F20,List!$D$5:$G$35,4,0) -> Area 1 - West Java | I20: =J20&K20 -> B401RA-GMZFJ20 | J20: B401RA-GMZFJ | K20: 20 | L20: =VLOOKUP(I20,'List Model'!A:E,4,0) -> CALYA | M20: =VLOOKUP(I20,'List Model'!A:E,5,0) -> CALYA 1.2G M/T | N20: =IF($Q20="",0,_xlfn.DAYS($A$6,$Q20)+1) -> 14 | O20: =IF($N20=0,"0",IF(AND($N20>=1,$N20<=7),"1 Minggu",IF(AND($N20>=8,$N20<=14),"2 Minggu",IF(AND($N20>=15,$N20<=21),"3 Minggu",IF(AND($N20>=22,$N20<=28),"4 Minggu",IF($N20>=29,"> 4 Minggu",0)))))) -> 2 Minggu | P20: =IF($N20=0,"0",IF(AND($N20>=0,$N20<30),"<30D",IF(AND($N20>=30,$N20<=60),"30D-60D",IF($N20>60,">60D",0)))) -> <30D | Q20: 46231 | R20: PENDING LOAN | S20: UNMATCH | AE20: SELVI DEWI AFRIANI | AF20: MUHAMMAD FADIL FAHMI RUSTANDI | AH20: DARK RED MICA MET. | AK20: 2026 | AM20: 0.2
C21: 16 | D21: Tunas Toyota | F21: Tunas Toyota Kiara Condong | G21: =VLOOKUP($F21,List!$D$5:$G$35,3,0) -> Area 1 | H21: =VLOOKUP($F21,List!$D$5:$G$35,4,0) -> Area 1 - West Java | I21: =J21&K21 -> A351RA-GBEFJ00 | J21: A351RA-GBEFJ | K21: 00 | L21: =VLOOKUP(I21,'List Model'!A:E,4,0) -> AGYA | M21: =VLOOKUP(I21,'List Model'!A:E,5,0) -> AGYA 1.2 G CVT | N21: =IF($Q21="",0,_xlfn.DAYS($A$6,$Q21)+1) -> 13 | O21: =IF($N21=0,"0",IF(AND($N21>=1,$N21<=7),"1 Minggu",IF(AND($N21>=8,$N21<=14),"2 Minggu",IF(AND($N21>=15,$N21<=21),"3 Minggu",IF(AND($N21>=22,$N21<=28),"4 Minggu",IF($N21>=29,"> 4 Minggu",0)))))) -> 2 Minggu | P21: =IF($N21=0,"0",IF(AND($N21>=0,$N21<30),"<30D",IF(AND($N21>=30,$N21<=60),"30D-60D",IF($N21>60,">60D",0)))) -> <30D | Q21: 46232 | R21: PENDING LOAN | S21: MATCH SUPPLY STOCK ON HAND | AE21: TEGES ADERIANI | AF21: ARDIAN PURNAMA | AH21: SILVER METALLIC | AJ21: MTF | AK21: 2026 | AM21: 0.2
C22: 17 | D22: Tunas Toyota | F22: Tunas Toyota Kiara Condong | G22: =VLOOKUP($F22,List!$D$5:$G$35,3,0) -> Area 1 | H22: =VLOOKUP($F22,List!$D$5:$G$35,4,0) -> Area 1 - West Java | I22: =J22&K22 -> B401RA-GMZFJ20 | J22: B401RA-GMZFJ | K22: 20 | L22: =VLOOKUP(I22,'List Model'!A:E,4,0) -> CALYA | M22: =VLOOKUP(I22,'List Model'!A:E,5,0) -> CALYA 1.2G M/T | N22: =IF($Q22="",0,_xlfn.DAYS($A$6,$Q22)+1) -> 12 | O22: =IF($N22=0,"0",IF(AND($N22>=1,$N22<=7),"1 Minggu",IF(AND($N22>=8,$N22<=14),"2 Minggu",IF(AND($N22>=15,$N22<=21),"3 Minggu",IF(AND($N22>=22,$N22<=28),"4 Minggu",IF($N22>=29,"> 4 Minggu",0)))))) -> 2 Minggu | P22: =IF($N22=0,"0",IF(AND($N22>=0,$N22<30),"<30D",IF(AND($N22>=30,$N22<=60),"30D-60D",IF($N22>60,">60D",0)))) -> <30D | Q22: 46233 | R22: FIRMED | S22: MATCH SUPPLY STOCK ON HAND | AE22: TUGIYONO | AF22: DADAN DARMADI | AH22: BLACK | AK22: 2026 | AM22: 0.2
C23: 18 | D23: Tunas Toyota | F23: Tunas Toyota Kiara Condong | G23: =VLOOKUP($F23,List!$D$5:$G$35,3,0) -> Area 1 | H23: =VLOOKUP($F23,List!$D$5:$G$35,4,0) -> Area 1 - West Java | I23: =J23&K23 -> MAGH10R-BRXLBD10 | J23: MAGH10R-BRXLBD | K23: 10 | L23: =VLOOKUP(I23,'List Model'!A:E,4,0) -> INNOVA ZENIX HYBRID | M23: =VLOOKUP(I23,'List Model'!A:E,5,0) -> INNOVA ZENIX HYBRID 2.0G HV CVT | N23: =IF($Q23="",0,_xlfn.DAYS($A$6,$Q23)+1) -> 11 | O23: =IF($N23=0,"0",IF(AND($N23>=1,$N23<=7),"1 Minggu",IF(AND($N23>=8,$N23<=14),"2 Minggu",IF(AND($N23>=15,$N23<=21),"3 Minggu",IF(AND($N23>=22,$N23<=28),"4 Minggu",IF($N23>=29,"> 4 Minggu",0)))))) -> 2 Minggu | P23: =IF($N23=0,"0",IF(AND($N23>=0,$N23<30),"<30D",IF(AND($N23>=30,$N23<=60),"30D-60D",IF($N23>60,">60D",0)))) -> <30D | Q23: 46234 | R23: FIRMED | S23: MATCH SUPPLY STOCK ON HAND | AE23: ENDANG SURYANA | AF23: YENI | AH23: ATTITUDE BLACK MICA | AK23: 2026 | AM23: 0.2
C24: 19 | D24: Tunas Toyota | F24: Tunas Toyota Kiara Condong | G24: =VLOOKUP($F24,List!$D$5:$G$35,3,0) -> Area 1 | H24: =VLOOKUP($F24,List!$D$5:$G$35,4,0) -> Area 1 - West Java | I24: =J24&K24 -> W102RE-LBVFJ08 | J24: W102RE-LBVFJ | K24: 08 | L24: =VLOOKUP(I24,'List Model'!A:E,4,0) -> VELOZ HYBRID | M24: =VLOOKUP(I24,'List Model'!A:E,5,0) -> VELOZ 1.5 Q HYBRID CVT-NON PREMIUM COLOR | N24: =IF($Q24="",0,_xlfn.DAYS($A$6,$Q24)+1) -> 10 | O24: =IF($N24=0,"0",IF(AND($N24>=1,$N24<=7),"1 Minggu",IF(AND($N24>=8,$N24<=14),"2 Minggu",IF(AND($N24>=15,$N24<=21),"3 Minggu",IF(AND($N24>=22,$N24<=28),"4 Minggu",IF($N24>=29,"> 4 Minggu",0)))))) -> 2 Minggu | P24: =IF($N24=0,"0",IF(AND($N24>=0,$N24<30),"<30D",IF(AND($N24>=30,$N24<=60),"30D-60D",IF($N24>60,">60D",0)))) -> <30D | Q24: 46235 | R24: FIRMED | S24: MATCH MDP | AE24: PT SURYA SUDECO | AF24: REGYAWAN KURNIA | AH24: BLACK MICA | AK24: 2026 | AM24: 0.2
C25: 20 | D25: Tunas Toyota | F25: Tunas Toyota Kiara Condong | G25: =VLOOKUP($F25,List!$D$5:$G$35,3,0) -> Area 1 | H25: =VLOOKUP($F25,List!$D$5:$G$35,4,0) -> Area 1 - West Java | I25: =J25&K25 -> W102RE-LBVFJ08 | J25: W102RE-LBVFJ | K25: 08 | L25: =VLOOKUP(I25,'List Model'!A:E,4,0) -> VELOZ HYBRID | M25: =VLOOKUP(I25,'List Model'!A:E,5,0) -> VELOZ 1.5 Q HYBRID CVT-NON PREMIUM COLOR | N25: =IF($Q25="",0,_xlfn.DAYS($A$6,$Q25)+1) -> 10 | O25: =IF($N25=0,"0",IF(AND($N25>=1,$N25<=7),"1 Minggu",IF(AND($N25>=8,$N25<=14),"2 Minggu",IF(AND($N25>=15,$N25<=21),"3 Minggu",IF(AND($N25>=22,$N25<=28),"4 Minggu",IF($N25>=29,"> 4 Minggu",0)))))) -> 2 Minggu | P25: =IF($N25=0,"0",IF(AND($N25>=0,$N25<30),"<30D",IF(AND($N25>=30,$N25<=60),"30D-60D",IF($N25>60,">60D",0)))) -> <30D | Q25: 46235 | R25: FIRMED | S25: MATCH MDP | AE25: PT SURYA SUDECO | AF25: REGYAWAN KURNIA | AH25: BLACK MICA | AK25: 2026 | AM25: 0.2
C26: 21 | D26: Tunas Toyota | F26: Tunas Toyota Kiara Condong | G26: =VLOOKUP($F26,List!$D$5:$G$35,3,0) -> Area 1 | H26: =VLOOKUP($F26,List!$D$5:$G$35,4,0) -> Area 1 - West Java | I26: =J26&K26 -> W102RE-LBVFJ08 | J26: W102RE-LBVFJ | K26: 08 | L26: =VLOOKUP(I26,'List Model'!A:E,4,0) -> VELOZ HYBRID | M26: =VLOOKUP(I26,'List Model'!A:E,5,0) -> VELOZ 1.5 Q HYBRID CVT-NON PREMIUM COLOR | N26: =IF($Q26="",0,_xlfn.DAYS($A$6,$Q26)+1) -> 10 | O26: =IF($N26=0,"0",IF(AND($N26>=1,$N26<=7),"1 Minggu",IF(AND($N26>=8,$N26<=14),"2 Minggu",IF(AND($N26>=15,$N26<=21),"3 Minggu",IF(AND($N26>=22,$N26<=28),"4 Minggu",IF($N26>=29,"> 4 Minggu",0)))))) -> 2 Minggu | P26: =IF($N26=0,"0",IF(AND($N26>=0,$N26<30),"<30D",IF(AND($N26>=30,$N26<=60),"30D-60D",IF($N26>60,">60D",0)))) -> <30D | Q26: 46235 | R26: FIRMED | S26: MATCH MDP | AE26: PT SURYA SUDECO | AF26: REGYAWAN KURNIA | AH26: BLACK MICA | AK26: 2026 | AM26: 0.2
C27: 22 | D27: Tunas Toyota | F27: Tunas Toyota Kiara Condong | G27: =VLOOKUP($F27,List!$D$5:$G$35,3,0) -> Area 1 | H27: =VLOOKUP($F27,List!$D$5:$G$35,4,0) -> Area 1 - West Java | I27: =J27&K27 -> W102RE-LBVFJ08 | J27: W102RE-LBVFJ | K27: 08 | L27: =VLOOKUP(I27,'List Model'!A:E,4,0) -> VELOZ HYBRID | M27: =VLOOKUP(I27,'List Model'!A:E,5,0) -> VELOZ 1.5 Q HYBRID CVT-NON PREMIUM COLOR | N27: =IF($Q27="",0,_xlfn.DAYS($A$6,$Q27)+1) -> 10 | O27: =IF($N27=0,"0",IF(AND($N27>=1,$N27<=7),"1 Minggu",IF(AND($N27>=8,$N27<=14),"2 Minggu",IF(AND($N27>=15,$N27<=21),"3 Minggu",IF(AND($N27>=22,$N27<=28),"4 Minggu",IF($N27>=29,"> 4 Minggu",0)))))) -> 2 Minggu | P27: =IF($N27=0,"0",IF(AND($N27>=0,$N27<30),"<30D",IF(AND($N27>=30,$N27<=60),"30D-60D",IF($N27>60,">60D",0)))) -> <30D | Q27: 46235 | R27: FIRMED | S27: MATCH MDP | AE27: PT SURYA SUDECO | AF27: REGYAWAN KURNIA | AH27: BLACK MICA | AK27: 2026 | AM27: 0.2
C28: 23 | D28: Tunas Toyota | F28: Tunas Toyota Kiara Condong | G28: =VLOOKUP($F28,List!$D$5:$G$35,3,0) -> Area 1 | H28: =VLOOKUP($F28,List!$D$5:$G$35,4,0) -> Area 1 - West Java | I28: =J28&K28 -> W102RE-LBVFJ08 | J28: W102RE-LBVFJ | K28: 08 | L28: =VLOOKUP(I28,'List Model'!A:E,4,0) -> VELOZ HYBRID | M28: =VLOOKUP(I28,'List Model'!A:E,5,0) -> VELOZ 1.5 Q HYBRID CVT-NON PREMIUM COLOR | N28: =IF($Q28="",0,_xlfn.DAYS($A$6,$Q28)+1) -> 10 | O28: =IF($N28=0,"0",IF(AND($N28>=1,$N28<=7),"1 Minggu",IF(AND($N28>=8,$N28<=14),"2 Minggu",IF(AND($N28>=15,$N28<=21),"3 Minggu",IF(AND($N28>=22,$N28<=28),"4 Minggu",IF($N28>=29,"> 4 Minggu",0)))))) -> 2 Minggu | P28: =IF($N28=0,"0",IF(AND($N28>=0,$N28<30),"<30D",IF(AND($N28>=30,$N28<=60),"30D-60D",IF($N28>60,">60D",0)))) -> <30D | Q28: 46235 | R28: FIRMED | S28: MATCH MDP | AE28: PT SURYA SUDECO | AF28: REGYAWAN KURNIA | AH28: BLACK MICA | AK28: 2026 | AM28: 0.2
C29: 24 | D29: Tunas Toyota | F29: Tunas Toyota Kiara Condong | G29: =VLOOKUP($F29,List!$D$5:$G$35,3,0) -> Area 1 | H29: =VLOOKUP($F29,List!$D$5:$G$35,4,0) -> Area 1 - West Java | I29: =J29&K29 -> W102RE-LBVFJ08 | J29: W102RE-LBVFJ | K29: 08 | L29: =VLOOKUP(I29,'List Model'!A:E,4,0) -> VELOZ HYBRID | M29: =VLOOKUP(I29,'List Model'!A:E,5,0) -> VELOZ 1.5 Q HYBRID CVT-NON PREMIUM COLOR | N29: =IF($Q29="",0,_xlfn.DAYS($A$6,$Q29)+1) -> 10 | O29: =IF($N29=0,"0",IF(AND($N29>=1,$N29<=7),"1 Minggu",IF(AND($N29>=8,$N29<=14),"2 Minggu",IF(AND($N29>=15,$N29<=21),"3 Minggu",IF(AND($N29>=22,$N29<=28),"4 Minggu",IF($N29>=29,"> 4 Minggu",0)))))) -> 2 Minggu | P29: =IF($N29=0,"0",IF(AND($N29>=0,$N29<30),"<30D",IF(AND($N29>=30,$N29<=60),"30D-60D",IF($N29>60,">60D",0)))) -> <30D | Q29: 46235 | R29: FIRMED | S29: MATCH MDP | AE29: PT SURYA SUDECO | AF29: REGYAWAN KURNIA | AH29: BLACK MICA | AK29: 2026 | AM29: 0.2
C30: 25 | D30: Tunas Toyota | F30: Tunas Toyota Kiara Condong | G30: =VLOOKUP($F30,List!$D$5:$G$35,3,0) -> Area 1 | H30: =VLOOKUP($F30,List!$D$5:$G$35,4,0) -> Area 1 - West Java | I30: =J30&K30 -> W102RE-LBVFJ08 | J30: W102RE-LBVFJ | K30: 08 | L30: =VLOOKUP(I30,'List Model'!A:E,4,0) -> VELOZ HYBRID | M30: =VLOOKUP(I30,'List Model'!A:E,5,0) -> VELOZ 1.5 Q HYBRID CVT-NON PREMIUM COLOR | N30: =IF($Q30="",0,_xlfn.DAYS($A$6,$Q30)+1) -> 10 | O30: =IF($N30=0,"0",IF(AND($N30>=1,$N30<=7),"1 Minggu",IF(AND($N30>=8,$N30<=14),"2 Minggu",IF(AND($N30>=15,$N30<=21),"3 Minggu",IF(AND($N30>=22,$N30<=28),"4 Minggu",IF($N30>=29,"> 4 Minggu",0)))))) -> 2 Minggu | P30: =IF($N30=0,"0",IF(AND($N30>=0,$N30<30),"<30D",IF(AND($N30>=30,$N30<=60),"30D-60D",IF($N30>60,">60D",0)))) -> <30D | Q30: 46235 | R30: FIRMED | S30: MATCH MDP | AE30: PT SURYA SUDECO | AF30: REGYAWAN KURNIA | AH30: BLACK MICA | AK30: 2026 | AM30: 0.2
C31: 26 | D31: Tunas Toyota | F31: Tunas Toyota Kiara Condong | G31: =VLOOKUP($F31,List!$D$5:$G$35,3,0) -> Area 1 | H31: =VLOOKUP($F31,List!$D$5:$G$35,4,0) -> Area 1 - West Java | I31: =J31&K31 -> W102RE-LBVFJ08 | J31: W102RE-LBVFJ | K31: 08 | L31: =VLOOKUP(I31,'List Model'!A:E,4,0) -> VELOZ HYBRID | M31: =VLOOKUP(I31,'List Model'!A:E,5,0) -> VELOZ 1.5 Q HYBRID CVT-NON PREMIUM COLOR | N31: =IF($Q31="",0,_xlfn.DAYS($A$6,$Q31)+1) -> 10 | O31: =IF($N31=0,"0",IF(AND($N31>=1,$N31<=7),"1 Minggu",IF(AND($N31>=8,$N31<=14),"2 Minggu",IF(AND($N31>=15,$N31<=21),"3 Minggu",IF(AND($N31>=22,$N31<=28),"4 Minggu",IF($N31>=29,"> 4 Minggu",0)))))) -> 2 Minggu | P31: =IF($N31=0,"0",IF(AND($N31>=0,$N31<30),"<30D",IF(AND($N31>=30,$N31<=60),"30D-60D",IF($N31>60,">60D",0)))) -> <30D | Q31: 46235 | R31: FIRMED | S31: MATCH MDP | AE31: PT SURYA SUDECO | AF31: REGYAWAN KURNIA | AH31: BLACK MICA | AK31: 2026 | AM31: 0.2
C32: 27 | D32: Tunas Toyota | F32: Tunas Toyota Kiara Condong | G32: =VLOOKUP($F32,List!$D$5:$G$35,3,0) -> Area 1 | H32: =VLOOKUP($F32,List!$D$5:$G$35,4,0) -> Area 1 - West Java | I32: =J32&K32 -> W102RE-LBVFJ08 | J32: W102RE-LBVFJ | K32: 08 | L32: =VLOOKUP(I32,'List Model'!A:E,4,0) -> VELOZ HYBRID | M32: =VLOOKUP(I32,'List Model'!A:E,5,0) -> VELOZ 1.5 Q HYBRID CVT-NON PREMIUM COLOR | N32: =IF($Q32="",0,_xlfn.DAYS($A$6,$Q32)+1) -> 10 | O32: =IF($N32=0,"0",IF(AND($N32>=1,$N32<=7),"1 Minggu",IF(AND($N32>=8,$N32<=14),"2 Minggu",IF(AND($N32>=15,$N32<=21),"3 Minggu",IF(AND($N32>=22,$N32<=28),"4 Minggu",IF($N32>=29,"> 4 Minggu",0)))))) -> 2 Minggu | P32: =IF($N32=0,"0",IF(AND($N32>=0,$N32<30),"<30D",IF(AND($N32>=30,$N32<=60),"30D-60D",IF($N32>60,">60D",0)))) -> <30D | Q32: 46235 | R32: FIRMED | S32: MATCH MDP | AE32: PT SURYA SUDECO | AF32: REGYAWAN KURNIA | AH32: BLACK MICA | AK32: 2026 | AM32: 0.2
C33: 28 | D33: Tunas Toyota | F33: Tunas Toyota Kiara Condong | G33: =VLOOKUP($F33,List!$D$5:$G$35,3,0) -> Area 1 | H33: =VLOOKUP($F33,List!$D$5:$G$35,4,0) -> Area 1 - West Java | I33: =J33&K33 -> W102RE-LBVFJ08 | J33: W102RE-LBVFJ | K33: 08 | L33: =VLOOKUP(I33,'List Model'!A:E,4,0) -> VELOZ HYBRID | M33: =VLOOKUP(I33,'List Model'!A:E,5,0) -> VELOZ 1.5 Q HYBRID CVT-NON PREMIUM COLOR | N33: =IF($Q33="",0,_xlfn.DAYS($A$6,$Q33)+1) -> 10 | O33: =IF($N33=0,"0",IF(AND($N33>=1,$N33<=7),"1 Minggu",IF(AND($N33>=8,$N33<=14),"2 Minggu",IF(AND($N33>=15,$N33<=21),"3 Minggu",IF(AND($N33>=22,$N33<=28),"4 Minggu",IF($N33>=29,"> 4 Minggu",0)))))) -> 2 Minggu | P33: =IF($N33=0,"0",IF(AND($N33>=0,$N33<30),"<30D",IF(AND($N33>=30,$N33<=60),"30D-60D",IF($N33>60,">60D",0)))) -> <30D | Q33: 46235 | R33: FIRMED | S33: MATCH MDP | AE33: PT SURYA SUDECO | AF33: REGYAWAN KURNIA | AH33: BLACK MICA | AK33: 2026 | AM33: 0.2
C34: 29 | D34: Tunas Toyota | F34: Tunas Toyota Kiara Condong | G34: =VLOOKUP($F34,List!$D$5:$G$35,3,0) -> Area 1 | H34: =VLOOKUP($F34,List!$D$5:$G$35,4,0) -> Area 1 - West Java | I34: =J34&K34 -> W102RE-LBVFJ08 | J34: W102RE-LBVFJ | K34: 08 | L34: =VLOOKUP(I34,'List Model'!A:E,4,0) -> VELOZ HYBRID | M34: =VLOOKUP(I34,'List Model'!A:E,5,0) -> VELOZ 1.5 Q HYBRID CVT-NON PREMIUM COLOR | N34: =IF($Q34="",0,_xlfn.DAYS($A$6,$Q34)+1) -> 10 | O34: =IF($N34=0,"0",IF(AND($N34>=1,$N34<=7),"1 Minggu",IF(AND($N34>=8,$N34<=14),"2 Minggu",IF(AND($N34>=15,$N34<=21),"3 Minggu",IF(AND($N34>=22,$N34<=28),"4 Minggu",IF($N34>=29,"> 4 Minggu",0)))))) -> 2 Minggu | P34: =IF($N34=0,"0",IF(AND($N34>=0,$N34<30),"<30D",IF(AND($N34>=30,$N34<=60),"30D-60D",IF($N34>60,">60D",0)))) -> <30D | Q34: 46235 | R34: FIRMED | S34: MATCH MDP | AE34: PT SURYA SUDECO | AF34: REGYAWAN KURNIA | AH34: BLACK MICA | AK34: 2026 | AM34: 0.2
C35: 30 | D35: Tunas Toyota | F35: Tunas Toyota Kiara Condong | G35: =VLOOKUP($F35,List!$D$5:$G$35,3,0) -> Area 1 | H35: =VLOOKUP($F35,List!$D$5:$G$35,4,0) -> Area 1 - West Java | I35: =J35&K35 -> W102RE-LBVFJ08 | J35: W102RE-LBVFJ | K35: 08 | L35: =VLOOKUP(I35,'List Model'!A:E,4,0) -> VELOZ HYBRID | M35: =VLOOKUP(I35,'List Model'!A:E,5,0) -> VELOZ 1.5 Q HYBRID CVT-NON PREMIUM COLOR | N35: =IF($Q35="",0,_xlfn.DAYS($A$6,$Q35)+1) -> 10 | O35: =IF($N35=0,"0",IF(AND($N35>=1,$N35<=7),"1 Minggu",IF(AND($N35>=8,$N35<=14),"2 Minggu",IF(AND($N35>=15,$N35<=21),"3 Minggu",IF(AND($N35>=22,$N35<=28),"4 Minggu",IF($N35>=29,"> 4 Minggu",0)))))) -> 2 Minggu | P35: =IF($N35=0,"0",IF(AND($N35>=0,$N35<30),"<30D",IF(AND($N35>=30,$N35<=60),"30D-60D",IF($N35>60,">60D",0)))) -> <30D | Q35: 46235 | R35: FIRMED | S35: MATCH MDP | AE35: PT SURYA SUDECO | AF35: REGYAWAN KURNIA | AH35: BLACK MICA | AK35: 2026 | AM35: 0.2
... C38: 33 | D38: Tunas Toyota | F38: Tunas Toyota Kiara Condong | G38: =VLOOKUP($F38,List!$D$5:$G$35,3,0) -> Area 1 | H38: =VLOOKUP($F38,List!$D$5:$G$35,4,0) -> Area 1 - West Java | I38: =J38&K38 -> W102RE-LBVFJ08 | J38: W102RE-LBVFJ | K38: 08 | L38: =VLOOKUP(I38,'List Model'!A:E,4,0) -> VELOZ HYBRID | M38: =VLOOKUP(I38,'List Model'!A:E,5,0) -> VELOZ 1.5 Q HYBRID CVT-NON PREMIUM COLOR | N38: =IF($Q38="",0,_xlfn.DAYS($A$6,$Q38)+1) -> 6 | O38: =IF($N38=0,"0",IF(AND($N38>=1,$N38<=7),"1 Minggu",IF(AND($N38>=8,$N38<=14),"2 Minggu",IF(AND($N38>=15,$N38<=21),"3 Minggu",IF(AND($N38>=22,$N38<=28),"4 Minggu",IF($N38>=29,"> 4 Minggu",0)))))) -> 1 Minggu | P38: =IF($N38=0,"0",IF(AND($N38>=0,$N38<30),"<30D",IF(AND($N38>=30,$N38<=60),"30D-60D",IF($N38>60,">60D",0)))) -> <30D | Q38: 46239 | R38: FIRMED | S38: MATCH MDP | AE38: PT SURYA SUDECO | AF38: REGYAWAN KURNIA | AH38: BLACK MICA | AK38: 2026 | AM38: 0.2
C39: 34 | D39: Tunas Toyota | F39: Tunas Toyota Kiara Condong | G39: =VLOOKUP($F39,List!$D$5:$G$35,3,0) -> Area 1 | H39: =VLOOKUP($F39,List!$D$5:$G$35,4,0) -> Area 1 - West Java | I39: =J39&K39 -> B101RA-GMSGJ41 | J39: B101RA-GMSGJ | K39: 41 | L39: =VLOOKUP(I39,'List Model'!A:E,4,0) -> AGYA | M39: =VLOOKUP(I39,'List Model'!A:E,5,0) -> AGYA 1.2 G M/T | N39: =IF($Q39="",0,_xlfn.DAYS($A$6,$Q39)+1) -> 2 | O39: =IF($N39=0,"0",IF(AND($N39>=1,$N39<=7),"1 Minggu",IF(AND($N39>=8,$N39<=14),"2 Minggu",IF(AND($N39>=15,$N39<=21),"3 Minggu",IF(AND($N39>=22,$N39<=28),"4 Minggu",IF($N39>=29,"> 4 Minggu",0)))))) -> 1 Minggu | P39: =IF($N39=0,"0",IF(AND($N39>=0,$N39<30),"<30D",IF(AND($N39>=30,$N39<=60),"30D-60D",IF($N39>60,">60D",0)))) -> <30D | Q39: 46243 | R39: PENDING LOAN | S39: MATCH MDP | AE39: RUDI HARIYANTO. S. T. | AF39: YANI ANDRIYANI | AH39: WHITE
C40: 35 | D40: Tunas Toyota | F40: Tunas Toyota Kiara Condong | G40: =VLOOKUP($F40,List!$D$5:$G$35,3,0) -> Area 1 | H40: =VLOOKUP($F40,List!$D$5:$G$35,4,0) -> Area 1 - West Java | I40: =J40&K40 -> B401RA-GMZFJ20 | J40: B401RA-GMZFJ | K40: 20 | L40: =VLOOKUP(I40,'List Model'!A:E,4,0) -> CALYA | M40: =VLOOKUP(I40,'List Model'!A:E,5,0) -> CALYA 1.2G M/T | N40: =IF($Q40="",0,_xlfn.DAYS($A$6,$Q40)+1) -> 2 | O40: =IF($N40=0,"0",IF(AND($N40>=1,$N40<=7),"1 Minggu",IF(AND($N40>=8,$N40<=14),"2 Minggu",IF(AND($N40>=15,$N40<=21),"3 Minggu",IF(AND($N40>=22,$N40<=28),"4 Minggu",IF($N40>=29,"> 4 Minggu",0)))))) -> 1 Minggu | P40: =IF($N40=0,"0",IF(AND($N40>=0,$N40<30),"<30D",IF(AND($N40>=30,$N40<=60),"30D-60D",IF($N40>60,">60D",0)))) -> <30D | Q40: 46243 | R40: PENDING LOAN | S40: MATCH SUPPLY STOCK ON HAND | AE40: RUNILAH BH SARIWAN KARTIYA | AF40: JUARNA KARMAN PUTRA | AH40: GRAY METALLIC
C41: 36 | D41: Tunas Toyota | F41: Tunas Toyota Kiara Condong | G41: =VLOOKUP($F41,List!$D$5:$G$35,3,0) -> Area 1 | H41: =VLOOKUP($F41,List!$D$5:$G$35,4,0) -> Area 1 - West Java | I41: =J41&K41 -> GUN112R-BTMXYD00 | J41: GUN112R-BTMXYD | K41: 00 | L41: =VLOOKUP(I41,'List Model'!A:E,4,0) -> HILUX S-CAB | M41: =VLOOKUP(I41,'List Model'!A:E,5,0) -> HILUX PICK UP 2.4 DSL M/T | N41: =IF($Q41="",0,_xlfn.DAYS($A$6,$Q41)+1) -> 3 | O41: =IF($N41=0,"0",IF(AND($N41>=1,$N41<=7),"1 Minggu",IF(AND($N41>=8,$N41<=14),"2 Minggu",IF(AND($N41>=15,$N41<=21),"3 Minggu",IF(AND($N41>=22,$N41<=28),"4 Minggu",IF($N41>=29,"> 4 Minggu",0)))))) -> 1 Minggu | P41: =IF($N41=0,"0",IF(AND($N41>=0,$N41<30),"<30D",IF(AND($N41>=30,$N41<=60),"30D-60D",IF($N41>60,">60D",0)))) -> <30D | Q41: 46242 | R41: PENDING LOAN | S41: UNMATCH | AE41: ABDUL KODIR | AF41: MUHAMMAD FADIL FAHMI RUSTANDI | AH41: ATTITUDE BLACK MICA | AJ41: PT.TOYOTA ASTRA FINANCIAL SERVICES
C42: 37 | D42: Tunas Toyota | F42: Tunas Toyota Kiara Condong | G42: =VLOOKUP($F42,List!$D$5:$G$35,3,0) -> Area 1 | H42: =VLOOKUP($F42,List!$D$5:$G$35,4,0) -> Area 1 - West Java | I42: =J42&K42 -> GUN142R-MDMSYD22 | J42: GUN142R-MDMSYD | K42: 22 | L42: =VLOOKUP(I42,'List Model'!A:E,4,0) -> INNOVA | M42: =VLOOKUP(I42,'List Model'!A:E,5,0) -> INNOVA 2.4G M/T | N42: =IF($Q42="",0,_xlfn.DAYS($A$6,$Q42)+1) -> 4 | O42: =IF($N42=0,"0",IF(AND($N42>=1,$N42<=7),"1 Minggu",IF(AND($N42>=8,$N42<=14),"2 Minggu",IF(AND($N42>=15,$N42<=21),"3 Minggu",IF(AND($N42>=22,$N42<=28),"4 Minggu",IF($N42>=29,"> 4 Minggu",0)))))) -> 1 Minggu | P42: =IF($N42=0,"0",IF(AND($N42>=0,$N42<30),"<30D",IF(AND($N42>=30,$N42<=60),"30D-60D",IF($N42>60,">60D",0)))) -> <30D | Q42: 46241 | R42: PENDING LOAN | S42: UNMATCH | AE42: DEDI TAUFIK HIDAYAT | AF42: ANDRI JAYA LAKSANA | AH42: SUPER WHITE II | AJ42: PT.TOYOTA ASTRA FINANCIAL SERVICES
C43: 38 | D43: Tunas Toyota | F43: Tunas Toyota Kiara Condong | G43: =VLOOKUP($F43,List!$D$5:$G$35,3,0) -> Area 1 | H43: =VLOOKUP($F43,List!$D$5:$G$35,4,0) -> Area 1 - West Java | I43: =J43&K43 -> A351RA-GBGFJ02 | J43: A351RA-GBGFJ | K43: 02 | L43: =VLOOKUP(I43,'List Model'!A:E,4,0) -> AGYA GR-S | M43: =VLOOKUP(I43,'List Model'!A:E,5,0) -> AGYA 1.2 GR CVT | N43: =IF($Q43="",0,_xlfn.DAYS($A$6,$Q43)+1) -> 4 | O43: =IF($N43=0,"0",IF(AND($N43>=1,$N43<=7),"1 Minggu",IF(AND($N43>=8,$N43<=14),"2 Minggu",IF(AND($N43>=15,$N43<=21),"3 Minggu",IF(AND($N43>=22,$N43<=28),"4 Minggu",IF($N43>=29,"> 4 Minggu",0)))))) -> 1 Minggu | P43: =IF($N43=0,"0",IF(AND($N43>=0,$N43<30),"<30D",IF(AND($N43>=30,$N43<=60),"30D-60D",IF($N43>60,">60D",0)))) -> <30D | Q43: 46241 | R43: PENDING LOAN | S43: UNMATCH | AE43: PUTRI HESTI PERTIWI | AF43: ARDIAN PURNAMA | AH43: RED M. M | AJ43: PT.TOYOTA ASTRA FINANCIAL SERVICES
C44: 39 | D44: Tunas Toyota | F44: Tunas Toyota Kiara Condong | G44: =VLOOKUP($F44,List!$D$5:$G$35,3,0) -> Area 1 | H44: =VLOOKUP($F44,List!$D$5:$G$35,4,0) -> Area 1 - West Java | I44: =J44&K44 -> B401RA-GQZFJ02 | J44: B401RA-GQZFJ | K44: 02 | L44: =VLOOKUP(I44,'List Model'!A:E,4,0) -> CALYA | M44: =VLOOKUP(I44,'List Model'!A:E,5,0) -> CALYA 1.2G A/T | N44: =IF($Q44="",0,_xlfn.DAYS($A$6,$Q44)+1) -> 4 | O44: =IF($N44=0,"0",IF(AND($N44>=1,$N44<=7),"1 Minggu",IF(AND($N44>=8,$N44<=14),"2 Minggu",IF(AND($N44>=15,$N44<=21),"3 Minggu",IF(AND($N44>=22,$N44<=28),"4 Minggu",IF($N44>=29,"> 4 Minggu",0)))))) -> 1 Minggu | P44: =IF($N44=0,"0",IF(AND($N44>=0,$N44<30),"<30D",IF(AND($N44>=30,$N44<=60),"30D-60D",IF($N44>60,">60D",0)))) -> <30D | Q44: 46241 | R44: PENDING LOAN | S44: MATCH SUPPLY STOCK ON HAND | AE44: MOCHAMAD KAMAL UDIN | AF44: NOFIA NURIFAH | AH44: BLACK
C45: 40 | D45: Tunas Toyota | F45: Tunas Toyota Kiara Condong | G45: =VLOOKUP($F45,List!$D$5:$G$35,3,0) -> Area 1 | H45: =VLOOKUP($F45,List!$D$5:$G$35,4,0) -> Area 1 - West Java | I45: =J45&K45 -> KDH223R-LEMDY00 | J45: KDH223R-LEMDY | K45: 00 | L45: =VLOOKUP(I45,'List Model'!A:E,4,0) -> HIACE | M45: =VLOOKUP(I45,'List Model'!A:E,5,0) -> HI ACE COMMUTER M/T | N45: =IF($Q45="",0,_xlfn.DAYS($A$6,$Q45)+1) -> 4 | O45: =IF($N45=0,"0",IF(AND($N45>=1,$N45<=7),"1 Minggu",IF(AND($N45>=8,$N45<=14),"2 Minggu",IF(AND($N45>=15,$N45<=21),"3 Minggu",IF(AND($N45>=22,$N45<=28),"4 Minggu",IF($N45>=29,"> 4 Minggu",0)))))) -> 1 Minggu | P45: =IF($N45=0,"0",IF(AND($N45>=0,$N45<30),"<30D",IF(AND($N45>=30,$N45<=60),"30D-60D",IF($N45>60,">60D",0)))) -> <30D | Q45: 46241 | R45: PENDING LOAN | S45: UNMATCH | AE45: AI NURJANAH | AF45: KHARISMA GALIH PUTRA | AH45: White
C46: 41 | D46: Tunas Toyota | F46: Tunas Toyota Kiara Condong | G46: =VLOOKUP($F46,List!$D$5:$G$35,3,0) -> Area 1 | H46: =VLOOKUP($F46,List!$D$5:$G$35,4,0) -> Area 1 - West Java | I46: =J46&K46 -> B401RA-GMZFJ20 | J46: B401RA-GMZFJ | K46: 20 | L46: =VLOOKUP(I46,'List Model'!A:E,4,0) -> CALYA | M46: =VLOOKUP(I46,'List Model'!A:E,5,0) -> CALYA 1.2G M/T | N46: =IF($Q46="",0,_xlfn.DAYS($A$6,$Q46)+1) -> 5 | O46: =IF($N46=0,"0",IF(AND($N46>=1,$N46<=7),"1 Minggu",IF(AND($N46>=8,$N46<=14),"2 Minggu",IF(AND($N46>=15,$N46<=21),"3 Minggu",IF(AND($N46>=22,$N46<=28),"4 Minggu",IF($N46>=29,"> 4 Minggu",0)))))) -> 1 Minggu | P46: =IF($N46=0,"0",IF(AND($N46>=0,$N46<30),"<30D",IF(AND($N46>=30,$N46<=60),"30D-60D",IF($N46>60,">60D",0)))) -> <30D | Q46: 46240 | R46: PENDING LOAN | S46: MATCH MDP | AE46: DENI RESMANA | AF46: DENO | AH46: Silver Metallic
C47: 42 | D47: Tunas Toyota | F47: Tunas Toyota Kiara Condong | G47: =VLOOKUP($F47,List!$D$5:$G$35,3,0) -> Area 1 | H47: =VLOOKUP($F47,List!$D$5:$G$35,4,0) -> Area 1 - West Java | I47: =J47&K47 -> GUN142R-MDTSXD30 | J47: GUN142R-MDTSXD | K47: 30 | L47: =VLOOKUP(I47,'List Model'!A:E,4,0) -> INNOVA | M47: =VLOOKUP(I47,'List Model'!A:E,5,0) -> INNOVA 2.4G A/T | N47: =IF($Q47="",0,_xlfn.DAYS($A$6,$Q47)+1) -> 5 | O47: =IF($N47=0,"0",IF(AND($N47>=1,$N47<=7),"1 Minggu",IF(AND($N47>=8,$N47<=14),"2 Minggu",IF(AND($N47>=15,$N47<=21),"3 Minggu",IF(AND($N47>=22,$N47<=28),"4 Minggu",IF($N47>=29,"> 4 Minggu",0)))))) -> 1 Minggu | P47: =IF($N47=0,"0",IF(AND($N47>=0,$N47<30),"<30D",IF(AND($N47>=30,$N47<=60),"30D-60D",IF($N47>60,">60D",0)))) -> <30D | Q47: 46240 | R47: PENDING LOAN | S47: MATCH SUPPLY STOCK ON HAND | AE47: SOIMAN | AF47: REGYAWAN KURNIA | AH47: ATTITUDE BLACK MICA
C48: 43 | D48: Tunas Toyota | F48: Tunas Toyota Kiara Condong | G48: =VLOOKUP($F48,List!$D$5:$G$35,3,0) -> Area 1 | H48: =VLOOKUP($F48,List!$D$5:$G$35,4,0) -> Area 1 - West Java | I48: =J48&K48 -> A351RA-GBEFJ00 | J48: A351RA-GBEFJ | K48: 00 | L48: =VLOOKUP(I48,'List Model'!A:E,4,0) -> AGYA | M48: =VLOOKUP(I48,'List Model'!A:E,5,0) -> AGYA 1.2 G CVT | N48: =IF($Q48="",0,_xlfn.DAYS($A$6,$Q48)+1) -> 6 | O48: =IF($N48=0,"0",IF(AND($N48>=1,$N48<=7),"1 Minggu",IF(AND($N48>=8,$N48<=14),"2 Minggu",IF(AND($N48>=15,$N48<=21),"3 Minggu",IF(AND($N48>=22,$N48<=28),"4 Minggu",IF($N48>=29,"> 4 Minggu",0)))))) -> 1 Minggu | P48: =IF($N48=0,"0",IF(AND($N48>=0,$N48<30),"<30D",IF(AND($N48>=30,$N48<=60),"30D-60D",IF($N48>60,">60D",0)))) -> <30D | Q48: 46239 | R48: PENDING LOAN | S48: MATCH MDP | AE48: ARIUS PUTRA JAYA GOHAE | AF48: ANDRI JAYA LAKSANA | AH48: WHITE | AJ48: PT. MANDIRI TUNAS FINANCE
C49: 44 | D49: Tunas Toyota | F49: Tunas Toyota Kiara Condong | G49: =VLOOKUP($F49,List!$D$5:$G$35,3,0) -> Area 1 | H49: =VLOOKUP($F49,List!$D$5:$G$35,4,0) -> Area 1 - West Java | I49: =J49&K49 -> B401RA-GMZFJ20 | J49: B401RA-GMZFJ | K49: 20 | L49: =VLOOKUP(I49,'List Model'!A:E,4,0) -> CALYA | M49: =VLOOKUP(I49,'List Model'!A:E,5,0) -> CALYA 1.2G M/T | N49: =IF($Q49="",0,_xlfn.DAYS($A$6,$Q49)+1) -> 6 | O49: =IF($N49=0,"0",IF(AND($N49>=1,$N49<=7),"1 Minggu",IF(AND($N49>=8,$N49<=14),"2 Minggu",IF(AND($N49>=15,$N49<=21),"3 Minggu",IF(AND($N49>=22,$N49<=28),"4 Minggu",IF($N49>=29,"> 4 Minggu",0)))))) -> 1 Minggu | P49: =IF($N49=0,"0",IF(AND($N49>=0,$N49<30),"<30D",IF(AND($N49>=30,$N49<=60),"30D-60D",IF($N49>60,">60D",0)))) -> <30D | Q49: 46239 | R49: PENDING LOAN | S49: MATCH MDP | AE49: DIKI ZAELANI | AF49: REGYAWAN KURNIA | AH49: WHITE
C50: 45 | D50: Tunas Toyota | F50: Tunas Toyota Kiara Condong | G50: =VLOOKUP($F50,List!$D$5:$G$35,3,0) -> Area 1 | H50: =VLOOKUP($F50,List!$D$5:$G$35,4,0) -> Area 1 - West Java | I50: =J50&K50 -> B401RA-GQZFJ20 | J50: B401RA-GQZFJ | K50: 20 | L50: =VLOOKUP(I50,'List Model'!A:E,4,0) -> CALYA | M50: =VLOOKUP(I50,'List Model'!A:E,5,0) -> CALYA 1.2G A/T | N50: =IF($Q50="",0,_xlfn.DAYS($A$6,$Q50)+1) -> 7 | O50: =IF($N50=0,"0",IF(AND($N50>=1,$N50<=7),"1 Minggu",IF(AND($N50>=8,$N50<=14),"2 Minggu",IF(AND($N50>=15,$N50<=21),"3 Minggu",IF(AND($N50>=22,$N50<=28),"4 Minggu",IF($N50>=29,"> 4 Minggu",0)))))) -> 1 Minggu | P50: =IF($N50=0,"0",IF(AND($N50>=0,$N50<30),"<30D",IF(AND($N50>=30,$N50<=60),"30D-60D",IF($N50>60,">60D",0)))) -> <30D | Q50: 46238 | R50: PENDING LOAN | S50: MATCH SUPPLY STOCK ON HAND | AE50: DAMAI LATIFAH WULANDINI | AF50: TOPIK HIDAYAT | AH50: BRONZE M.M. | AJ50: PT. MANDIRI TUNAS FINANCE
C51: 46 | D51: Tunas Toyota | F51: Tunas Toyota Kiara Condong | G51: =VLOOKUP($F51,List!$D$5:$G$35,3,0) -> Area 1 | H51: =VLOOKUP($F51,List!$D$5:$G$35,4,0) -> Area 1 - West Java | I51: =J51&K51 -> A250RA-GBVVJ31 | J51: A250RA-GBVVJ | K51: 31 | L51: =VLOOKUP(I51,'List Model'!A:E,4,0) -> RAIZE | M51: =VLOOKUP(I51,'List Model'!A:E,5,0) -> RAIZE 1.0T S CVT One Tone | N51: =IF($Q51="",0,_xlfn.DAYS($A$6,$Q51)+1) -> 7 | O51: =IF($N51=0,"0",IF(AND($N51>=1,$N51<=7),"1 Minggu",IF(AND($N51>=8,$N51<=14),"2 Minggu",IF(AND($N51>=15,$N51<=21),"3 Minggu",IF(AND($N51>=22,$N51<=28),"4 Minggu",IF($N51>=29,"> 4 Minggu",0)))))) -> 1 Minggu | P51: =IF($N51=0,"0",IF(AND($N51>=0,$N51<30),"<30D",IF(AND($N51>=30,$N51<=60),"30D-60D",IF($N51>60,">60D",0)))) -> <30D | Q51: 46238 | R51: PENDING LOAN | S51: MATCH MDP | AE51: VINA SINTIA | AF51: YENI | AH51: BLACK WHITE | AJ51: PT.TOYOTA ASTRA FINANCIAL SERVICES
C52: 47 | D52: Tunas Toyota | F52: Tunas Toyota Kiara Condong | G52: =VLOOKUP($F52,List!$D$5:$G$35,3,0) -> Area 1 | H52: =VLOOKUP($F52,List!$D$5:$G$35,4,0) -> Area 1 - West Java | I52: =J52&K52 -> W101RE-LMMFJ00 | J52: W101RE-LMMFJ | K52: 00 | L52: =VLOOKUP(I52,'List Model'!A:E,4,0) -> AVANZA NEW | M52: =VLOOKUP(I52,'List Model'!A:E,5,0) -> NEW AVANZA 1.5G M/T | N52: =IF($Q52="",0,_xlfn.DAYS($A$6,$Q52)+1) -> 7 | O52: =IF($N52=0,"0",IF(AND($N52>=1,$N52<=7),"1 Minggu",IF(AND($N52>=8,$N52<=14),"2 Minggu",IF(AND($N52>=15,$N52<=21),"3 Minggu",IF(AND($N52>=22,$N52<=28),"4 Minggu",IF($N52>=29,"> 4 Minggu",0)))))) -> 1 Minggu | P52: =IF($N52=0,"0",IF(AND($N52>=0,$N52<30),"<30D",IF(AND($N52>=30,$N52<=60),"30D-60D",IF($N52>60,">60D",0)))) -> <30D | Q52: 46238 | R52: PENDING LOAN | S52: MATCH MDP | AE52: SITI SONDARI | AF52: MUHAMMAD FADIL FAHMI RUSTANDI | AH52: WHITE | AJ52: PT. MANDIRI TUNAS FINANCE
C53: 48 | D53: Tunas Toyota | F53: Tunas Toyota Kiara Condong | G53: =VLOOKUP($F53,List!$D$5:$G$35,3,0) -> Area 1 | H53: =VLOOKUP($F53,List!$D$5:$G$35,4,0) -> Area 1 - West Java | I53: =J53&K53 -> W101RE-LBMFJ00 | J53: W101RE-LBMFJ | K53: 00 | L53: =VLOOKUP(I53,'List Model'!A:E,4,0) -> AVANZA NEW | M53: =VLOOKUP(I53,'List Model'!A:E,5,0) -> NEW AVANZA 1.5G CVT | N53: =IF($Q53="",0,_xlfn.DAYS($A$6,$Q53)+1) -> 7 | O53: =IF($N53=0,"0",IF(AND($N53>=1,$N53<=7),"1 Minggu",IF(AND($N53>=8,$N53<=14),"2 Minggu",IF(AND($N53>=15,$N53<=21),"3 Minggu",IF(AND($N53>=22,$N53<=28),"4 Minggu",IF($N53>=29,"> 4 Minggu",0)))))) -> 1 Minggu | P53: =IF($N53=0,"0",IF(AND($N53>=0,$N53<30),"<30D",IF(AND($N53>=30,$N53<=60),"30D-60D",IF($N53>60,">60D",0)))) -> <30D | Q53: 46238 | R53: PENDING LOAN | S53: MATCH MDP | AE53: TANTO BUDIMAN | AF53: REGYAWAN KURNIA | AH53: GRAY METALLIC
C54: 49 | D54: Tunas Toyota | F54: Tunas Toyota Kiara Condong | G54: =VLOOKUP($F54,List!$D$5:$G$35,3,0) -> Area 1 | H54: =VLOOKUP($F54,List!$D$5:$G$35,4,0) -> Area 1 - West Java | I54: =J54&K54 -> GUN142R-MDTSXD30 | J54: GUN142R-MDTSXD | K54: 30 | L54: =VLOOKUP(I54,'List Model'!A:E,4,0) -> INNOVA | M54: =VLOOKUP(I54,'List Model'!A:E,5,0) -> INNOVA 2.4G A/T | N54: =IF($Q54="",0,_xlfn.DAYS($A$6,$Q54)+1) -> 7 | O54: =IF($N54=0,"0",IF(AND($N54>=1,$N54<=7),"1 Minggu",IF(AND($N54>=8,$N54<=14),"2 Minggu",IF(AND($N54>=15,$N54<=21),"3 Minggu",IF(AND($N54>=22,$N54<=28),"4 Minggu",IF($N54>=29,"> 4 Minggu",0)))))) -> 1 Minggu | P54: =IF($N54=0,"0",IF(AND($N54>=0,$N54<30),"<30D",IF(AND($N54>=30,$N54<=60),"30D-60D",IF($N54>60,">60D",0)))) -> <30D | Q54: 46238 | R54: PENDING LOAN | S54: MATCH MDP | AE54: IWAN SUTARYO | AF54: DENO | AH54: ATTITUDE BLACK MICA
C55: 50 | D55: Tunas Toyota | F55: Tunas Toyota Kiara Condong | G55: =VLOOKUP($F55,List!$D$5:$G$35,3,0) -> Area 1 | H55: =VLOOKUP($F55,List!$D$5:$G$35,4,0) -> Area 1 - West Java | I55: =J55&K55 -> W101RE-LMMFJ00 | J55: W101RE-LMMFJ | K55: 00 | L55: =VLOOKUP(I55,'List Model'!A:E,4,0) -> AVANZA NEW | M55: =VLOOKUP(I55,'List Model'!A:E,5,0) -> NEW AVANZA 1.5G M/T | N55: =IF($Q55="",0,_xlfn.DAYS($A$6,$Q55)+1) -> 9 | O55: =IF($N55=0,"0",IF(AND($N55>=1,$N55<=7),"1 Minggu",IF(AND($N55>=8,$N55<=14),"2 Minggu",IF(AND($N55>=15,$N55<=21),"3 Minggu",IF(AND($N55>=22,$N55<=28),"4 Minggu",IF($N55>=29,"> 4 Minggu",0)))))) -> 2 Minggu | P55: =IF($N55=0,"0",IF(AND($N55>=0,$N55<30),"<30D",IF(AND($N55>=30,$N55<=60),"30D-60D",IF($N55>60,">60D",0)))) -> <30D | Q55: 46236 | R55: PENDING LOAN | S55: MATCH SUPPLY STOCK ON HAND | AE55: JUMAEIRI | AF55: DADI SOBARI | AH55: SILVER METALLIC | AJ55: PT.TOYOTA ASTRA FINANCIAL SERVICES
C56: 51 | D56: Tunas Toyota | F56: Tunas Toyota Kiara Condong | G56: =VLOOKUP($F56,List!$D$5:$G$35,3,0) -> Area 1 | H56: =VLOOKUP($F56,List!$D$5:$G$35,4,0) -> Area 1 - West Java | I56: =J56&K56 -> W102RE-LBVFJ08 | J56: W102RE-LBVFJ | K56: 08 | L56: =VLOOKUP(I56,'List Model'!A:E,4,0) -> VELOZ HYBRID | M56: =VLOOKUP(I56,'List Model'!A:E,5,0) -> VELOZ 1.5 Q HYBRID CVT-NON PREMIUM COLOR | N56: =IF($Q56="",0,_xlfn.DAYS($A$6,$Q56)+1) -> 10 | O56: =IF($N56=0,"0",IF(AND($N56>=1,$N56<=7),"1 Minggu",IF(AND($N56>=8,$N56<=14),"2 Minggu",IF(AND($N56>=15,$N56<=21),"3 Minggu",IF(AND($N56>=22,$N56<=28),"4 Minggu",IF($N56>=29,"> 4 Minggu",0)))))) -> 2 Minggu | P56: =IF($N56=0,"0",IF(AND($N56>=0,$N56<30),"<30D",IF(AND($N56>=30,$N56<=60),"30D-60D",IF($N56>60,">60D",0)))) -> <30D | Q56: 46235 | R56: PENDING LOAN | S56: MATCH MDP | AE56: PT SURYA SUDECO | AF56: REGYAWAN KURNIA | AH56: BLACK MICA
C57: 52 | D57: Tunas Toyota | F57: Tunas Toyota Kiara Condong | G57: =VLOOKUP($F57,List!$D$5:$G$35,3,0) -> Area 1 | H57: =VLOOKUP($F57,List!$D$5:$G$35,4,0) -> Area 1 - West Java | I57: =J57&K57 -> W102RE-LBVFJ08 | J57: W102RE-LBVFJ | K57: 08 | L57: =VLOOKUP(I57,'List Model'!A:E,4,0) -> VELOZ HYBRID | M57: =VLOOKUP(I57,'List Model'!A:E,5,0) -> VELOZ 1.5 Q HYBRID CVT-NON PREMIUM COLOR | N57: =IF($Q57="",0,_xlfn.DAYS($A$6,$Q57)+1) -> 10 | O57: =IF($N57=0,"0",IF(AND($N57>=1,$N57<=7),"1 Minggu",IF(AND($N57>=8,$N57<=14),"2 Minggu",IF(AND($N57>=15,$N57<=21),"3 Minggu",IF(AND($N57>=22,$N57<=28),"4 Minggu",IF($N57>=29,"> 4 Minggu",0)))))) -> 2 Minggu | P57: =IF($N57=0,"0",IF(AND($N57>=0,$N57<30),"<30D",IF(AND($N57>=30,$N57<=60),"30D-60D",IF($N57>60,">60D",0)))) -> <30D | Q57: 46235 | R57: PENDING LOAN | S57: MATCH MDP | AE57: PT SURYA SUDECO | AF57: REGYAWAN KURNIA | AH57: BLACK MICA
C58: 53 | D58: Tunas Toyota | F58: Tunas Toyota Kiara Condong | G58: =VLOOKUP($F58,List!$D$5:$G$35,3,0) -> Area 1 | H58: =VLOOKUP($F58,List!$D$5:$G$35,4,0) -> Area 1 - West Java | I58: =J58&K58 -> W101RE-LMMFJ00 | J58: W101RE-LMMFJ | K58: 00 | L58: =VLOOKUP(I58,'List Model'!A:E,4,0) -> AVANZA NEW | M58: =VLOOKUP(I58,'List Model'!A:E,5,0) -> NEW AVANZA 1.5G M/T | N58: =IF($Q58="",0,_xlfn.DAYS($A$6,$Q58)+1) -> 11 | O58: =IF($N58=0,"0",IF(AND($N58>=1,$N58<=7),"1 Minggu",IF(AND($N58>=8,$N58<=14),"2 Minggu",IF(AND($N58>=15,$N58<=21),"3 Minggu",IF(AND($N58>=22,$N58<=28),"4 Minggu",IF($N58>=29,"> 4 Minggu",0)))))) -> 2 Minggu | P58: =IF($N58=0,"0",IF(AND($N58>=0,$N58<30),"<30D",IF(AND($N58>=30,$N58<=60),"30D-60D",IF($N58>60,">60D",0)))) -> <30D | Q58: 46234 | R58: PENDING LOAN | S58: MATCH MDP | AE58: TETEN HERMAWAN | AF58: NURI LESTARI KRISTIANTY | AH58: BLACK MICA
C59: 54 | D59: Tunas Toyota | F59: Tunas Toyota Kiara Condong | G59: =VLOOKUP($F59,List!$D$5:$G$35,3,0) -> Area 1 | H59: =VLOOKUP($F59,List!$D$5:$G$35,4,0) -> Area 1 - West Java | I59: =J59&K59 -> W100RE-LMDFJ00 | J59: W100RE-LMDFJ | K59: 00 | L59: =VLOOKUP(I59,'List Model'!A:E,4,0) -> AVANZA NEW | M59: =VLOOKUP(I59,'List Model'!A:E,5,0) -> NEW AVANZA 1.3E M/T | N59: =IF($Q59="",0,_xlfn.DAYS($A$6,$Q59)+1) -> 19 | O59: =IF($N59=0,"0",IF(AND($N59>=1,$N59<=7),"1 Minggu",IF(AND($N59>=8,$N59<=14),"2 Minggu",IF(AND($N59>=15,$N59<=21),"3 Minggu",IF(AND($N59>=22,$N59<=28),"4 Minggu",IF($N59>=29,"> 4 Minggu",0)))))) -> 3 Minggu | P59: =IF($N59=0,"0",IF(AND($N59>=0,$N59<30),"<30D",IF(AND($N59>=30,$N59<=60),"30D-60D",IF($N59>60,">60D",0)))) -> <30D | Q59: 46226 | R59: PENDING LOAN | S59: MATCH SUPPLY STOCK ON HAND | AE59: FARHAN FAUZAN TAMIR | AF59: RIZKI RISMAWAN | AH59: GRAY METALLIC | AJ59: PT.TOYOTA ASTRA FINANCIAL SERVICES

Sheet Pvt OS
A1: OS ORDER | AO1: STOCK MATCHING | BM1: MATCH MDP/OH
A2: PL <30D | E2: FIRMED <30D | I2: FIRMED 30-600 | M2: FIRMED & MATCH 30-60D | Q2: FIRMED >60D | U2: FIRMED & MATCH >60D | Y2: UNFIRMED 30-60D | AC2: UNFIRMED & MATCH 30-60D | AG2: UNFIRMED >60D | AK2: UNFIRMED & MATCH >60D | AO2: UNFIRMED & MATCH <30D | AS2: FIRMED & MATCH <30D | AW2: UNFIRMED & UNMATCH <30D | BA2: FIRMED & UNMATCH <30D | BE2: FIRMED & UNMATCH >30D | BI2: UNFIRMED & UNMATCH >30D | BM2: FIRMED & MATCH STOCK | BP2: PL & MATCH STOCK <30D
A3: Month | B3: (ALL) | E3: Month | F3: (ALL) | I3: Month | J3: (ALL) | M3: Month | N3: (ALL) | Q3: Month | R3: (ALL) | U3: Month | V3: (ALL) | Y3: Month | Z3: (ALL) | AC3: Month | AD3: (ALL) | AG3: Month | AH3: (ALL) | AK3: Month | AL3: (ALL) | AO3: Month | AP3: (ALL) | AS3: Month | AT3: (ALL) | AW3: Month | AX3: (ALL) | BA3: Month | BB3: (ALL) | BE3: Month | BF3: (ALL) | BI3: Month | BJ3: (ALL)
A4: OS Category | B4: <30D | E4: OS Category | F4: <30D | I4: OS Category | J4: (blank) | M4: OS Category | N4: (blank) | Q4: OS Category | R4: (Multiple Items) | U4: OS Category | V4: >60D | Y4: OS Category | Z4: 30D-60D | AC4: OS Category | AD4: 30D-60D | AG4: OS Category | AH4: >60D | AK4: OS Category | AL4: >60D | AO4: OS Category | AP4: <30D | AS4: OS Category | AT4: <30D | AW4: OS Category | AX4: <30D | BA4: OS Category | BB4: <30D | BE4: OS Category | BF4: (Multiple Items) | BI4: OS Category | BJ4: (Multiple Items) | BM4: Month | BN4: (ALL) | BP4: Month | BQ4: (ALL)
A5: Status SPK | B5: (Multiple Items) | E5: Status SPK | F5: FIRMED | I5: Status SPK | J5: FIRMED | M5: Status SPK | N5: FIRMED | Q5: Status SPK | R5: FIRMED | U5: Status SPK | V5: FIRMED | Y5: Status SPK | Z5: (Multiple Items) | AC5: Status SPK | AD5: (Multiple Items) | AG5: Status SPK | AH5: (Multiple Items) | AK5: Status SPK | AL5: (Multiple Items) | AO5: Status SPK | AP5: (Multiple Items) | AS5: Status SPK | AT5: FIRMED | AW5: Status SPK | AX5: (Multiple Items) | BA5: Status SPK | BB5: FIRMED | BE5: Status SPK | BF5: FIRMED | BI5: Status SPK | BJ5: (Multiple Items) | BM5: OS Category | BN5: (ALL) | BP5: OS Category | BQ5: <30D
A6: Status Supply | B6: (ALL) | E6: Status Supply | F6: (ALL) | I6: Status Supply | J6: (ALL) | M6: Status Supply | N6: (Multiple Items) | Q6: Status Supply | R6: (ALL) | U6: Status Supply | V6: (Multiple Items) | Y6: Status Supply | Z6: (ALL) | AC6: Status Supply | AD6: (Multiple Items) | AG6: Status Supply | AH6: (ALL) | AK6: Status Supply | AL6: (Multiple Items) | AO6: Status Supply | AP6: (Multiple Items) | AS6: Status Supply | AT6: (Multiple Items) | AW6: Status Supply | AX6: UNMATCH | BA6: Status Supply | BB6: UNMATCH | BE6: Status Supply | BF6: UNMATCH | BI6: Status Supply | BJ6: UNMATCH | BM6: Status SPK | BN6: FIRMED | BP6: Status SPK | BQ6: (Multiple Items)
A8: Dealer | B8: Model | C8: Count of Area AGM | E8: Dealer | F8: Model | G8: Count of Area AGM | I8: Dealer | J8: Model | K8: Count of Area AGM | M8: Dealer | N8: Model | O8: Count of Area AGM | Q8: Dealer | R8: Model | S8: Count of Area AGM | U8: Dealer | V8: Model | W8: Count of Area AGM | Y8: Dealer | Z8: Model | AA8: Count of Area AGM | AC8: Dealer | AD8: Model | AE8: Count of Area AGM | AG8: Dealer | AH8: Model | AI8: Count of Area AGM | AK8: Dealer | AL8: Model | AM8: Count of Area AGM | AO8: Dealer | AP8: Model | AQ8: Count of Area AGM | AS8: Dealer | AT8: Model | AU8: Count of Area AGM | AW8: Dealer | AX8: Model | AY8: Count of Area AGM | BA8: Dealer | BB8: Model | BC8: Count of Area AGM | BE8: Dealer | BF8: Model | BG8: Count of Area AGM | BI8: Dealer | BJ8: Model | BK8: Count of Area AGM | BM8: Status Supply | BN8: Count of Area AGM | BP8: Status Supply | BQ8: Count of Area AGM
A9: Tunas Toyota | B9: AGYA | C9: 3 | E9: Tunas Toyota | F9: CALYA | G9: 1 | I9: Grand Total | M9: Grand Total | Q9: Grand Total | U9: Grand Total | Y9: Tunas Toyota | Z9: HILUX D-CAB | AA9: 1 | AC9: Grand Total | AG9: Tunas Toyota | AH9: YARIS CROSS GASOLINE | AI9: 1 | AK9: Grand Total | AO9: Tunas Toyota | AP9: AGYA | AQ9: 3 | AS9: Tunas Toyota | AT9: CALYA | AU9: 1 | AW9: Tunas Toyota | AX9: CALYA | AY9: 1 | BA9: Grand Total | BE9: Grand Total | BI9: Tunas Toyota | BJ9: HILUX D-CAB | BK9: 1 | BM9: MATCH SUPPLY STOCK ON HAND | BN9: 3 | BP9: MATCH SUPPLY STOCK ON HAND | BQ9: 13
A10: Tunas Toyota | B10: CALYA | C10: 8 | E10: Tunas Toyota | F10: INNOVA ZENIX HYBRID | G10: 1 | Y10: Tunas Toyota | Z10: INNOVA ZENIX HYBRID | AA10: 1 | AG10: Tunas Toyota Total | AI10: 1 | AO10: Tunas Toyota | AP10: CALYA | AQ10: 7 | AS10: Tunas Toyota | AT10: INNOVA ZENIX HYBRID | AU10: 1 | AW10: Tunas Toyota | AX10: INNOVA | AY10: 1 | BI10: Tunas Toyota | BJ10: INNOVA ZENIX HYBRID | BK10: 1 | BM10: MATCH MDP | BN10: 15 | BP10: MATCH MDP | BQ10: 11
A11: Tunas Toyota | B11: INNOVA | C11: 3 | E11: Tunas Toyota | F11: FORTUNER 4X2 | G11: 1 | Y11: Tunas Toyota | Z11: HIACE | AA11: 2 | AG11: Grand Total | AI11: 1 | AO11: Tunas Toyota | AP11: INNOVA | AQ11: 2 | AS11: Tunas Toyota | AT11: FORTUNER 4X2 | AU11: 1 | AW11: Tunas Toyota | AX11: HIACE | AY11: 1 | BI11: Tunas Toyota | BJ11: HIACE | BK11: 2 | BM11: Grand Total | BN11: 18 | BP11: Grand Total | BQ11: 24
A12: Tunas Toyota | B12: AVANZA NEW | C12: 7 | E12: Tunas Toyota | F12: VELOZ HYBRID | G12: 15 | Y12: Tunas Toyota Total | AA12: 4 | AO12: Tunas Toyota | AP12: AVANZA NEW | AQ12: 8 | AS12: Tunas Toyota | AT12: VELOZ HYBRID | AU12: 15 | AW12: Tunas Toyota | AX12: FORTUNER 4X2 | AY12: 1 | BI12: Tunas Toyota | BJ12: YARIS CROSS GASOLINE | BK12: 1
A13: Tunas Toyota | B13: RAIZE | C13: 1 | E13: Tunas Toyota Total | G13: 18 | Y13: Grand Total | AA13: 4 | AO13: Tunas Toyota | AP13: RAIZE | AQ13: 1 | AS13: Tunas Toyota Total | AU13: 18 | AW13: Tunas Toyota | AX13: HIACE PREMIO | AY13: 1 | BI13: Tunas Toyota Total | BK13: 5
A14: Tunas Toyota | B14: HIACE | C14: 1 | E14: Grand Total | G14: 18 | AO14: Tunas Toyota | AP14: INNOVA ZENIX | AQ14: 1 | AS14: Grand Total | AU14: 18 | AW14: Tunas Toyota | AX14: AGYA GR-S | AY14: 1 | BI14: Grand Total | BK14: 5
A15: Tunas Toyota | B15: FORTUNER 4X2 | C15: 1 | AO15: Tunas Toyota | AP15: VELOZ HYBRID | AQ15: 2 | AW15: Tunas Toyota | AX15: HILUX S-CAB | AY15: 1
A16: Tunas Toyota | B16: HIACE PREMIO | C16: 1 | AO16: Tunas Toyota Total | AQ16: 24 | AW16: Tunas Toyota Total | AY16: 7
A17: Tunas Toyota | B17: INNOVA ZENIX | C17: 1 | AO17: Grand Total | AQ17: 24 | AW17: Grand Total | AY17: 7
A18: Tunas Toyota | B18: AGYA GR-S | C18: 1
A19: Tunas Toyota | B19: HILUX S-CAB | C19: 1
A20: Tunas Toyota | B20: VELOZ HYBRID | C20: 2
A21: Tunas Toyota Total | C21: 30
A22: Grand Total | C22: 30

Sheet Aging
B2: 1 Minggu | C2: =IFERROR(GETPIVOTDATA("Area AGM",$E$8,"Umur Outstansing","1 Minggu"),0) -> 12 | E2: UNFIRMED & MATCH <30D
B3: 2 Minggu | C3: =IFERROR(GETPIVOTDATA("Area AGM",$E$8,"Umur Outstansing","2 Minggu"),0) -> 5 | E3: Month | F3: (ALL)
B4: 3 Minggu | C4: =IFERROR(GETPIVOTDATA("Area AGM",$E$8,"Umur Outstansing","3 Minggu"),0) -> 5 | E4: OS Category | F4: <30D
B5: 4 Minggu | C5: =IFERROR(GETPIVOTDATA("Area AGM",$E$8,"Umur Outstansing","4 Minggu"),0) -> 1 | E5: Status SPK | F5: PENDING LOAN
E6: Status Supply | F6: (Multiple Items)
E8: Umur Outstansing | F8: Count of Area AGM
E9: 3 Minggu | F9: 5
E10: 4 Minggu | F10: 1
E11: 2 Minggu | F11: 5
E12: 1 Minggu | F12: 12
E13: Grand Total | F13: 23

Sheet Reason Unmatch
A1: Gap from OS | B1: Match & Unfirmed (PL + CPI) | G1: Unmatch to Stock
B2: TOTAL | C2: 1 Minggu | D2: 2 Minggu | E2: 3 Minggu | F2: 4 Minggu | G2: TOTAL | H2: Firmed | I2: P.Loan | J2: UNMATCH | L2: UNFIRMED & MATCH <30D | T2: UNMATCH & FIRMED | W2: UNMATCH & PL
A3: Avanza New | B3: =SUM(C3:F3) -> 8 | C3: =IF(IFERROR(GETPIVOTDATA("Area AGM",$L$8,"Model",""&$A3&"","Umur Outstansing",""&C$2&""),0)=0,"",IFERROR(GETPIVOTDATA("Area AGM",$L$8,"Model",""&$A3&"","Umur Outstansing",""&C$2&""),0)) -> 2 | D3: =IF(IFERROR(GETPIVOTDATA("Area AGM",$L$8,"Model",""&$A3&"","Umur Outstansing",""&D$2&""),0)=0,"",IFERROR(GETPIVOTDATA("Area AGM",$L$8,"Model",""&$A3&"","Umur Outstansing",""&D$2&""),0)) -> 2 | E3: =IF(IFERROR(GETPIVOTDATA("Area AGM",$L$8,"Model",""&$A3&"","Umur Outstansing",""&E$2&""),0)=0,"",IFERROR(GETPIVOTDATA("Area AGM",$L$8,"Model",""&$A3&"","Umur Outstansing",""&E$2&""),0)) -> 3 | F3: =IF(IFERROR(GETPIVOTDATA("Area AGM",$L$8,"Model",""&$A3&"","Umur Outstansing",""&F$2&""),0)=0,"",IFERROR(GETPIVOTDATA("Area AGM",$L$8,"Model",""&$A3&"","Umur Outstansing",""&F$2&""),0)) -> 1 | G3: =SUM(H3:I3) -> 0 | H3: =IFERROR(VLOOKUP(A3,$T$7:$U$77,2,0),0) -> 0 | I3: =IFERROR(VLOOKUP(A3,$W$7:$X$78,2,0),0) -> 0 | L3: Month | M3: (ALL) | T3: Month | U3: (ALL) | W3: Month | X3: (ALL)
A4: Veloz Hybrid | B4: =SUM(C4:F4) -> 2 | C4: =IF(IFERROR(GETPIVOTDATA("Area AGM",$L$8,"Model",""&$A4&"","Umur Outstansing",""&C$2&""),0)=0,"",IFERROR(GETPIVOTDATA("Area AGM",$L$8,"Model",""&$A4&"","Umur Outstansing",""&C$2&""),0)) | D4: =IF(IFERROR(GETPIVOTDATA("Area AGM",$L$8,"Model",""&$A4&"","Umur Outstansing",""&D$2&""),0)=0,"",IFERROR(GETPIVOTDATA("Area AGM",$L$8,"Model",""&$A4&"","Umur Outstansing",""&D$2&""),0)) -> 2 | E4: =IF(IFERROR(GETPIVOTDATA("Area AGM",$L$8,"Model",""&$A4&"","Umur Outstansing",""&E$2&""),0)=0,"",IFERROR(GETPIVOTDATA("Area AGM",$L$8,"Model",""&$A4&"","Umur Outstansing",""&E$2&""),0)) | F4: =IF(IFERROR(GETPIVOTDATA("Area AGM",$L$8,"Model",""&$A4&"","Umur Outstansing",""&F$2&""),0)=0,"",IFERROR(GETPIVOTDATA("Area AGM",$L$8,"Model",""&$A4&"","Umur Outstansing",""&F$2&""),0)) | G4: =SUM(H4:I4) -> 0 | H4: =IFERROR(VLOOKUP(A4,$T$7:$U$77,2,0),0) -> 0 | I4: =IFERROR(VLOOKUP(A4,$W$7:$X$78,2,0),0) -> 0 | L4: OS Category | M4: (Multiple Items) | T4: OS Category | U4: (ALL) | W4: OS Category | X4: (ALL)
A5: Raize | B5: =SUM(C5:F5) -> 1 | C5: =IF(IFERROR(GETPIVOTDATA("Area AGM",$L$8,"Model",""&$A5&"","Umur Outstansing",""&C$2&""),0)=0,"",IFERROR(GETPIVOTDATA("Area AGM",$L$8,"Model",""&$A5&"","Umur Outstansing",""&C$2&""),0)) -> 1 | D5: =IF(IFERROR(GETPIVOTDATA("Area AGM",$L$8,"Model",""&$A5&"","Umur Outstansing",""&D$2&""),0)=0,"",IFERROR(GETPIVOTDATA("Area AGM",$L$8,"Model",""&$A5&"","Umur Outstansing",""&D$2&""),0)) | E5: =IF(IFERROR(GETPIVOTDATA("Area AGM",$L$8,"Model",""&$A5&"","Umur Outstansing",""&E$2&""),0)=0,"",IFERROR(GETPIVOTDATA("Area AGM",$L$8,"Model",""&$A5&"","Umur Outstansing",""&E$2&""),0)) | F5: =IF(IFERROR(GETPIVOTDATA("Area AGM",$L$8,"Model",""&$A5&"","Umur Outstansing",""&F$2&""),0)=0,"",IFERROR(GETPIVOTDATA("Area AGM",$L$8,"Model",""&$A5&"","Umur Outstansing",""&F$2&""),0)) | G5: =SUM(H5:I5) -> 0 | H5: =IFERROR(VLOOKUP(A5,$T$7:$U$77,2,0),0) -> 0 | I5: =IFERROR(VLOOKUP(A5,$W$7:$X$78,2,0),0) -> 0 | L5: Status SPK | M5: (Multiple Items) | T5: Status SPK | U5: FIRMED | W5: Status SPK | X5: (Multiple Items)
A6: Agya | B6: =SUM(C6:F6) -> 3 | C6: =IF(IFERROR(GETPIVOTDATA("Area AGM",$L$8,"Model",""&$A6&"","Umur Outstansing",""&C$2&""),0)=0,"",IFERROR(GETPIVOTDATA("Area AGM",$L$8,"Model",""&$A6&"","Umur Outstansing",""&C$2&""),0)) -> 2 | D6: =IF(IFERROR(GETPIVOTDATA("Area AGM",$L$8,"Model",""&$A6&"","Umur Outstansing",""&D$2&""),0)=0,"",IFERROR(GETPIVOTDATA("Area AGM",$L$8,"Model",""&$A6&"","Umur Outstansing",""&D$2&""),0)) -> 1 | E6: =IF(IFERROR(GETPIVOTDATA("Area AGM",$L$8,"Model",""&$A6&"","Umur Outstansing",""&E$2&""),0)=0,"",IFERROR(GETPIVOTDATA("Area AGM",$L$8,"Model",""&$A6&"","Umur Outstansing",""&E$2&""),0)) | F6: =IF(IFERROR(GETPIVOTDATA("Area AGM",$L$8,"Model",""&$A6&"","Umur Outstansing",""&F$2&""),0)=0,"",IFERROR(GETPIVOTDATA("Area AGM",$L$8,"Model",""&$A6&"","Umur Outstansing",""&F$2&""),0)) | G6: =SUM(H6:I6) -> 0 | H6: =IFERROR(VLOOKUP(A6,$T$7:$U$77,2,0),0) -> 0 | I6: =IFERROR(VLOOKUP(A6,$W$7:$X$78,2,0),0) -> 0 | L6: Status Supply | M6: (Multiple Items) | T6: Status Supply | U6: UNMATCH | W6: Status Supply | X6: UNMATCH
A7: Agya GR-S | B7: =SUM(C7:F7) -> 0 | C7: =IF(IFERROR(GETPIVOTDATA("Area AGM",$L$8,"Model",""&$A7&"","Umur Outstansing",""&C$2&""),0)=0,"",IFERROR(GETPIVOTDATA("Area AGM",$L$8,"Model",""&$A7&"","Umur Outstansing",""&C$2&""),0)) | D7: =IF(IFERROR(GETPIVOTDATA("Area AGM",$L$8,"Model",""&$A7&"","Umur Outstansing",""&D$2&""),0)=0,"",IFERROR(GETPIVOTDATA("Area AGM",$L$8,"Model",""&$A7&"","Umur Outstansing",""&D$2&""),0)) | E7: =IF(IFERROR(GETPIVOTDATA("Area AGM",$L$8,"Model",""&$A7&"","Umur Outstansing",""&E$2&""),0)=0,"",IFERROR(GETPIVOTDATA("Area AGM",$L$8,"Model",""&$A7&"","Umur Outstansing",""&E$2&""),0)) | F7: =IF(IFERROR(GETPIVOTDATA("Area AGM",$L$8,"Model",""&$A7&"","Umur Outstansing",""&F$2&""),0)=0,"",IFERROR(GETPIVOTDATA("Area AGM",$L$8,"Model",""&$A7&"","Umur Outstansing",""&F$2&""),0)) | G7: =SUM(H7:I7) -> 1 | H7: =IFERROR(VLOOKUP(A7,$T$7:$U$77,2,0),0) -> 0 | I7: =IFERROR(VLOOKUP(A7,$W$7:$X$78,2,0),0) -> 1
A8: Calya | B8: =SUM(C8:F8) -> 7 | C8: =IF(IFERROR(GETPIVOTDATA("Area AGM",$L$8,"Model",""&$A8&"","Umur Outstansing",""&C$2&""),0)=0,"",IFERROR(GETPIVOTDATA("Area AGM",$L$8,"Model",""&$A8&"","Umur Outstansing",""&C$2&""),0)) -> 5 | D8: =IF(IFERROR(GETPIVOTDATA("Area AGM",$L$8,"Model",""&$A8&"","Umur Outstansing",""&D$2&""),0)=0,"",IFERROR(GETPIVOTDATA("Area AGM",$L$8,"Model",""&$A8&"","Umur Outstansing",""&D$2&""),0)) | E8: =IF(IFERROR(GETPIVOTDATA("Area AGM",$L$8,"Model",""&$A8&"","Umur Outstansing",""&E$2&""),0)=0,"",IFERROR(GETPIVOTDATA("Area AGM",$L$8,"Model",""&$A8&"","Umur Outstansing",""&E$2&""),0)) -> 2 | F8: =IF(IFERROR(GETPIVOTDATA("Area AGM",$L$8,"Model",""&$A8&"","Umur Outstansing",""&F$2&""),0)=0,"",IFERROR(GETPIVOTDATA("Area AGM",$L$8,"Model",""&$A8&"","Umur Outstansing",""&F$2&""),0)) | G8: =SUM(H8:I8) -> 1 | H8: =IFERROR(VLOOKUP(A8,$T$7:$U$77,2,0),0) -> 0 | I8: =IFERROR(VLOOKUP(A8,$W$7:$X$78,2,0),0) -> 1 | L8: Count of Area AGM | M8: Umur Outstansing | T8: Model | U8: Count of Area AGM | W8: Model | X8: Count of Area AGM
A9: Yaris | B9: =SUM(C9:F9) -> 0 | C9: =IF(IFERROR(GETPIVOTDATA("Area AGM",$L$8,"Model",""&$A9&"","Umur Outstansing",""&C$2&""),0)=0,"",IFERROR(GETPIVOTDATA("Area AGM",$L$8,"Model",""&$A9&"","Umur Outstansing",""&C$2&""),0)) | D9: =IF(IFERROR(GETPIVOTDATA("Area AGM",$L$8,"Model",""&$A9&"","Umur Outstansing",""&D$2&""),0)=0,"",IFERROR(GETPIVOTDATA("Area AGM",$L$8,"Model",""&$A9&"","Umur Outstansing",""&D$2&""),0)) | E9: =IF(IFERROR(GETPIVOTDATA("Area AGM",$L$8,"Model",""&$A9&"","Umur Outstansing",""&E$2&""),0)=0,"",IFERROR(GETPIVOTDATA("Area AGM",$L$8,"Model",""&$A9&"","Umur Outstansing",""&E$2&""),0)) | F9: =IF(IFERROR(GETPIVOTDATA("Area AGM",$L$8,"Model",""&$A9&"","Umur Outstansing",""&F$2&""),0)=0,"",IFERROR(GETPIVOTDATA("Area AGM",$L$8,"Model",""&$A9&"","Umur Outstansing",""&F$2&""),0)) | G9: =SUM(H9:I9) -> 0 | H9: =IFERROR(VLOOKUP(A9,$T$7:$U$77,2,0),0) -> 0 | I9: =IFERROR(VLOOKUP(A9,$W$7:$X$78,2,0),0) -> 0 | L9: Model | M9: 3 Minggu | N9: 4 Minggu | O9: 2 Minggu | P9: 1 Minggu | Q9: Grand Total | T9: Grand Total | W9: CALYA | X9: 1
A10: Yaris Cross Gasoline | B10: =SUM(C10:F10) -> 0 | C10: =IF(IFERROR(GETPIVOTDATA("Area AGM",$L$8,"Model",""&$A10&"","Umur Outstansing",""&C$2&""),0)=0,"",IFERROR(GETPIVOTDATA("Area AGM",$L$8,"Model",""&$A10&"","Umur Outstansing",""&C$2&""),0)) | D10: =IF(IFERROR(GETPIVOTDATA("Area AGM",$L$8,"Model",""&$A10&"","Umur Outstansing",""&D$2&""),0)=0,"",IFERROR(GETPIVOTDATA("Area AGM",$L$8,"Model",""&$A10&"","Umur Outstansing",""&D$2&""),0)) | E10: =IF(IFERROR(GETPIVOTDATA("Area AGM",$L$8,"Model",""&$A10&"","Umur Outstansing",""&E$2&""),0)=0,"",IFERROR(GETPIVOTDATA("Area AGM",$L$8,"Model",""&$A10&"","Umur Outstansing",""&E$2&""),0)) | F10: =IF(IFERROR(GETPIVOTDATA("Area AGM",$L$8,"Model",""&$A10&"","Umur Outstansing",""&F$2&""),0)=0,"",IFERROR(GETPIVOTDATA("Area AGM",$L$8,"Model",""&$A10&"","Umur Outstansing",""&F$2&""),0)) | G10: =SUM(H10:I10) -> 1 | H10: =IFERROR(VLOOKUP(A10,$T$7:$U$77,2,0),0) -> 0 | I10: =IFERROR(VLOOKUP(A10,$W$7:$X$78,2,0),0) -> 1 | L10: AGYA | O10: 1 | P10: 2 | Q10: 3 | W10: FORTUNER 4X2 | X10: 1
A11: Yaris Cross Hybrid | B11: =SUM(C11:F11) -> 0 | C11: =IF(IFERROR(GETPIVOTDATA("Area AGM",$L$8,"Model",""&$A11&"","Umur Outstansing",""&C$2&""),0)=0,"",IFERROR(GETPIVOTDATA("Area AGM",$L$8,"Model",""&$A11&"","Umur Outstansing",""&C$2&""),0)) | D11: =IF(IFERROR(GETPIVOTDATA("Area AGM",$L$8,"Model",""&$A11&"","Umur Outstansing",""&D$2&""),0)=0,"",IFERROR(GETPIVOTDATA("Area AGM",$L$8,"Model",""&$A11&"","Umur Outstansing",""&D$2&""),0)) | E11: =IF(IFERROR(GETPIVOTDATA("Area AGM",$L$8,"Model",""&$A11&"","Umur Outstansing",""&E$2&""),0)=0,"",IFERROR(GETPIVOTDATA("Area AGM",$L$8,"Model",""&$A11&"","Umur Outstansing",""&E$2&""),0)) | F11: =IF(IFERROR(GETPIVOTDATA("Area AGM",$L$8,"Model",""&$A11&"","Umur Outstansing",""&F$2&""),0)=0,"",IFERROR(GETPIVOTDATA("Area AGM",$L$8,"Model",""&$A11&"","Umur Outstansing",""&F$2&""),0)) | G11: =SUM(H11:I11) -> 0 | H11: =IFERROR(VLOOKUP(A11,$T$7:$U$77,2,0),0) -> 0 | I11: =IFERROR(VLOOKUP(A11,$W$7:$X$78,2,0),0) -> 0 | L11: CALYA | M11: 2 | P11: 5 | Q11: 7 | W11: HIACE | X11: 3
A12: Innova | B12: =SUM(C12:F12) -> 2 | C12: =IF(IFERROR(GETPIVOTDATA("Area AGM",$L$8,"Model",""&$A12&"","Umur Outstansing",""&C$2&""),0)=0,"",IFERROR(GETPIVOTDATA("Area AGM",$L$8,"Model",""&$A12&"","Umur Outstansing",""&C$2&""),0)) -> 2 | D12: =IF(IFERROR(GETPIVOTDATA("Area AGM",$L$8,"Model",""&$A12&"","Umur Outstansing",""&D$2&""),0)=0,"",IFERROR(GETPIVOTDATA("Area AGM",$L$8,"Model",""&$A12&"","Umur Outstansing",""&D$2&""),0)) | E12: =IF(IFERROR(GETPIVOTDATA("Area AGM",$L$8,"Model",""&$A12&"","Umur Outstansing",""&E$2&""),0)=0,"",IFERROR(GETPIVOTDATA("Area AGM",$L$8,"Model",""&$A12&"","Umur Outstansing",""&E$2&""),0)) | F12: =IF(IFERROR(GETPIVOTDATA("Area AGM",$L$8,"Model",""&$A12&"","Umur Outstansing",""&F$2&""),0)=0,"",IFERROR(GETPIVOTDATA("Area AGM",$L$8,"Model",""&$A12&"","Umur Outstansing",""&F$2&""),0)) | G12: =SUM(H12:I12) -> 1 | H12: =IFERROR(VLOOKUP(A12,$T$7:$U$77,2,0),0) -> 0 | I12: =IFERROR(VLOOKUP(A12,$W$7:$X$78,2,0),0) -> 1 | L12: INNOVA | P12: 2 | Q12: 2 | W12: HILUX D-CAB | X12: 1
A13: Innova Zenix Hybrid | B13: =SUM(C13:F13) -> 0 | C13: =IF(IFERROR(GETPIVOTDATA("Area AGM",$L$8,"Model",""&$A13&"","Umur Outstansing",""&C$2&""),0)=0,"",IFERROR(GETPIVOTDATA("Area AGM",$L$8,"Model",""&$A13&"","Umur Outstansing",""&C$2&""),0)) | D13: =IF(IFERROR(GETPIVOTDATA("Area AGM",$L$8,"Model",""&$A13&"","Umur Outstansing",""&D$2&""),0)=0,"",IFERROR(GETPIVOTDATA("Area AGM",$L$8,"Model",""&$A13&"","Umur Outstansing",""&D$2&""),0)) | E13: =IF(IFERROR(GETPIVOTDATA("Area AGM",$L$8,"Model",""&$A13&"","Umur Outstansing",""&E$2&""),0)=0,"",IFERROR(GETPIVOTDATA("Area AGM",$L$8,"Model",""&$A13&"","Umur Outstansing",""&E$2&""),0)) | F13: =IF(IFERROR(GETPIVOTDATA("Area AGM",$L$8,"Model",""&$A13&"","Umur Outstansing",""&F$2&""),0)=0,"",IFERROR(GETPIVOTDATA("Area AGM",$L$8,"Model",""&$A13&"","Umur Outstansing",""&F$2&""),0)) | G13: =SUM(H13:I13) -> 1 | H13: =IFERROR(VLOOKUP(A13,$T$7:$U$77,2,0),0) -> 0 | I13: =IFERROR(VLOOKUP(A13,$W$7:$X$78,2,0),0) -> 1 | L13: AVANZA NEW | M13: 3 | N13: 1 | O13: 2 | P13: 2 | Q13: 8 | W13: INNOVA | X13: 1
